Workbook

Sheet Calculation
W1: AFS Days | X1: Shipment Plan Days | AC1: Bunch Qty | AF1: to ship
W2: 30 | X2: 40 | AC2: 2 | AF2: =SUM(AF4:AF833) -> 3148
A3: Group Name | B3: SKU | C3: Title | D3: Category | E3: Int – WH | F3: Dec – WH | G3: Non Apron Qty | H3: APR- Sky Blue | I3: APR- Dark Blue | J3: APR- Brown | K3: APR- Green | L3: APR- Tan | M3: APR- Black | N3: APR- Red | O3: APR- Grey | P3: weight | Q3: Total Weight | S3: HSN | T3: GST | U3: COST | V3: SKU | W3: Title | X3: Tra. Qty | Y3: quantity | Z3: Available Qty | AA3: Fulfilment ID | AB3: Sale-Total | AC3: Sale-WH | AD3: Ship – WH | AE3: Sum | AF3: Final – WH
A4: APR- Black | B4: Apron_Black | C4: CRASOME Polyester Kitchen Apron for Men Women Chef Cooking Restaurants gardening workshop barbers With Pockets and Adjustable Strap ( Black ) | D4: Apron | E4: =IF(ISNUMBER(AD4),IF(AD4>=0,IF(AD4=0,1,INT(AD4/$AC$2)),""),"") | F4: =IF(E4="","",IF(AD4=0,0,AD4/$AC$2-E4)) | G4: =IF(ISERROR(SEARCH("Apron",D4)),AF4,"") | M4: =IF(ISNUMBER($AF4),1*$AF4,"") | P4: {=XLOOKUP(B4,Weight!B:B,Weight!D:D,"#N/A",0)} -> 140 | Q4: =IF(AF4="","",AF4*P4) | S4: 392620 | T4: 12 | U4: 60 | V4: =B4 -> Apron_Black | W4: =C4 -> CRASOME Polyester Kitchen Apron for Men Women Chef Cooking Restaurants gardening workshop barbers With Pockets and Adjustable Strap ( Black ) | X4: =SUMIFS('Transit Shipment'!$B$10:$B$1048462,'Transit Shipment'!$A$10:$A$1048462,B4,'Transit Shipment'!$C$10:$C$1048462,AA4) -> 0 | Y4: =IF(SUMIFS(DIH!$S$2:$S833,DIH!$D$2:$D833,B4,DIH!$U$2:$U833,AA4)>0,SUMIFS(DIH!$S$2:$S833,DIH!$D$2:$D833,B4,DIH!$U$2:$U833,AA4),0) -> 2 | Z4: =SUM(X4:Y4) -> 2 | AA4: AMD2 | AB4: =IF(ISNA(VLOOKUP($B4,'Business Report'!$D$2:$J$202,2,0)),"",VLOOKUP($B4,'Business Report'!$D$2:$J$202,2,0)) -> 117 | AC4: =SUMIFS(AFS!$P$2:$P$6260,AFS!$N$2:$N$6260,B4,AFS!$AT$2:$AT$6260,AA4) -> 0 | AD4: =CEILING(AC4/$W$2*$X$2,1)-sum(X4:Y4) -> -2 | AF4: =IF(ISNUMBER(AD4),IF(AD4<=0,"",IF(F4="","",E4*$AC$2+IF(F4>0,$AC$2,0))))
A5: APR- Black | B5: Apron_Black | C5: CRASOME Polyester Kitchen Apron for Men Women Chef Cooking Restaurants gardening workshop barbers With Pockets and Adjustable Strap ( Black ) | D5: Apron | E5: =IF(ISNUMBER(AD5),IF(AD5>=0,IF(AD5=0,1,INT(AD5/$AC$2)),""),"") -> 0 | F5: =IF(E5="","",IF(AD5=0,0,AD5/$AC$2-E5)) -> 0.5 | G5: =IF(ISERROR(SEARCH("Apron",D5)),AF5,"") | M5: =IF(ISNUMBER($AF5),1*$AF5,"") -> 2 | P5: {=XLOOKUP(B5,Weight!B:B,Weight!D:D,"#N/A",0)} -> 140 | Q5: =IF(AF5="","",AF5*P5) -> 280 | S5: 392620 | T5: 12 | U5: 60 | X5: =SUMIFS('Transit Shipment'!$B$10:$B$1048462,'Transit Shipment'!$A$10:$A$1048462,B5,'Transit Shipment'!$C$10:$C$1048462,AA5) -> 0 | Y5: =IF(SUMIFS(DIH!$S$2:$S833,DIH!$D$2:$D833,B5,DIH!$U$2:$U833,AA5)>0,SUMIFS(DIH!$S$2:$S833,DIH!$D$2:$D833,B5,DIH!$U$2:$U833,AA5),0) -> 7 | Z5: =SUM(X5:Y5) -> 7 | AA5: BLR8 | AB5: =IF(ISNA(VLOOKUP($B5,'Business Report'!$D$2:$J$202,2,0)),"",VLOOKUP($B5,'Business Report'!$D$2:$J$202,2,0)) -> 117 | AC5: =SUMIFS(AFS!$P$2:$P$6260,AFS!$N$2:$N$6260,B5,AFS!$AT$2:$AT$6260,AA5) -> 6 | AD5: =CEILING(AC5/$W$2*$X$2,1)-sum(X5:Y5) -> 1 | AF5: =IF(ISNUMBER(AD5),IF(AD5<=0,"",IF(F5="","",E5*$AC$2+IF(F5>0,$AC$2,0)))) -> 2
A6: APR- Black | B6: Apron_Black | C6: CRASOME Polyester Kitchen Apron for Men Women Chef Cooking Restaurants gardening workshop barbers With Pockets and Adjustable Strap ( Black ) | D6: Apron | E6: =IF(ISNUMBER(AD6),IF(AD6>=0,IF(AD6=0,1,INT(AD6/$AC$2)),""),"") -> 2 | F6: =IF(E6="","",IF(AD6=0,0,AD6/$AC$2-E6)) -> 0.5 | G6: =IF(ISERROR(SEARCH("Apron",D6)),AF6,"") | M6: =IF(ISNUMBER($AF6),1*$AF6,"") -> 6 | P6: {=XLOOKUP(B6,Weight!B:B,Weight!D:D,"#N/A",0)} -> 140 | Q6: =IF(AF6="","",AF6*P6) -> 840 | S6: 392620 | T6: 12 | U6: 60 | X6: =SUMIFS('Transit Shipment'!$B$10:$B$1048462,'Transit Shipment'!$A$10:$A$1048462,B6,'Transit Shipment'!$C$10:$C$1048462,AA6) -> 0 | Y6: =IF(SUMIFS(DIH!$S$2:$S833,DIH!$D$2:$D833,B6,DIH!$U$2:$U833,AA6)>0,SUMIFS(DIH!$S$2:$S833,DIH!$D$2:$D833,B6,DIH!$U$2:$U833,AA6),0) -> 2 | Z6: =SUM(X6:Y6) -> 2 | AA6: BLR7 | AB6: =IF(ISNA(VLOOKUP($B6,'Business Report'!$D$2:$J$202,2,0)),"",VLOOKUP($B6,'Business Report'!$D$2:$J$202,2,0)) -> 117 | AC6: =SUMIFS(AFS!$P$2:$P$6260,AFS!$N$2:$N$6260,B6,AFS!$AT$2:$AT$6260,AA6) -> 5 | AD6: =CEILING(AC6/$W$2*$X$2,1)-sum(X6:Y6) -> 5 | AF6: =IF(ISNUMBER(AD6),IF(AD6<=0,"",IF(F6="","",E6*$AC$2+IF(F6>0,$AC$2,0)))) -> 6
A7: APR- Black | B7: Apron_Black | C7: CRASOME Polyester Kitchen Apron for Men Women Chef Cooking Restaurants gardening workshop barbers With Pockets and Adjustable Strap ( Black ) | D7: Apron | E7: =IF(ISNUMBER(AD7),IF(AD7>=0,IF(AD7=0,1,INT(AD7/$AC$2)),""),"") -> 0 | F7: =IF(E7="","",IF(AD7=0,0,AD7/$AC$2-E7)) -> 0.5 | G7: =IF(ISERROR(SEARCH("Apron",D7)),AF7,"") | M7: =IF(ISNUMBER($AF7),1*$AF7,"") -> 2 | P7: {=XLOOKUP(B7,Weight!B:B,Weight!D:D,"#N/A",0)} -> 140 | Q7: =IF(AF7="","",AF7*P7) -> 280 | S7: 392620 | T7: 12 | U7: 60 | X7: =SUMIFS('Transit Shipment'!$B$10:$B$1048462,'Transit Shipment'!$A$10:$A$1048462,B7,'Transit Shipment'!$C$10:$C$1048462,AA7) -> 0 | Y7: =IF(SUMIFS(DIH!$S$2:$S833,DIH!$D$2:$D833,B7,DIH!$U$2:$U833,AA7)>0,SUMIFS(DIH!$S$2:$S833,DIH!$D$2:$D833,B7,DIH!$U$2:$U833,AA7),0) -> 1 | Z7: =SUM(X7:Y7) -> 1 | AA7: CJB1 | AB7: =IF(ISNA(VLOOKUP($B7,'Business Report'!$D$2:$J$202,2,0)),"",VLOOKUP($B7,'Business Report'!$D$2:$J$202,2,0)) -> 117 | AC7: =SUMIFS(AFS!$P$2:$P$6260,AFS!$N$2:$N$6260,B7,AFS!$AT$2:$AT$6260,AA7) -> 1 | AD7: =CEILING(AC7/$W$2*$X$2,1)-sum(X7:Y7) -> 1 | AF7: =IF(ISNUMBER(AD7),IF(AD7<=0,"",IF(F7="","",E7*$AC$2+IF(F7>0,$AC$2,0)))) -> 2
A8: APR- Black | B8: Apron_Black | C8: CRASOME Polyester Kitchen Apron for Men Women Chef Cooking Restaurants gardening workshop barbers With Pockets and Adjustable Strap ( Black ) | D8: Apron | E8: =IF(ISNUMBER(AD8),IF(AD8>=0,IF(AD8=0,1,INT(AD8/$AC$2)),""),"") -> 1 | F8: =IF(E8="","",IF(AD8=0,0,AD8/$AC$2-E8)) -> 0.5 | G8: =IF(ISERROR(SEARCH("Apron",D8)),AF8,"") | M8: =IF(ISNUMBER($AF8),1*$AF8,"") -> 4 | P8: {=XLOOKUP(B8,Weight!B:B,Weight!D:D,"#N/A",0)} -> 140 | Q8: =IF(AF8="","",AF8*P8) -> 560 | S8: 392620 | T8: 12 | U8: 60 | X8: =SUMIFS('Transit Shipment'!$B$10:$B$1048462,'Transit Shipment'!$A$10:$A$1048462,B8,'Transit Shipment'!$C$10:$C$1048462,AA8) -> 0 | Y8: =IF(SUMIFS(DIH!$S$2:$S833,DIH!$D$2:$D833,B8,DIH!$U$2:$U833,AA8)>0,SUMIFS(DIH!$S$2:$S833,DIH!$D$2:$D833,B8,DIH!$U$2:$U833,AA8),0) -> 1 | Z8: =SUM(X8:Y8) -> 1 | AA8: MAA4 | AB8: =IF(ISNA(VLOOKUP($B8,'Business Report'!$D$2:$J$202,2,0)),"",VLOOKUP($B8,'Business Report'!$D$2:$J$202,2,0)) -> 117 | AC8: =SUMIFS(AFS!$P$2:$P$6260,AFS!$N$2:$N$6260,B8,AFS!$AT$2:$AT$6260,AA8) -> 3 | AD8: =CEILING(AC8/$W$2*$X$2,1)-sum(X8:Y8) -> 3 | AF8: =IF(ISNUMBER(AD8),IF(AD8<=0,"",IF(F8="","",E8*$AC$2+IF(F8>0,$AC$2,0)))) -> 4
A9: APR- Black | B9: Apron_Black | C9: CRASOME Polyester Kitchen Apron for Men Women Chef Cooking Restaurants gardening workshop barbers With Pockets and Adjustable Strap ( Black ) | D9: Apron | E9: =IF(ISNUMBER(AD9),IF(AD9>=0,IF(AD9=0,1,INT(AD9/$AC$2)),""),"") -> 2 | F9: =IF(E9="","",IF(AD9=0,0,AD9/$AC$2-E9)) -> 0.5 | G9: =IF(ISERROR(SEARCH("Apron",D9)),AF9,"") | M9: =IF(ISNUMBER($AF9),1*$AF9,"") -> 6 | P9: {=XLOOKUP(B9,Weight!B:B,Weight!D:D,"#N/A",0)} -> 140 | Q9: =IF(AF9="","",AF9*P9) -> 840 | S9: 392620 | T9: 12 | U9: 60 | X9: =SUMIFS('Transit Shipment'!$B$10:$B$1048462,'Transit Shipment'!$A$10:$A$1048462,B9,'Transit Shipment'!$C$10:$C$1048462,AA9) -> 0 | Y9: =IF(SUMIFS(DIH!$S$2:$S833,DIH!$D$2:$D833,B9,DIH!$U$2:$U833,AA9)>0,SUMIFS(DIH!$S$2:$S833,DIH!$D$2:$D833,B9,DIH!$U$2:$U833,AA9),0) -> 1 | Z9: =SUM(X9:Y9) -> 1 | AA9: DEL4 | AB9: =IF(ISNA(VLOOKUP($B9,'Business Report'!$D$2:$J$202,2,0)),"",VLOOKUP($B9,'Business Report'!$D$2:$J$202,2,0)) -> 117 | AC9: =SUMIFS(AFS!$P$2:$P$6260,AFS!$N$2:$N$6260,B9,AFS!$AT$2:$AT$6260,AA9) -> 4 | AD9: =CEILING(AC9/$W$2*$X$2,1)-sum(X9:Y9) -> 5 | AF9: =IF(ISNUMBER(AD9),IF(AD9<=0,"",IF(F9="","",E9*$AC$2+IF(F9>0,$AC$2,0)))) -> 6
A10: APR- Black | B10: Apron_Black | C10: CRASOME Polyester Kitchen Apron for Men Women Chef Cooking Restaurants gardening workshop barbers With Pockets and Adjustable Strap ( Black ) | D10: Apron | E10: =IF(ISNUMBER(AD10),IF(AD10>=0,IF(AD10=0,1,INT(AD10/$AC$2)),""),"") | F10: =IF(E10="","",IF(AD10=0,0,AD10/$AC$2-E10)) | G10: =IF(ISERROR(SEARCH("Apron",D10)),AF10,"") | M10: =IF(ISNUMBER($AF10),1*$AF10,"") | P10: {=XLOOKUP(B10,Weight!B:B,Weight!D:D,"#N/A",0)} -> 140 | Q10: =IF(AF10="","",AF10*P10) | S10: 392620 | T10: 12 | U10: 60 | X10: =SUMIFS('Transit Shipment'!$B$10:$B$1048462,'Transit Shipment'!$A$10:$A$1048462,B10,'Transit Shipment'!$C$10:$C$1048462,AA10) -> 0 | Y10: =IF(SUMIFS(DIH!$S$2:$S833,DIH!$D$2:$D833,B10,DIH!$U$2:$U833,AA10)>0,SUMIFS(DIH!$S$2:$S833,DIH!$D$2:$D833,B10,DIH!$U$2:$U833,AA10),0) -> 4 | Z10: =SUM(X10:Y10) -> 4 | AA10: DEL5 | AB10: =IF(ISNA(VLOOKUP($B10,'Business Report'!$D$2:$J$202,2,0)),"",VLOOKUP($B10,'Business Report'!$D$2:$J$202,2,0)) -> 117 | AC10: =SUMIFS(AFS!$P$2:$P$6260,AFS!$N$2:$N$6260,B10,AFS!$AT$2:$AT$6260,AA10) -> 2 | AD10: =CEILING(AC10/$W$2*$X$2,1)-sum(X10:Y10) -> -1 | AF10: =IF(ISNUMBER(AD10),IF(AD10<=0,"",IF(F10="","",E10*$AC$2+IF(F10>0,$AC$2,0))))
A11: APR- Black | B11: Apron_Black | C11: CRASOME Polyester Kitchen Apron for Men Women Chef Cooking Restaurants gardening workshop barbers With Pockets and Adjustable Strap ( Black ) | D11: Apron | E11: =IF(ISNUMBER(AD11),IF(AD11>=0,IF(AD11=0,1,INT(AD11/$AC$2)),""),"") -> 3 | F11: =IF(E11="","",IF(AD11=0,0,AD11/$AC$2-E11)) -> 0.5 | G11: =IF(ISERROR(SEARCH("Apron",D11)),AF11,"") | M11: =IF(ISNUMBER($AF11),1*$AF11,"") -> 8 | P11: {=XLOOKUP(B11,Weight!B:B,Weight!D:D,"#N/A",0)} -> 140 | Q11: =IF(AF11="","",AF11*P11) -> 1120 | S11: 392620 | T11: 12 | U11: 60 | X11: =SUMIFS('Transit Shipment'!$B$10:$B$1048462,'Transit Shipment'!$A$10:$A$1048462,B11,'Transit Shipment'!$C$10:$C$1048462,AA11) -> 0 | Y11: =IF(SUMIFS(DIH!$S$2:$S833,DIH!$D$2:$D833,B11,DIH!$U$2:$U833,AA11)>0,SUMIFS(DIH!$S$2:$S833,DIH!$D$2:$D833,B11,DIH!$U$2:$U833,AA11),0) -> 5 | Z11: =SUM(X11:Y11) -> 5 | AA11: BOM5 | AB11: =IF(ISNA(VLOOKUP($B11,'Business Report'!$D$2:$J$202,2,0)),"",VLOOKUP($B11,'Business Report'!$D$2:$J$202,2,0)) -> 117 | AC11: =SUMIFS(AFS!$P$2:$P$6260,AFS!$N$2:$N$6260,B11,AFS!$AT$2:$AT$6260,AA11) -> 9 | AD11: =CEILING(AC11/$W$2*$X$2,1)-sum(X11:Y11) -> 7 | AF11: =IF(ISNUMBER(AD11),IF(AD11<=0,"",IF(F11="","",E11*$AC$2+IF(F11>0,$AC$2,0)))) -> 8
A12: APR- Black | B12: Apron_Black | C12: CRASOME Polyester Kitchen Apron for Men Women Chef Cooking Restaurants gardening workshop barbers With Pockets and Adjustable Strap ( Black ) | D12: Apron | E12: =IF(ISNUMBER(AD12),IF(AD12>=0,IF(AD12=0,1,INT(AD12/$AC$2)),""),"") -> 1 | F12: =IF(E12="","",IF(AD12=0,0,AD12/$AC$2-E12)) -> 0 | G12: =IF(ISERROR(SEARCH("Apron",D12)),AF12,"") | M12: =IF(ISNUMBER($AF12),1*$AF12,"") | P12: {=XLOOKUP(B12,Weight!B:B,Weight!D:D,"#N/A",0)} -> 140 | Q12: =IF(AF12="","",AF12*P12) | S12: 392620 | T12: 12 | U12: 60 | X12: =SUMIFS('Transit Shipment'!$B$10:$B$1048462,'Transit Shipment'!$A$10:$A$1048462,B12,'Transit Shipment'!$C$10:$C$1048462,AA12) -> 0 | Y12: =IF(SUMIFS(DIH!$S$2:$S833,DIH!$D$2:$D833,B12,DIH!$U$2:$U833,AA12)>0,SUMIFS(DIH!$S$2:$S833,DIH!$D$2:$D833,B12,DIH!$U$2:$U833,AA12),0) -> 0 | Z12: =SUM(X12:Y12) -> 0 | AA12: BOM7 | AB12: =IF(ISNA(VLOOKUP($B12,'Business Report'!$D$2:$J$202,2,0)),"",VLOOKUP($B12,'Business Report'!$D$2:$J$202,2,0)) -> 117 | AC12: =SUMIFS(AFS!$P$2:$P$6260,AFS!$N$2:$N$6260,B12,AFS!$AT$2:$AT$6260,AA12) -> 0 | AD12: =CEILING(AC12/$W$2*$X$2,1)-sum(X12:Y12) -> 0 | AE12: =SUM(AD4:AD12) -> 19 | AF12: =IF(ISNUMBER(AD12),IF(AD12<=0,"",IF(F12="","",E12*$AC$2+IF(F12>0,$AC$2,0))))
A13: APR- Dark Blue | B13: Apron_Blue | C13: CRASOME Polyester Kitchen Apron for Men Women Chef Cooking Restaurants gardening workshop barbers With Pockets and Adjustable Strap (Blue) | D13: Apron | E13: =IF(ISNUMBER(AD13),IF(AD13>=0,IF(AD13=0,1,INT(AD13/$AC$2)),""),"") | F13: =IF(E13="","",IF(AD13=0,0,AD13/$AC$2-E13)) | G13: =IF(ISERROR(SEARCH("Apron",D13)),AF13,"") | I13: =IF(ISNUMBER($AF13),1*$AF13,"") | P13: {=XLOOKUP(B13,Weight!B:B,Weight!D:D,"#N/A",0)} -> 140 | Q13: =IF(AF13="","",AF13*P13) | S13: 392620 | T13: 12 | U13: 60 | V13: =B13 -> Apron_Blue | W13: =C13 -> CRASOME Polyester Kitchen Apron for Men Women Chef Cooking Restaurants gardening workshop barbers With Pockets and Adjustable Strap (Blue) | X13: =SUMIFS('Transit Shipment'!$B$10:$B$1048462,'Transit Shipment'!$A$10:$A$1048462,B13,'Transit Shipment'!$C$10:$C$1048462,AA13) -> 0 | Y13: =IF(SUMIFS(DIH!$S$2:$S833,DIH!$D$2:$D833,B13,DIH!$U$2:$U833,AA13)>0,SUMIFS(DIH!$S$2:$S833,DIH!$D$2:$D833,B13,DIH!$U$2:$U833,AA13),0) -> 3 | Z13: =SUM(X13:Y13) -> 3 | AA13: AMD2 | AB13: =IF(ISNA(VLOOKUP($B13,'Business Report'!$D$2:$J$202,2,0)),"",VLOOKUP($B13,'Business Report'!$D$2:$J$202,2,0)) -> 15 | AC13: =SUMIFS(AFS!$P$2:$P$6260,AFS!$N$2:$N$6260,B13,AFS!$AT$2:$AT$6260,AA13) -> 1 | AD13: =CEILING(AC13/$W$2*$X$2,1)-sum(X13:Y13) -> -1 | AF13: =IF(ISNUMBER(AD13),IF(AD13<=0,"",IF(F13="","",E13*$AC$2+IF(F13>0,$AC$2,0)))) | AI13: =IF(ISNUMBER(AG13),IF(AG13<=0,"",IF(I13="","",H13*$AC$2+IF(I13>0,$AC$2,0)))) -> FALSE
A14: APR- Dark Blue | B14: Apron_Blue | C14: CRASOME Polyester Kitchen Apron for Men Women Chef Cooking Restaurants gardening workshop barbers With Pockets and Adjustable Strap (Blue) | D14: Apron | E14: =IF(ISNUMBER(AD14),IF(AD14>=0,IF(AD14=0,1,INT(AD14/$AC$2)),""),"") -> 8 | F14: =IF(E14="","",IF(AD14=0,0,AD14/$AC$2-E14)) -> 0 | G14: =IF(ISERROR(SEARCH("Apron",D14)),AF14,"") | I14: =IF(ISNUMBER($AF14),1*$AF14,"") -> 16 | P14: {=XLOOKUP(B14,Weight!B:B,Weight!D:D,"#N/A",0)} -> 140 | Q14: =IF(AF14="","",AF14*P14) -> 2240 | S14: 392620 | T14: 12 | U14: 60 | X14: =SUMIFS('Transit Shipment'!$B$10:$B$1048462,'Transit Shipment'!$A$10:$A$1048462,B14,'Transit Shipment'!$C$10:$C$1048462,AA14) -> 0 | Y14: =IF(SUMIFS(DIH!$S$2:$S833,DIH!$D$2:$D833,B14,DIH!$U$2:$U833,AA14)>0,SUMIFS(DIH!$S$2:$S833,DIH!$D$2:$D833,B14,DIH!$U$2:$U833,AA14),0) -> 0 | Z14: =SUM(X14:Y14) -> 0 | AA14: BLR8 | AB14: =IF(ISNA(VLOOKUP($B14,'Business Report'!$D$2:$J$202,2,0)),"",VLOOKUP($B14,'Business Report'!$D$2:$J$202,2,0)) -> 15 | AC14: =SUMIFS(AFS!$P$2:$P$6260,AFS!$N$2:$N$6260,B14,AFS!$AT$2:$AT$6260,AA14) -> 12 | AD14: =CEILING(AC14/$W$2*$X$2,1)-sum(X14:Y14) -> 16 | AF14: =IF(ISNUMBER(AD14),IF(AD14<=0,"",IF(F14="","",E14*$AC$2+IF(F14>0,$AC$2,0)))) -> 16 | AI14: =IF(ISNUMBER(AG14),IF(AG14<=0,"",IF(I14="","",H14*$AC$2+IF(I14>0,$AC$2,0)))) -> FALSE
A15: APR- Dark Blue | B15: Apron_Blue | C15: CRASOME Polyester Kitchen Apron for Men Women Chef Cooking Restaurants gardening workshop barbers With Pockets and Adjustable Strap (Blue) | D15: Apron | E15: =IF(ISNUMBER(AD15),IF(AD15>=0,IF(AD15=0,1,INT(AD15/$AC$2)),""),"") -> 2 | F15: =IF(E15="","",IF(AD15=0,0,AD15/$AC$2-E15)) -> 0.5 | G15: =IF(ISERROR(SEARCH("Apron",D15)),AF15,"") | I15: =IF(ISNUMBER($AF15),1*$AF15,"") -> 6 | P15: {=XLOOKUP(B15,Weight!B:B,Weight!D:D,"#N/A",0)} -> 140 | Q15: =IF(AF15="","",AF15*P15) -> 840 | S15: 392620 | T15: 12 | U15: 60 | X15: =SUMIFS('Transit Shipment'!$B$10:$B$1048462,'Transit Shipment'!$A$10:$A$1048462,B15,'Transit Shipment'!$C$10:$C$1048462,AA15) -> 0 | Y15: =IF(SUMIFS(DIH!$S$2:$S833,DIH!$D$2:$D833,B15,DIH!$U$2:$U833,AA15)>0,SUMIFS(DIH!$S$2:$S833,DIH!$D$2:$D833,B15,DIH!$U$2:$U833,AA15),0) -> 2 | Z15: =SUM(X15:Y15) -> 2 | AA15: BLR7 | AB15: =IF(ISNA(VLOOKUP($B15,'Business Report'!$D$2:$J$202,2,0)),"",VLOOKUP($B15,'Business Report'!$D$2:$J$202,2,0)) -> 15 | AC15: =SUMIFS(AFS!$P$2:$P$6260,AFS!$N$2:$N$6260,B15,AFS!$AT$2:$AT$6260,AA15) -> 5 | AD15: =CEILING(AC15/$W$2*$X$2,1)-sum(X15:Y15) -> 5 | AF15: =IF(ISNUMBER(AD15),IF(AD15<=0,"",IF(F15="","",E15*$AC$2+IF(F15>0,$AC$2,0)))) -> 6 | AI15: =IF(ISNUMBER(AG15),IF(AG15<=0,"",IF(I15="","",H15*$AC$2+IF(I15>0,$AC$2,0)))) -> FALSE
A16: APR- Dark Blue | B16: Apron_Blue | C16: CRASOME Polyester Kitchen Apron for Men Women Chef Cooking Restaurants gardening workshop barbers With Pockets and Adjustable Strap (Blue) | D16: Apron | E16: =IF(ISNUMBER(AD16),IF(AD16>=0,IF(AD16=0,1,INT(AD16/$AC$2)),""),"") -> 1 | F16: =IF(E16="","",IF(AD16=0,0,AD16/$AC$2-E16)) -> 0.5 | G16: =IF(ISERROR(SEARCH("Apron",D16)),AF16,"") | I16: =IF(ISNUMBER($AF16),1*$AF16,"") -> 4 | P16: {=XLOOKUP(B16,Weight!B:B,Weight!D:D,"#N/A",0)} -> 140 | Q16: =IF(AF16="","",AF16*P16) -> 560 | S16: 392620 | T16: 12 | U16: 60 | X16: =SUMIFS('Transit Shipment'!$B$10:$B$1048462,'Transit Shipment'!$A$10:$A$1048462,B16,'Transit Shipment'!$C$10:$C$1048462,AA16) -> 0 | Y16: =IF(SUMIFS(DIH!$S$2:$S833,DIH!$D$2:$D833,B16,DIH!$U$2:$U833,AA16)>0,SUMIFS(DIH!$S$2:$S833,DIH!$D$2:$D833,B16,DIH!$U$2:$U833,AA16),0) -> 1 | Z16: =SUM(X16:Y16) -> 1 | AA16: CJB1 | AB16: =IF(ISNA(VLOOKUP($B16,'Business Report'!$D$2:$J$202,2,0)),"",VLOOKUP($B16,'Business Report'!$D$2:$J$202,2,0)) -> 15 | AC16: =SUMIFS(AFS!$P$2:$P$6260,AFS!$N$2:$N$6260,B16,AFS!$AT$2:$AT$6260,AA16) -> 3 | AD16: =CEILING(AC16/$W$2*$X$2,1)-sum(X16:Y16) -> 3 | AF16: =IF(ISNUMBER(AD16),IF(AD16<=0,"",IF(F16="","",E16*$AC$2+IF(F16>0,$AC$2,0)))) -> 4 | AI16: =IF(ISNUMBER(AG16),IF(AG16<=0,"",IF(I16="","",H16*$AC$2+IF(I16>0,$AC$2,0)))) -> FALSE
A17: APR- Dark Blue | B17: Apron_Blue | C17: CRASOME Polyester Kitchen Apron for Men Women Chef Cooking Restaurants gardening workshop barbers With Pockets and Adjustable Strap (Blue) | D17: Apron | E17: =IF(ISNUMBER(AD17),IF(AD17>=0,IF(AD17=0,1,INT(AD17/$AC$2)),""),"") -> 4 | F17: =IF(E17="","",IF(AD17=0,0,AD17/$AC$2-E17)) -> 0.5 | G17: =IF(ISERROR(SEARCH("Apron",D17)),AF17,"") | I17: =IF(ISNUMBER($AF17),1*$AF17,"") -> 10 | P17: {=XLOOKUP(B17,Weight!B:B,Weight!D:D,"#N/A",0)} -> 140 | Q17: =IF(AF17="","",AF17*P17) -> 1400 | S17: 392620 | T17: 12 | U17: 60 | X17: =SUMIFS('Transit Shipment'!$B$10:$B$1048462,'Transit Shipment'!$A$10:$A$1048462,B17,'Transit Shipment'!$C$10:$C$1048462,AA17) -> 0 | Y17: =IF(SUMIFS(DIH!$S$2:$S833,DIH!$D$2:$D833,B17,DIH!$U$2:$U833,AA17)>0,SUMIFS(DIH!$S$2:$S833,DIH!$D$2:$D833,B17,DIH!$U$2:$U833,AA17),0) -> 1 | Z17: =SUM(X17:Y17) -> 1 | AA17: MAA4 | AB17: =IF(ISNA(VLOOKUP($B17,'Business Report'!$D$2:$J$202,2,0)),"",VLOOKUP($B17,'Business Report'!$D$2:$J$202,2,0)) -> 15 | AC17: =SUMIFS(AFS!$P$2:$P$6260,AFS!$N$2:$N$6260,B17,AFS!$AT$2:$AT$6260,AA17) -> 7 | AD17: =CEILING(AC17/$W$2*$X$2,1)-sum(X17:Y17) -> 9 | AF17: =IF(ISNUMBER(AD17),IF(AD17<=0,"",IF(F17="","",E17*$AC$2+IF(F17>0,$AC$2,0)))) -> 10 | AI17: =IF(ISNUMBER(AG17),IF(AG17<=0,"",IF(I17="","",H17*$AC$2+IF(I17>0,$AC$2,0)))) -> FALSE
A18: APR- Dark Blue | B18: Apron_Blue | C18: CRASOME Polyester Kitchen Apron for Men Women Chef Cooking Restaurants gardening workshop barbers With Pockets and Adjustable Strap (Blue) | D18: Apron | E18: =IF(ISNUMBER(AD18),IF(AD18>=0,IF(AD18=0,1,INT(AD18/$AC$2)),""),"") -> 1 | F18: =IF(E18="","",IF(AD18=0,0,AD18/$AC$2-E18)) -> 0 | G18: =IF(ISERROR(SEARCH("Apron",D18)),AF18,"") | I18: =IF(ISNUMBER($AF18),1*$AF18,"") | P18: {=XLOOKUP(B18,Weight!B:B,Weight!D:D,"#N/A",0)} -> 140 | Q18: =IF(AF18="","",AF18*P18) | S18: 392620 | T18: 12 | U18: 60 | X18: =SUMIFS('Transit Shipment'!$B$10:$B$1048462,'Transit Shipment'!$A$10:$A$1048462,B18,'Transit Shipment'!$C$10:$C$1048462,AA18) -> 0 | Y18: =IF(SUMIFS(DIH!$S$2:$S833,DIH!$D$2:$D833,B18,DIH!$U$2:$U833,AA18)>0,SUMIFS(DIH!$S$2:$S833,DIH!$D$2:$D833,B18,DIH!$U$2:$U833,AA18),0) -> 2 | Z18: =SUM(X18:Y18) -> 2 | AA18: DEL4 | AB18: =IF(ISNA(VLOOKUP($B18,'Business Report'!$D$2:$J$202,2,0)),"",VLOOKUP($B18,'Business Report'!$D$2:$J$202,2,0)) -> 15 | AC18: =SUMIFS(AFS!$P$2:$P$6260,AFS!$N$2:$N$6260,B18,AFS!$AT$2:$AT$6260,AA18) -> 1 | AD18: =CEILING(AC18/$W$2*$X$2,1)-sum(X18:Y18) -> 0 | AF18: =IF(ISNUMBER(AD18),IF(AD18<=0,"",IF(F18="","",E18*$AC$2+IF(F18>0,$AC$2,0)))) | AI18: =IF(ISNUMBER(AG18),IF(AG18<=0,"",IF(I18="","",H18*$AC$2+IF(I18>0,$AC$2,0)))) -> FALSE
A19: APR- Dark Blue | B19: Apron_Blue | C19: CRASOME Polyester Kitchen Apron for Men Women Chef Cooking Restaurants gardening workshop barbers With Pockets and Adjustable Strap (Blue) | D19: Apron | E19: =IF(ISNUMBER(AD19),IF(AD19>=0,IF(AD19=0,1,INT(AD19/$AC$2)),""),"") -> 3 | F19: =IF(E19="","",IF(AD19=0,0,AD19/$AC$2-E19)) -> 0 | G19: =IF(ISERROR(SEARCH("Apron",D19)),AF19,"") | I19: =IF(ISNUMBER($AF19),1*$AF19,"") -> 6 | P19: {=XLOOKUP(B19,Weight!B:B,Weight!D:D,"#N/A",0)} -> 140 | Q19: =IF(AF19="","",AF19*P19) -> 840 | S19: 392620 | T19: 12 | U19: 60 | X19: =SUMIFS('Transit Shipment'!$B$10:$B$1048462,'Transit Shipment'!$A$10:$A$1048462,B19,'Transit Shipment'!$C$10:$C$1048462,AA19) -> 0 | Y19: =IF(SUMIFS(DIH!$S$2:$S833,DIH!$D$2:$D833,B19,DIH!$U$2:$U833,AA19)>0,SUMIFS(DIH!$S$2:$S833,DIH!$D$2:$D833,B19,DIH!$U$2:$U833,AA19),0) -> 2 | Z19: =SUM(X19:Y19) -> 2 | AA19: DEL5 | AB19: =IF(ISNA(VLOOKUP($B19,'Business Report'!$D$2:$J$202,2,0)),"",VLOOKUP($B19,'Business Report'!$D$2:$J$202,2,0)) -> 15 | AC19: =SUMIFS(AFS!$P$2:$P$6260,AFS!$N$2:$N$6260,B19,AFS!$AT$2:$AT$6260,AA19) -> 6 | AD19: =CEILING(AC19/$W$2*$X$2,1)-sum(X19:Y19) -> 6 | AF19: =IF(ISNUMBER(AD19),IF(AD19<=0,"",IF(F19="","",E19*$AC$2+IF(F19>0,$AC$2,0)))) -> 6 | AI19: =IF(ISNUMBER(AG19),IF(AG19<=0,"",IF(I19="","",H19*$AC$2+IF(I19>0,$AC$2,0)))) -> FALSE
A20: APR- Dark Blue | B20: Apron_Blue | C20: CRASOME Polyester Kitchen Apron for Men Women Chef Cooking Restaurants gardening workshop barbers With Pockets and Adjustable Strap (Blue) | D20: Apron | E20: =IF(ISNUMBER(AD20),IF(AD20>=0,IF(AD20=0,1,INT(AD20/$AC$2)),""),"") -> 1 | F20: =IF(E20="","",IF(AD20=0,0,AD20/$AC$2-E20)) -> 0 | G20: =IF(ISERROR(SEARCH("Apron",D20)),AF20,"") | I20: =IF(ISNUMBER($AF20),1*$AF20,"") | P20: {=XLOOKUP(B20,Weight!B:B,Weight!D:D,"#N/A",0)} -> 140 | Q20: =IF(AF20="","",AF20*P20) | S20: 392620 | T20: 12 | U20: 60 | X20: =SUMIFS('Transit Shipment'!$B$10:$B$1048462,'Transit Shipment'!$A$10:$A$1048462,B20,'Transit Shipment'!$C$10:$C$1048462,AA20) -> 0 | Y20: =IF(SUMIFS(DIH!$S$2:$S833,DIH!$D$2:$D833,B20,DIH!$U$2:$U833,AA20)>0,SUMIFS(DIH!$S$2:$S833,DIH!$D$2:$D833,B20,DIH!$U$2:$U833,AA20),0) -> 7 | Z20: =SUM(X20:Y20) -> 7 | AA20: BOM5 | AB20: =IF(ISNA(VLOOKUP($B20,'Business Report'!$D$2:$J$202,2,0)),"",VLOOKUP($B20,'Business Report'!$D$2:$J$202,2,0)) -> 15 | AC20: =SUMIFS(AFS!$P$2:$P$6260,AFS!$N$2:$N$6260,B20,AFS!$AT$2:$AT$6260,AA20) -> 5 | AD20: =CEILING(AC20/$W$2*$X$2,1)-sum(X20:Y20) -> 0 | AF20: =IF(ISNUMBER(AD20),IF(AD20<=0,"",IF(F20="","",E20*$AC$2+IF(F20>0,$AC$2,0)))) | AI20: =IF(ISNUMBER(AG20),IF(AG20<=0,"",IF(I20="","",H20*$AC$2+IF(I20>0,$AC$2,0)))) -> FALSE
A21: APR- Dark Blue | B21: Apron_Blue | C21: CRASOME Polyester Kitchen Apron for Men Women Chef Cooking Restaurants gardening workshop barbers With Pockets and Adjustable Strap (Blue) | D21: Apron | E21: =IF(ISNUMBER(AD21),IF(AD21>=0,IF(AD21=0,1,INT(AD21/$AC$2)),""),"") -> 1 | F21: =IF(E21="","",IF(AD21=0,0,AD21/$AC$2-E21)) -> 0 | G21: =IF(ISERROR(SEARCH("Apron",D21)),AF21,"") | I21: =IF(ISNUMBER($AF21),1*$AF21,"") | P21: {=XLOOKUP(B21,Weight!B:B,Weight!D:D,"#N/A",0)} -> 140 | Q21: =IF(AF21="","",AF21*P21) | S21: 392620 | T21: 12 | U21: 60 | X21: =SUMIFS('Transit Shipment'!$B$10:$B$1048462,'Transit Shipment'!$A$10:$A$1048462,B21,'Transit Shipment'!$C$10:$C$1048462,AA21) -> 0 | Y21: =IF(SUMIFS(DIH!$S$2:$S833,DIH!$D$2:$D833,B21,DIH!$U$2:$U833,AA21)>0,SUMIFS(DIH!$S$2:$S833,DIH!$D$2:$D833,B21,DIH!$U$2:$U833,AA21),0) -> 0 | Z21: =SUM(X21:Y21) -> 0 | AA21: BOM7 | AB21: =IF(ISNA(VLOOKUP($B21,'Business Report'!$D$2:$J$202,2,0)),"",VLOOKUP($B21,'Business Report'!$D$2:$J$202,2,0)) -> 15 | AC21: =SUMIFS(AFS!$P$2:$P$6260,AFS!$N$2:$N$6260,B21,AFS!$AT$2:$AT$6260,AA21) -> 0 | AD21: =CEILING(AC21/$W$2*$X$2,1)-sum(X21:Y21) -> 0 | AE21: =SUM(AD13:AD21) -> 38 | AF21: =IF(ISNUMBER(AD21),IF(AD21<=0,"",IF(F21="","",E21*$AC$2+IF(F21>0,$AC$2,0)))) | AI21: =IF(ISNUMBER(AG21),IF(AG21<=0,"",IF(I21="","",H21*$AC$2+IF(I21>0,$AC$2,0)))) -> FALSE
A22: APR- Brown | B22: Apron_Brown | C22: CRASOME Polyester Kitchen Apron for Men Women Chef Cooking Restaurants gardening workshop, barbers With Pockets and Adjustable Strap ( Brown ) | D22: Apron | E22: =IF(ISNUMBER(AD22),IF(AD22>=0,IF(AD22=0,1,INT(AD22/$AC$2)),""),"") | F22: =IF(E22="","",IF(AD22=0,0,AD22/$AC$2-E22)) | G22: =IF(ISERROR(SEARCH("Apron",D22)),AF22,"") | J22: =IF(ISNUMBER($AF22),1*$AF22,"") | P22: {=XLOOKUP(B22,Weight!B:B,Weight!D:D,"#N/A",0)} -> 140 | Q22: =IF(AF22="","",AF22*P22) | S22: 392620 | T22: 12 | U22: 60 | V22: =B22 -> Apron_Brown | W22: =C22 -> CRASOME Polyester Kitchen Apron for Men Women Chef Cooking Restaurants gardening workshop, barbers With Pockets and Adjustable Strap ( Brown ) | X22: =SUMIFS('Transit Shipment'!$B$10:$B$1048462,'Transit Shipment'!$A$10:$A$1048462,B22,'Transit Shipment'!$C$10:$C$1048462,AA22) -> 0 | Y22: =IF(SUMIFS(DIH!$S$2:$S833,DIH!$D$2:$D833,B22,DIH!$U$2:$U833,AA22)>0,SUMIFS(DIH!$S$2:$S833,DIH!$D$2:$D833,B22,DIH!$U$2:$U833,AA22),0) -> 5 | Z22: =SUM(X22:Y22) -> 5 | AA22: AMD2 | AB22: =IF(ISNA(VLOOKUP($B22,'Business Report'!$D$2:$J$202,2,0)),"",VLOOKUP($B22,'Business Report'!$D$2:$J$202,2,0)) -> 33 | AC22: =SUMIFS(AFS!$P$2:$P$6260,AFS!$N$2:$N$6260,B22,AFS!$AT$2:$AT$6260,AA22) -> 0 | AD22: =CEILING(AC22/$W$2*$X$2,1)-sum(X22:Y22) -> -5 | AF22: =IF(ISNUMBER(AD22),IF(AD22<=0,"",IF(F22="","",E22*$AC$2+IF(F22>0,$AC$2,0))))
A23: APR- Brown | B23: Apron_Brown | C23: CRASOME Polyester Kitchen Apron for Men Women Chef Cooking Restaurants gardening workshop, barbers With Pockets and Adjustable Strap ( Brown ) | D23: Apron | E23: =IF(ISNUMBER(AD23),IF(AD23>=0,IF(AD23=0,1,INT(AD23/$AC$2)),""),"") | F23: =IF(E23="","",IF(AD23=0,0,AD23/$AC$2-E23)) | G23: =IF(ISERROR(SEARCH("Apron",D23)),AF23,"") | J23: =IF(ISNUMBER($AF23),1*$AF23,"") | P23: {=XLOOKUP(B23,Weight!B:B,Weight!D:D,"#N/A",0)} -> 140 | Q23: =IF(AF23="","",AF23*P23) | S23: 392620 | T23: 12 | U23: 60 | X23: =SUMIFS('Transit Shipment'!$B$10:$B$1048462,'Transit Shipment'!$A$10:$A$1048462,B23,'Transit Shipment'!$C$10:$C$1048462,AA23) -> 0 | Y23: =IF(SUMIFS(DIH!$S$2:$S833,DIH!$D$2:$D833,B23,DIH!$U$2:$U833,AA23)>0,SUMIFS(DIH!$S$2:$S833,DIH!$D$2:$D833,B23,DIH!$U$2:$U833,AA23),0) -> 21 | Z23: =SUM(X23:Y23) -> 21 | AA23: BLR8 | AB23: =IF(ISNA(VLOOKUP($B23,'Business Report'!$D$2:$J$202,2,0)),"",VLOOKUP($B23,'Business Report'!$D$2:$J$202,2,0)) -> 33 | AC23: =SUMIFS(AFS!$P$2:$P$6260,AFS!$N$2:$N$6260,B23,AFS!$AT$2:$AT$6260,AA23) -> 4 | AD23: =CEILING(AC23/$W$2*$X$2,1)-sum(X23:Y23) -> -15 | AF23: =IF(ISNUMBER(AD23),IF(AD23<=0,"",IF(F23="","",E23*$AC$2+IF(F23>0,$AC$2,0))))
A24: APR- Brown | B24: Apron_Brown | C24: CRASOME Polyester Kitchen Apron for Men Women Chef Cooking Restaurants gardening workshop, barbers With Pockets and Adjustable Strap ( Brown ) | D24: Apron | E24: =IF(ISNUMBER(AD24),IF(AD24>=0,IF(AD24=0,1,INT(AD24/$AC$2)),""),"") -> 2 | F24: =IF(E24="","",IF(AD24=0,0,AD24/$AC$2-E24)) -> 0.5 | G24: =IF(ISERROR(SEARCH("Apron",D24)),AF24,"") | J24: =IF(ISNUMBER($AF24),1*$AF24,"") -> 6 | P24: {=XLOOKUP(B24,Weight!B:B,Weight!D:D,"#N/A",0)} -> 140 | Q24: =IF(AF24="","",AF24*P24) -> 840 | S24: 392620 | T24: 12 | U24: 60 | X24: =SUMIFS('Transit Shipment'!$B$10:$B$1048462,'Transit Shipment'!$A$10:$A$1048462,B24,'Transit Shipment'!$C$10:$C$1048462,AA24) -> 0 | Y24: =IF(SUMIFS(DIH!$S$2:$S833,DIH!$D$2:$D833,B24,DIH!$U$2:$U833,AA24)>0,SUMIFS(DIH!$S$2:$S833,DIH!$D$2:$D833,B24,DIH!$U$2:$U833,AA24),0) -> 7 | Z24: =SUM(X24:Y24) -> 7 | AA24: BLR7 | AB24: =IF(ISNA(VLOOKUP($B24,'Business Report'!$D$2:$J$202,2,0)),"",VLOOKUP($B24,'Business Report'!$D$2:$J$202,2,0)) -> 33 | AC24: =SUMIFS(AFS!$P$2:$P$6260,AFS!$N$2:$N$6260,B24,AFS!$AT$2:$AT$6260,AA24) -> 9 | AD24: =CEILING(AC24/$W$2*$X$2,1)-sum(X24:Y24) -> 5 | AF24: =IF(ISNUMBER(AD24),IF(AD24<=0,"",IF(F24="","",E24*$AC$2+IF(F24>0,$AC$2,0)))) -> 6
A25: APR- Brown | B25: Apron_Brown | C25: CRASOME Polyester Kitchen Apron for Men Women Chef Cooking Restaurants gardening workshop, barbers With Pockets and Adjustable Strap ( Brown ) | D25: Apron | E25: =IF(ISNUMBER(AD25),IF(AD25>=0,IF(AD25=0,1,INT(AD25/$AC$2)),""),"") | F25: =IF(E25="","",IF(AD25=0,0,AD25/$AC$2-E25)) | G25: =IF(ISERROR(SEARCH("Apron",D25)),AF25,"") | J25: =IF(ISNUMBER($AF25),1*$AF25,"") | P25: {=XLOOKUP(B25,Weight!B:B,Weight!D:D,"#N/A",0)} -> 140 | Q25: =IF(AF25="","",AF25*P25) | S25: 392620 | T25: 12 | U25: 60 | X25: =SUMIFS('Transit Shipment'!$B$10:$B$1048462,'Transit Shipment'!$A$10:$A$1048462,B25,'Transit Shipment'!$C$10:$C$1048462,AA25) -> 0 | Y25: =IF(SUMIFS(DIH!$S$2:$S833,DIH!$D$2:$D833,B25,DIH!$U$2:$U833,AA25)>0,SUMIFS(DIH!$S$2:$S833,DIH!$D$2:$D833,B25,DIH!$U$2:$U833,AA25),0) -> 3 | Z25: =SUM(X25:Y25) -> 3 | AA25: CJB1 | AB25: =IF(ISNA(VLOOKUP($B25,'Business Report'!$D$2:$J$202,2,0)),"",VLOOKUP($B25,'Business Report'!$D$2:$J$202,2,0)) -> 33 | AC25: =SUMIFS(AFS!$P$2:$P$6260,AFS!$N$2:$N$6260,B25,AFS!$AT$2:$AT$6260,AA25) -> 1 | AD25: =CEILING(AC25/$W$2*$X$2,1)-sum(X25:Y25) -> -1 | AF25: =IF(ISNUMBER(AD25),IF(AD25<=0,"",IF(F25="","",E25*$AC$2+IF(F25>0,$AC$2,0))))
A26: APR- Brown | B26: Apron_Brown | C26: CRASOME Polyester Kitchen Apron for Men Women Chef Cooking Restaurants gardening workshop, barbers With Pockets and Adjustable Strap ( Brown ) | D26: Apron | E26: =IF(ISNUMBER(AD26),IF(AD26>=0,IF(AD26=0,1,INT(AD26/$AC$2)),""),"") | F26: =IF(E26="","",IF(AD26=0,0,AD26/$AC$2-E26)) | G26: =IF(ISERROR(SEARCH("Apron",D26)),AF26,"") | J26: =IF(ISNUMBER($AF26),1*$AF26,"") | P26: {=XLOOKUP(B26,Weight!B:B,Weight!D:D,"#N/A",0)} -> 140 | Q26: =IF(AF26="","",AF26*P26) | S26: 392620 | T26: 12 | U26: 60 | X26: =SUMIFS('Transit Shipment'!$B$10:$B$1048462,'Transit Shipment'!$A$10:$A$1048462,B26,'Transit Shipment'!$C$10:$C$1048462,AA26) -> 0 | Y26: =IF(SUMIFS(DIH!$S$2:$S833,DIH!$D$2:$D833,B26,DIH!$U$2:$U833,AA26)>0,SUMIFS(DIH!$S$2:$S833,DIH!$D$2:$D833,B26,DIH!$U$2:$U833,AA26),0) -> 17 | Z26: =SUM(X26:Y26) -> 17 | AA26: MAA4 | AB26: =IF(ISNA(VLOOKUP($B26,'Business Report'!$D$2:$J$202,2,0)),"",VLOOKUP($B26,'Business Report'!$D$2:$J$202,2,0)) -> 33 | AC26: =SUMIFS(AFS!$P$2:$P$6260,AFS!$N$2:$N$6260,B26,AFS!$AT$2:$AT$6260,AA26) -> 8 | AD26: =CEILING(AC26/$W$2*$X$2,1)-sum(X26:Y26) -> -6 | AF26: =IF(ISNUMBER(AD26),IF(AD26<=0,"",IF(F26="","",E26*$AC$2+IF(F26>0,$AC$2,0))))
A27: APR- Brown | B27: Apron_Brown | C27: CRASOME Polyester Kitchen Apron for Men Women Chef Cooking Restaurants gardening workshop, barbers With Pockets and Adjustable Strap ( Brown ) | D27: Apron | E27: =IF(ISNUMBER(AD27),IF(AD27>=0,IF(AD27=0,1,INT(AD27/$AC$2)),""),"") -> 1 | F27: =IF(E27="","",IF(AD27=0,0,AD27/$AC$2-E27)) -> 0.5 | G27: =IF(ISERROR(SEARCH("Apron",D27)),AF27,"") | J27: =IF(ISNUMBER($AF27),1*$AF27,"") -> 4 | P27: {=XLOOKUP(B27,Weight!B:B,Weight!D:D,"#N/A",0)} -> 140 | Q27: =IF(AF27="","",AF27*P27) -> 560 | S27: 392620 | T27: 12 | U27: 60 | X27: =SUMIFS('Transit Shipment'!$B$10:$B$1048462,'Transit Shipment'!$A$10:$A$1048462,B27,'Transit Shipment'!$C$10:$C$1048462,AA27) -> 0 | Y27: =IF(SUMIFS(DIH!$S$2:$S833,DIH!$D$2:$D833,B27,DIH!$U$2:$U833,AA27)>0,SUMIFS(DIH!$S$2:$S833,DIH!$D$2:$D833,B27,DIH!$U$2:$U833,AA27),0) -> 8 | Z27: =SUM(X27:Y27) -> 8 | AA27: DEL4 | AB27: =IF(ISNA(VLOOKUP($B27,'Business Report'!$D$2:$J$202,2,0)),"",VLOOKUP($B27,'Business Report'!$D$2:$J$202,2,0)) -> 33 | AC27: =SUMIFS(AFS!$P$2:$P$6260,AFS!$N$2:$N$6260,B27,AFS!$AT$2:$AT$6260,AA27) -> 8 | AD27: =CEILING(AC27/$W$2*$X$2,1)-sum(X27:Y27) -> 3 | AF27: =IF(ISNUMBER(AD27),IF(AD27<=0,"",IF(F27="","",E27*$AC$2+IF(F27>0,$AC$2,0)))) -> 4
A28: APR- Brown | B28: Apron_Brown | C28: CRASOME Polyester Kitchen Apron for Men Women Chef Cooking Restaurants gardening workshop, barbers With Pockets and Adjustable Strap ( Brown ) | D28: Apron | E28: =IF(ISNUMBER(AD28),IF(AD28>=0,IF(AD28=0,1,INT(AD28/$AC$2)),""),"") -> 1 | F28: =IF(E28="","",IF(AD28=0,0,AD28/$AC$2-E28)) -> 0.5 | G28: =IF(ISERROR(SEARCH("Apron",D28)),AF28,"") | J28: =IF(ISNUMBER($AF28),1*$AF28,"") -> 4 | P28: {=XLOOKUP(B28,Weight!B:B,Weight!D:D,"#N/A",0)} -> 140 | Q28: =IF(AF28="","",AF28*P28) -> 560 | S28: 392620 | T28: 12 | U28: 60 | X28: =SUMIFS('Transit Shipment'!$B$10:$B$1048462,'Transit Shipment'!$A$10:$A$1048462,B28,'Transit Shipment'!$C$10:$C$1048462,AA28) -> 0 | Y28: =IF(SUMIFS(DIH!$S$2:$S833,DIH!$D$2:$D833,B28,DIH!$U$2:$U833,AA28)>0,SUMIFS(DIH!$S$2:$S833,DIH!$D$2:$D833,B28,DIH!$U$2:$U833,AA28),0) -> 8 | Z28: =SUM(X28:Y28) -> 8 | AA28: DEL5 | AB28: =IF(ISNA(VLOOKUP($B28,'Business Report'!$D$2:$J$202,2,0)),"",VLOOKUP($B28,'Business Report'!$D$2:$J$202,2,0)) -> 33 | AC28: =SUMIFS(AFS!$P$2:$P$6260,AFS!$N$2:$N$6260,B28,AFS!$AT$2:$AT$6260,AA28) -> 8 | AD28: =CEILING(AC28/$W$2*$X$2,1)-sum(X28:Y28) -> 3 | AF28: =IF(ISNUMBER(AD28),IF(AD28<=0,"",IF(F28="","",E28*$AC$2+IF(F28>0,$AC$2,0)))) -> 4
A29: APR- Brown | B29: Apron_Brown | C29: CRASOME Polyester Kitchen Apron for Men Women Chef Cooking Restaurants gardening workshop, barbers With Pockets and Adjustable Strap ( Brown ) | D29: Apron | E29: =IF(ISNUMBER(AD29),IF(AD29>=0,IF(AD29=0,1,INT(AD29/$AC$2)),""),"") | F29: =IF(E29="","",IF(AD29=0,0,AD29/$AC$2-E29)) | G29: =IF(ISERROR(SEARCH("Apron",D29)),AF29,"") | J29: =IF(ISNUMBER($AF29),1*$AF29,"") | P29: {=XLOOKUP(B29,Weight!B:B,Weight!D:D,"#N/A",0)} -> 140 | Q29: =IF(AF29="","",AF29*P29) | S29: 392620 | T29: 12 | U29: 60 | X29: =SUMIFS('Transit Shipment'!$B$10:$B$1048462,'Transit Shipment'!$A$10:$A$1048462,B29,'Transit Shipment'!$C$10:$C$1048462,AA29) -> 0 | Y29: =IF(SUMIFS(DIH!$S$2:$S833,DIH!$D$2:$D833,B29,DIH!$U$2:$U833,AA29)>0,SUMIFS(DIH!$S$2:$S833,DIH!$D$2:$D833,B29,DIH!$U$2:$U833,AA29),0) -> 10 | Z29: =SUM(X29:Y29) -> 10 | AA29: BOM5 | AB29: =IF(ISNA(VLOOKUP($B29,'Business Report'!$D$2:$J$202,2,0)),"",VLOOKUP($B29,'Business Report'!$D$2:$J$202,2,0)) -> 33 | AC29: =SUMIFS(AFS!$P$2:$P$6260,AFS!$N$2:$N$6260,B29,AFS!$AT$2:$AT$6260,AA29) -> 4 | AD29: =CEILING(AC29/$W$2*$X$2,1)-sum(X29:Y29) -> -4 | AF29: =IF(ISNUMBER(AD29),IF(AD29<=0,"",IF(F29="","",E29*$AC$2+IF(F29>0,$AC$2,0))))
A30: APR- Brown | B30: Apron_Brown | C30: CRASOME Polyester Kitchen Apron for Men Women Chef Cooking Restaurants gardening workshop, barbers With Pockets and Adjustable Strap ( Brown ) | D30: Apron | E30: =IF(ISNUMBER(AD30),IF(AD30>=0,IF(AD30=0,1,INT(AD30/$AC$2)),""),"") -> 1 | F30: =IF(E30="","",IF(AD30=0,0,AD30/$AC$2-E30)) -> 0 | G30: =IF(ISERROR(SEARCH("Apron",D30)),AF30,"") | J30: =IF(ISNUMBER($AF30),1*$AF30,"") -> 2 | P30: {=XLOOKUP(B30,Weight!B:B,Weight!D:D,"#N/A",0)} -> 140 | Q30: =IF(AF30="","",AF30*P30) -> 280 | S30: 392620 | T30: 12 | U30: 60 | X30: =SUMIFS('Transit Shipment'!$B$10:$B$1048462,'Transit Shipment'!$A$10:$A$1048462,B30,'Transit Shipment'!$C$10:$C$1048462,AA30) -> 0 | Y30: =IF(SUMIFS(DIH!$S$2:$S833,DIH!$D$2:$D833,B30,DIH!$U$2:$U833,AA30)>0,SUMIFS(DIH!$S$2:$S833,DIH!$D$2:$D833,B30,DIH!$U$2:$U833,AA30),0) -> 0 | Z30: =SUM(X30:Y30) -> 0 | AA30: BOM7 | AB30: =IF(ISNA(VLOOKUP($B30,'Business Report'!$D$2:$J$202,2,0)),"",VLOOKUP($B30,'Business Report'!$D$2:$J$202,2,0)) -> 33 | AC30: =SUMIFS(AFS!$P$2:$P$6260,AFS!$N$2:$N$6260,B30,AFS!$AT$2:$AT$6260,AA30) -> 1 | AD30: =CEILING(AC30/$W$2*$X$2,1)-sum(X30:Y30) -> 2 | AE30: =SUM(AD22:AD30) -> -18 | AF30: =IF(ISNUMBER(AD30),IF(AD30<=0,"",IF(F30="","",E30*$AC$2+IF(F30>0,$AC$2,0)))) -> 2
A31: APR- Grey | B31: Apron_Grey | C31: CRASOME Polyester Kitchen Apron for Men Women Chef Cooking Restaurants gardening workshop, barbers With Pockets and Adjustable Strap ( Grey ) | D31: Apron | E31: =IF(ISNUMBER(AD31),IF(AD31>=0,IF(AD31=0,1,INT(AD31/$AC$2)),""),"") -> 1 | F31: =IF(E31="","",IF(AD31=0,0,AD31/$AC$2-E31)) -> 0 | G31: =IF(ISERROR(SEARCH("Apron",D31)),AF31,"") | O31: =IF(ISNUMBER($AF31),1*$AF31,"") | P31: {=XLOOKUP(B31,Weight!B:B,Weight!D:D,"#N/A",0)} -> 140 | Q31: =IF(AF31="","",AF31*P31) | S31: 392620 | T31: 12 | U31: 60 | V31: =B31 -> Apron_Grey | W31: =C31 -> CRASOME Polyester Kitchen Apron for Men Women Chef Cooking Restaurants gardening workshop, barbers With Pockets and Adjustable Strap ( Grey ) | X31: =SUMIFS('Transit Shipment'!$B$10:$B$1048462,'Transit Shipment'!$A$10:$A$1048462,B31,'Transit Shipment'!$C$10:$C$1048462,AA31) -> 0 | Y31: =IF(SUMIFS(DIH!$S$2:$S833,DIH!$D$2:$D833,B31,DIH!$U$2:$U833,AA31)>0,SUMIFS(DIH!$S$2:$S833,DIH!$D$2:$D833,B31,DIH!$U$2:$U833,AA31),0) -> 2 | Z31: =SUM(X31:Y31) -> 2 | AA31: AMD2 | AB31: =IF(ISNA(VLOOKUP($B31,'Business Report'!$D$2:$J$202,2,0)),"",VLOOKUP($B31,'Business Report'!$D$2:$J$202,2,0)) -> 21 | AC31: =SUMIFS(AFS!$P$2:$P$6260,AFS!$N$2:$N$6260,B31,AFS!$AT$2:$AT$6260,AA31) -> 1 | AD31: =CEILING(AC31/$W$2*$X$2,1)-sum(X31:Y31) -> 0 | AF31: =IF(ISNUMBER(AD31),IF(AD31<=0,"",IF(F31="","",E31*$AC$2+IF(F31>0,$AC$2,0))))
A32: APR- Grey | B32: Apron_Grey | C32: CRASOME Polyester Kitchen Apron for Men Women Chef Cooking Restaurants gardening workshop, barbers With Pockets and Adjustable Strap ( Grey ) | D32: Apron | E32: =IF(ISNUMBER(AD32),IF(AD32>=0,IF(AD32=0,1,INT(AD32/$AC$2)),""),"") | F32: =IF(E32="","",IF(AD32=0,0,AD32/$AC$2-E32)) | G32: =IF(ISERROR(SEARCH("Apron",D32)),AF32,"") | O32: =IF(ISNUMBER($AF32),1*$AF32,"") | P32: {=XLOOKUP(B32,Weight!B:B,Weight!D:D,"#N/A",0)} -> 140 | Q32: =IF(AF32="","",AF32*P32) | S32: 392620 | T32: 12 | U32: 60 | X32: =SUMIFS('Transit Shipment'!$B$10:$B$1048462,'Transit Shipment'!$A$10:$A$1048462,B32,'Transit Shipment'!$C$10:$C$1048462,AA32) -> 0 | Y32: =IF(SUMIFS(DIH!$S$2:$S833,DIH!$D$2:$D833,B32,DIH!$U$2:$U833,AA32)>0,SUMIFS(DIH!$S$2:$S833,DIH!$D$2:$D833,B32,DIH!$U$2:$U833,AA32),0) -> 10 | Z32: =SUM(X32:Y32) -> 10 | AA32: BLR8 | AB32: =IF(ISNA(VLOOKUP($B32,'Business Report'!$D$2:$J$202,2,0)),"",VLOOKUP($B32,'Business Report'!$D$2:$J$202,2,0)) -> 21 | AC32: =SUMIFS(AFS!$P$2:$P$6260,AFS!$N$2:$N$6260,B32,AFS!$AT$2:$AT$6260,AA32) -> 2 | AD32: =CEILING(AC32/$W$2*$X$2,1)-sum(X32:Y32) -> -7 | AF32: =IF(ISNUMBER(AD32),IF(AD32<=0,"",IF(F32="","",E32*$AC$2+IF(F32>0,$AC$2,0))))
A33: APR- Grey | B33: Apron_Grey | C33: CRASOME Polyester Kitchen Apron for Men Women Chef Cooking Restaurants gardening workshop, barbers With Pockets and Adjustable Strap ( Grey ) | D33: Apron | E33: =IF(ISNUMBER(AD33),IF(AD33>=0,IF(AD33=0,1,INT(AD33/$AC$2)),""),"") -> 0 | F33: =IF(E33="","",IF(AD33=0,0,AD33/$AC$2-E33)) -> 0.5 | G33: =IF(ISERROR(SEARCH("Apron",D33)),AF33,"") | O33: =IF(ISNUMBER($AF33),1*$AF33,"") -> 2 | P33: {=XLOOKUP(B33,Weight!B:B,Weight!D:D,"#N/A",0)} -> 140 | Q33: =IF(AF33="","",AF33*P33) -> 280 | S33: 392620 | T33: 12 | U33: 60 | X33: =SUMIFS('Transit Shipment'!$B$10:$B$1048462,'Transit Shipment'!$A$10:$A$1048462,B33,'Transit Shipment'!$C$10:$C$1048462,AA33) -> 0 | Y33: =IF(SUMIFS(DIH!$S$2:$S833,DIH!$D$2:$D833,B33,DIH!$U$2:$U833,AA33)>0,SUMIFS(DIH!$S$2:$S833,DIH!$D$2:$D833,B33,DIH!$U$2:$U833,AA33),0) -> 1 | Z33: =SUM(X33:Y33) -> 1 | AA33: BLR7 | AB33: =IF(ISNA(VLOOKUP($B33,'Business Report'!$D$2:$J$202,2,0)),"",VLOOKUP($B33,'Business Report'!$D$2:$J$202,2,0)) -> 21 | AC33: =SUMIFS(AFS!$P$2:$P$6260,AFS!$N$2:$N$6260,B33,AFS!$AT$2:$AT$6260,AA33) -> 1 | AD33: =CEILING(AC33/$W$2*$X$2,1)-sum(X33:Y33) -> 1 | AF33: =IF(ISNUMBER(AD33),IF(AD33<=0,"",IF(F33="","",E33*$AC$2+IF(F33>0,$AC$2,0)))) -> 2
A34: APR- Grey | B34: Apron_Grey | C34: CRASOME Polyester Kitchen Apron for Men Women Chef Cooking Restaurants gardening workshop, barbers With Pockets and Adjustable Strap ( Grey ) | D34: Apron | E34: =IF(ISNUMBER(AD34),IF(AD34>=0,IF(AD34=0,1,INT(AD34/$AC$2)),""),"") | F34: =IF(E34="","",IF(AD34=0,0,AD34/$AC$2-E34)) | G34: =IF(ISERROR(SEARCH("Apron",D34)),AF34,"") | O34: =IF(ISNUMBER($AF34),1*$AF34,"") | P34: {=XLOOKUP(B34,Weight!B:B,Weight!D:D,"#N/A",0)} -> 140 | Q34: =IF(AF34="","",AF34*P34) | S34: 392620 | T34: 12 | U34: 60 | X34: =SUMIFS('Transit Shipment'!$B$10:$B$1048462,'Transit Shipment'!$A$10:$A$1048462,B34,'Transit Shipment'!$C$10:$C$1048462,AA34) -> 0 | Y34: =IF(SUMIFS(DIH!$S$2:$S833,DIH!$D$2:$D833,B34,DIH!$U$2:$U833,AA34)>0,SUMIFS(DIH!$S$2:$S833,DIH!$D$2:$D833,B34,DIH!$U$2:$U833,AA34),0) -> 4 | Z34: =SUM(X34:Y34) -> 4 | AA34: CJB1 | AB34: =IF(ISNA(VLOOKUP($B34,'Business Report'!$D$2:$J$202,2,0)),"",VLOOKUP($B34,'Business Report'!$D$2:$J$202,2,0)) -> 21 | AC34: =SUMIFS(AFS!$P$2:$P$6260,AFS!$N$2:$N$6260,B34,AFS!$AT$2:$AT$6260,AA34) -> 0 | AD34: =CEILING(AC34/$W$2*$X$2,1)-sum(X34:Y34) -> -4 | AF34: =IF(ISNUMBER(AD34),IF(AD34<=0,"",IF(F34="","",E34*$AC$2+IF(F34>0,$AC$2,0))))
A35: APR- Grey | B35: Apron_Grey | C35: CRASOME Polyester Kitchen Apron for Men Women Chef Cooking Restaurants gardening workshop, barbers With Pockets and Adjustable Strap ( Grey ) | D35: Apron | E35: =IF(ISNUMBER(AD35),IF(AD35>=0,IF(AD35=0,1,INT(AD35/$AC$2)),""),"") -> 2 | F35: =IF(E35="","",IF(AD35=0,0,AD35/$AC$2-E35)) -> 0.5 | G35: =IF(ISERROR(SEARCH("Apron",D35)),AF35,"") | O35: =IF(ISNUMBER($AF35),1*$AF35,"") -> 6 | P35: {=XLOOKUP(B35,Weight!B:B,Weight!D:D,"#N/A",0)} -> 140 | Q35: =IF(AF35="","",AF35*P35) -> 840 | S35: 392620 | T35: 12 | U35: 60 | X35: =SUMIFS('Transit Shipment'!$B$10:$B$1048462,'Transit Shipment'!$A$10:$A$1048462,B35,'Transit Shipment'!$C$10:$C$1048462,AA35) -> 0 | Y35: =IF(SUMIFS(DIH!$S$2:$S833,DIH!$D$2:$D833,B35,DIH!$U$2:$U833,AA35)>0,SUMIFS(DIH!$S$2:$S833,DIH!$D$2:$D833,B35,DIH!$U$2:$U833,AA35),0) -> 3 | Z35: =SUM(X35:Y35) -> 3 | AA35: MAA4 | AB35: =IF(ISNA(VLOOKUP($B35,'Business Report'!$D$2:$J$202,2,0)),"",VLOOKUP($B35,'Business Report'!$D$2:$J$202,2,0)) -> 21 | AC35: =SUMIFS(AFS!$P$2:$P$6260,AFS!$N$2:$N$6260,B35,AFS!$AT$2:$AT$6260,AA35) -> 6 | AD35: =CEILING(AC35/$W$2*$X$2,1)-sum(X35:Y35) -> 5 | AF35: =IF(ISNUMBER(AD35),IF(AD35<=0,"",IF(F35="","",E35*$AC$2+IF(F35>0,$AC$2,0)))) -> 6
A36: APR- Grey | B36: Apron_Grey | C36: CRASOME Polyester Kitchen Apron for Men Women Chef Cooking Restaurants gardening workshop, barbers With Pockets and Adjustable Strap ( Grey ) | D36: Apron | E36: =IF(ISNUMBER(AD36),IF(AD36>=0,IF(AD36=0,1,INT(AD36/$AC$2)),""),"") | F36: =IF(E36="","",IF(AD36=0,0,AD36/$AC$2-E36)) | G36: =IF(ISERROR(SEARCH("Apron",D36)),AF36,"") | O36: =IF(ISNUMBER($AF36),1*$AF36,"") | P36: {=XLOOKUP(B36,Weight!B:B,Weight!D:D,"#N/A",0)} -> 140 | Q36: =IF(AF36="","",AF36*P36) | S36: 392620 | T36: 12 | U36: 60 | X36: =SUMIFS('Transit Shipment'!$B$10:$B$1048462,'Transit Shipment'!$A$10:$A$1048462,B36,'Transit Shipment'!$C$10:$C$1048462,AA36) -> 0 | Y36: =IF(SUMIFS(DIH!$S$2:$S833,DIH!$D$2:$D833,B36,DIH!$U$2:$U833,AA36)>0,SUMIFS(DIH!$S$2:$S833,DIH!$D$2:$D833,B36,DIH!$U$2:$U833,AA36),0) -> 3 | Z36: =SUM(X36:Y36) -> 3 | AA36: DEL4 | AB36: =IF(ISNA(VLOOKUP($B36,'Business Report'!$D$2:$J$202,2,0)),"",VLOOKUP($B36,'Business Report'!$D$2:$J$202,2,0)) -> 21 | AC36: =SUMIFS(AFS!$P$2:$P$6260,AFS!$N$2:$N$6260,B36,AFS!$AT$2:$AT$6260,AA36) -> 0 | AD36: =CEILING(AC36/$W$2*$X$2,1)-sum(X36:Y36) -> -3 | AF36: =IF(ISNUMBER(AD36),IF(AD36<=0,"",IF(F36="","",E36*$AC$2+IF(F36>0,$AC$2,0))))
A37: APR- Grey | B37: Apron_Grey | C37: CRASOME Polyester Kitchen Apron for Men Women Chef Cooking Restaurants gardening workshop, barbers With Pockets and Adjustable Strap ( Grey ) | D37: Apron | E37: =IF(ISNUMBER(AD37),IF(AD37>=0,IF(AD37=0,1,INT(AD37/$AC$2)),""),"") | F37: =IF(E37="","",IF(AD37=0,0,AD37/$AC$2-E37)) | G37: =IF(ISERROR(SEARCH("Apron",D37)),AF37,"") | O37: =IF(ISNUMBER($AF37),1*$AF37,"") | P37: {=XLOOKUP(B37,Weight!B:B,Weight!D:D,"#N/A",0)} -> 140 | Q37: =IF(AF37="","",AF37*P37) | S37: 392620 | T37: 12 | U37: 60 | X37: =SUMIFS('Transit Shipment'!$B$10:$B$1048462,'Transit Shipment'!$A$10:$A$1048462,B37,'Transit Shipment'!$C$10:$C$1048462,AA37) -> 0 | Y37: =IF(SUMIFS(DIH!$S$2:$S833,DIH!$D$2:$D833,B37,DIH!$U$2:$U833,AA37)>0,SUMIFS(DIH!$S$2:$S833,DIH!$D$2:$D833,B37,DIH!$U$2:$U833,AA37),0) -> 12 | Z37: =SUM(X37:Y37) -> 12 | AA37: DEL5 | AB37: =IF(ISNA(VLOOKUP($B37,'Business Report'!$D$2:$J$202,2,0)),"",VLOOKUP($B37,'Business Report'!$D$2:$J$202,2,0)) -> 21 | AC37: =SUMIFS(AFS!$P$2:$P$6260,AFS!$N$2:$N$6260,B37,AFS!$AT$2:$AT$6260,AA37) -> 1 | AD37: =CEILING(AC37/$W$2*$X$2,1)-sum(X37:Y37) -> -10 | AF37: =IF(ISNUMBER(AD37),IF(AD37<=0,"",IF(F37="","",E37*$AC$2+IF(F37>0,$AC$2,0))))
A38: APR- Grey | B38: Apron_Grey | C38: CRASOME Polyester Kitchen Apron for Men Women Chef Cooking Restaurants gardening workshop, barbers With Pockets and Adjustable Strap ( Grey ) | D38: Apron | E38: =IF(ISNUMBER(AD38),IF(AD38>=0,IF(AD38=0,1,INT(AD38/$AC$2)),""),"") -> 1 | F38: =IF(E38="","",IF(AD38=0,0,AD38/$AC$2-E38)) -> 0 | G38: =IF(ISERROR(SEARCH("Apron",D38)),AF38,"") | O38: =IF(ISNUMBER($AF38),1*$AF38,"") | P38: {=XLOOKUP(B38,Weight!B:B,Weight!D:D,"#N/A",0)} -> 140 | Q38: =IF(AF38="","",AF38*P38) | S38: 392620 | T38: 12 | U38: 60 | X38: =SUMIFS('Transit Shipment'!$B$10:$B$1048462,'Transit Shipment'!$A$10:$A$1048462,B38,'Transit Shipment'!$C$10:$C$1048462,AA38) -> 0 | Y38: =IF(SUMIFS(DIH!$S$2:$S833,DIH!$D$2:$D833,B38,DIH!$U$2:$U833,AA38)>0,SUMIFS(DIH!$S$2:$S833,DIH!$D$2:$D833,B38,DIH!$U$2:$U833,AA38),0) -> 2 | Z38: =SUM(X38:Y38) -> 2 | AA38: BOM5 | AB38: =IF(ISNA(VLOOKUP($B38,'Business Report'!$D$2:$J$202,2,0)),"",VLOOKUP($B38,'Business Report'!$D$2:$J$202,2,0)) -> 21 | AC38: =SUMIFS(AFS!$P$2:$P$6260,AFS!$N$2:$N$6260,B38,AFS!$AT$2:$AT$6260,AA38) -> 1 | AD38: =CEILING(AC38/$W$2*$X$2,1)-sum(X38:Y38) -> 0 | AF38: =IF(ISNUMBER(AD38),IF(AD38<=0,"",IF(F38="","",E38*$AC$2+IF(F38>0,$AC$2,0))))
A39: APR- Grey | B39: Apron_Grey | C39: CRASOME Polyester Kitchen Apron for Men Women Chef Cooking Restaurants gardening workshop, barbers With Pockets and Adjustable Strap ( Grey ) | D39: Apron | E39: =IF(ISNUMBER(AD39),IF(AD39>=0,IF(AD39=0,1,INT(AD39/$AC$2)),""),"") -> 1 | F39: =IF(E39="","",IF(AD39=0,0,AD39/$AC$2-E39)) -> 0 | G39: =IF(ISERROR(SEARCH("Apron",D39)),AF39,"") | O39: =IF(ISNUMBER($AF39),1*$AF39,"") | P39: {=XLOOKUP(B39,Weight!B:B,Weight!D:D,"#N/A",0)} -> 140 | Q39: =IF(AF39="","",AF39*P39) | S39: 392620 | T39: 12 | U39: 60 | X39: =SUMIFS('Transit Shipment'!$B$10:$B$1048462,'Transit Shipment'!$A$10:$A$1048462,B39,'Transit Shipment'!$C$10:$C$1048462,AA39) -> 0 | Y39: =IF(SUMIFS(DIH!$S$2:$S833,DIH!$D$2:$D833,B39,DIH!$U$2:$U833,AA39)>0,SUMIFS(DIH!$S$2:$S833,DIH!$D$2:$D833,B39,DIH!$U$2:$U833,AA39),0) -> 0 | Z39: =SUM(X39:Y39) -> 0 | AA39: BOM7 | AB39: =IF(ISNA(VLOOKUP($B39,'Business Report'!$D$2:$J$202,2,0)),"",VLOOKUP($B39,'Business Report'!$D$2:$J$202,2,0)) -> 21 | AC39: =SUMIFS(AFS!$P$2:$P$6260,AFS!$N$2:$N$6260,B39,AFS!$AT$2:$AT$6260,AA39) -> 0 | AD39: =CEILING(AC39/$W$2*$X$2,1)-sum(X39:Y39) -> 0 | AE39: =SUM(AD31:AD39) -> -18 | AF39: =IF(ISNUMBER(AD39),IF(AD39<=0,"",IF(F39="","",E39*$AC$2+IF(F39>0,$AC$2,0))))
A40: APR- Red | B40: Apron_Red | C40: CRASOME Polyester Kitchen Apron for Men Women Chef Cooking Restaurants gardening workshop, barbers With Pockets and Adjustable Strap ( Red ) | D40: Apron | E40: =IF(ISNUMBER(AD40),IF(AD40>=0,IF(AD40=0,1,INT(AD40/$AC$2)),""),"") -> 1 | F40: =IF(E40="","",IF(AD40=0,0,AD40/$AC$2-E40)) -> 0 | G40: =IF(ISERROR(SEARCH("Apron",D40)),AF40,"") | N40: =IF(ISNUMBER($AF40),1*$AF40,"") | P40: {=XLOOKUP(B40,Weight!B:B,Weight!D:D,"#N/A",0)} -> 140 | Q40: =IF(AF40="","",AF40*P40) | S40: 392620 | T40: 12 | U40: 60 | V40: =B40 -> Apron_Red | W40: =C40 -> CRASOME Polyester Kitchen Apron for Men Women Chef Cooking Restaurants gardening workshop, barbers With Pockets and Adjustable Strap ( Red ) | X40: =SUMIFS('Transit Shipment'!$B$10:$B$1048462,'Transit Shipment'!$A$10:$A$1048462,B40,'Transit Shipment'!$C$10:$C$1048462,AA40) -> 0 | Y40: =IF(SUMIFS(DIH!$S$2:$S833,DIH!$D$2:$D833,B40,DIH!$U$2:$U833,AA40)>0,SUMIFS(DIH!$S$2:$S833,DIH!$D$2:$D833,B40,DIH!$U$2:$U833,AA40),0) -> 0 | Z40: =SUM(X40:Y40) -> 0 | AA40: AMD2 | AB40: =IF(ISNA(VLOOKUP($B40,'Business Report'!$D$2:$J$202,2,0)),"",VLOOKUP($B40,'Business Report'!$D$2:$J$202,2,0)) -> 12 | AC40: =SUMIFS(AFS!$P$2:$P$6260,AFS!$N$2:$N$6260,B40,AFS!$AT$2:$AT$6260,AA40) -> 0 | AD40: =CEILING(AC40/$W$2*$X$2,1)-sum(X40:Y40) -> 0 | AF40: =IF(ISNUMBER(AD40),IF(AD40<=0,"",IF(F40="","",E40*$AC$2+IF(F40>0,$AC$2,0))))
A41: APR- Red | B41: Apron_Red | C41: CRASOME Polyester Kitchen Apron for Men Women Chef Cooking Restaurants gardening workshop, barbers With Pockets and Adjustable Strap ( Red ) | D41: Apron | E41: =IF(ISNUMBER(AD41),IF(AD41>=0,IF(AD41=0,1,INT(AD41/$AC$2)),""),"") -> 2 | F41: =IF(E41="","",IF(AD41=0,0,AD41/$AC$2-E41)) -> 0 | G41: =IF(ISERROR(SEARCH("Apron",D41)),AF41,"") | N41: =IF(ISNUMBER($AF41),1*$AF41,"") -> 4 | P41: {=XLOOKUP(B41,Weight!B:B,Weight!D:D,"#N/A",0)} -> 140 | Q41: =IF(AF41="","",AF41*P41) -> 560 | S41: 392620 | T41: 12 | U41: 60 | X41: =SUMIFS('Transit Shipment'!$B$10:$B$1048462,'Transit Shipment'!$A$10:$A$1048462,B41,'Transit Shipment'!$C$10:$C$1048462,AA41) -> 0 | Y41: =IF(SUMIFS(DIH!$S$2:$S833,DIH!$D$2:$D833,B41,DIH!$U$2:$U833,AA41)>0,SUMIFS(DIH!$S$2:$S833,DIH!$D$2:$D833,B41,DIH!$U$2:$U833,AA41),0) -> 0 | Z41: =SUM(X41:Y41) -> 0 | AA41: BLR8 | AB41: =IF(ISNA(VLOOKUP($B41,'Business Report'!$D$2:$J$202,2,0)),"",VLOOKUP($B41,'Business Report'!$D$2:$J$202,2,0)) -> 12 | AC41: =SUMIFS(AFS!$P$2:$P$6260,AFS!$N$2:$N$6260,B41,AFS!$AT$2:$AT$6260,AA41) -> 3 | AD41: =CEILING(AC41/$W$2*$X$2,1)-sum(X41:Y41) -> 4 | AF41: =IF(ISNUMBER(AD41),IF(AD41<=0,"",IF(F41="","",E41*$AC$2+IF(F41>0,$AC$2,0)))) -> 4
A42: APR- Red | B42: Apron_Red | C42: CRASOME Polyester Kitchen Apron for Men Women Chef Cooking Restaurants gardening workshop, barbers With Pockets and Adjustable Strap ( Red ) | D42: Apron | E42: =IF(ISNUMBER(AD42),IF(AD42>=0,IF(AD42=0,1,INT(AD42/$AC$2)),""),"") -> 1 | F42: =IF(E42="","",IF(AD42=0,0,AD42/$AC$2-E42)) -> 0 | G42: =IF(ISERROR(SEARCH("Apron",D42)),AF42,"") | N42: =IF(ISNUMBER($AF42),1*$AF42,"") | P42: {=XLOOKUP(B42,Weight!B:B,Weight!D:D,"#N/A",0)} -> 140 | Q42: =IF(AF42="","",AF42*P42) | S42: 392620 | T42: 12 | U42: 60 | X42: =SUMIFS('Transit Shipment'!$B$10:$B$1048462,'Transit Shipment'!$A$10:$A$1048462,B42,'Transit Shipment'!$C$10:$C$1048462,AA42) -> 0 | Y42: =IF(SUMIFS(DIH!$S$2:$S833,DIH!$D$2:$D833,B42,DIH!$U$2:$U833,AA42)>0,SUMIFS(DIH!$S$2:$S833,DIH!$D$2:$D833,B42,DIH!$U$2:$U833,AA42),0) -> 0 | Z42: =SUM(X42:Y42) -> 0 | AA42: BLR7 | AB42: =IF(ISNA(VLOOKUP($B42,'Business Report'!$D$2:$J$202,2,0)),"",VLOOKUP($B42,'Business Report'!$D$2:$J$202,2,0)) -> 12 | AC42: =SUMIFS(AFS!$P$2:$P$6260,AFS!$N$2:$N$6260,B42,AFS!$AT$2:$AT$6260,AA42) -> 0 | AD42: =CEILING(AC42/$W$2*$X$2,1)-sum(X42:Y42) -> 0 | AF42: =IF(ISNUMBER(AD42),IF(AD42<=0,"",IF(F42="","",E42*$AC$2+IF(F42>0,$AC$2,0))))
A43: APR- Red | B43: Apron_Red | C43: CRASOME Polyester Kitchen Apron for Men Women Chef Cooking Restaurants gardening workshop, barbers With Pockets and Adjustable Strap ( Red ) | D43: Apron | E43: =IF(ISNUMBER(AD43),IF(AD43>=0,IF(AD43=0,1,INT(AD43/$AC$2)),""),"") -> 1 | F43: =IF(E43="","",IF(AD43=0,0,AD43/$AC$2-E43)) -> 0 | G43: =IF(ISERROR(SEARCH("Apron",D43)),AF43,"") | N43: =IF(ISNUMBER($AF43),1*$AF43,"") | P43: {=XLOOKUP(B43,Weight!B:B,Weight!D:D,"#N/A",0)} -> 140 | Q43: =IF(AF43="","",AF43*P43) | S43: 392620 | T43: 12 | U43: 60 | X43: =SUMIFS('Transit Shipment'!$B$10:$B$1048462,'Transit Shipment'!$A$10:$A$1048462,B43,'Transit Shipment'!$C$10:$C$1048462,AA43) -> 0 | Y43: =IF(SUMIFS(DIH!$S$2:$S833,DIH!$D$2:$D833,B43,DIH!$U$2:$U833,AA43)>0,SUMIFS(DIH!$S$2:$S833,DIH!$D$2:$D833,B43,DIH!$U$2:$U833,AA43),0) -> 0 | Z43: =SUM(X43:Y43) -> 0 | AA43: CJB1 | AB43: =IF(ISNA(VLOOKUP($B43,'Business Report'!$D$2:$J$202,2,0)),"",VLOOKUP($B43,'Business Report'!$D$2:$J$202,2,0)) -> 12 | AC43: =SUMIFS(AFS!$P$2:$P$6260,AFS!$N$2:$N$6260,B43,AFS!$AT$2:$AT$6260,AA43) -> 0 | AD43: =CEILING(AC43/$W$2*$X$2,1)-sum(X43:Y43) -> 0 | AF43: =IF(ISNUMBER(AD43),IF(AD43<=0,"",IF(F43="","",E43*$AC$2+IF(F43>0,$AC$2,0))))
A44: APR- Red | B44: Apron_Red | C44: CRASOME Polyester Kitchen Apron for Men Women Chef Cooking Restaurants gardening workshop, barbers With Pockets and Adjustable Strap ( Red ) | D44: Apron | E44: =IF(ISNUMBER(AD44),IF(AD44>=0,IF(AD44=0,1,INT(AD44/$AC$2)),""),"") -> 1 | F44: =IF(E44="","",IF(AD44=0,0,AD44/$AC$2-E44)) -> 0 | G44: =IF(ISERROR(SEARCH("Apron",D44)),AF44,"") | N44: =IF(ISNUMBER($AF44),1*$AF44,"") | P44: {=XLOOKUP(B44,Weight!B:B,Weight!D:D,"#N/A",0)} -> 140 | Q44: =IF(AF44="","",AF44*P44) | S44: 392620 | T44: 12 | U44: 60 | X44: =SUMIFS('Transit Shipment'!$B$10:$B$1048462,'Transit Shipment'!$A$10:$A$1048462,B44,'Transit Shipment'!$C$10:$C$1048462,AA44) -> 0 | Y44: =IF(SUMIFS(DIH!$S$2:$S833,DIH!$D$2:$D833,B44,DIH!$U$2:$U833,AA44)>0,SUMIFS(DIH!$S$2:$S833,DIH!$D$2:$D833,B44,DIH!$U$2:$U833,AA44),0) -> 0 | Z44: =SUM(X44:Y44) -> 0 | AA44: MAA4 | AB44: =IF(ISNA(VLOOKUP($B44,'Business Report'!$D$2:$J$202,2,0)),"",VLOOKUP($B44,'Business Report'!$D$2:$J$202,2,0)) -> 12 | AC44: =SUMIFS(AFS!$P$2:$P$6260,AFS!$N$2:$N$6260,B44,AFS!$AT$2:$AT$6260,AA44) -> 0 | AD44: =CEILING(AC44/$W$2*$X$2,1)-sum(X44:Y44) -> 0 | AF44: =IF(ISNUMBER(AD44),IF(AD44<=0,"",IF(F44="","",E44*$AC$2+IF(F44>0,$AC$2,0))))
A45: APR- Red | B45: Apron_Red | C45: CRASOME Polyester Kitchen Apron for Men Women Chef Cooking Restaurants gardening workshop, barbers With Pockets and Adjustable Strap ( Red ) | D45: Apron | E45: =IF(ISNUMBER(AD45),IF(AD45>=0,IF(AD45=0,1,INT(AD45/$AC$2)),""),"") -> 1 | F45: =IF(E45="","",IF(AD45=0,0,AD45/$AC$2-E45)) -> 0 | G45: =IF(ISERROR(SEARCH("Apron",D45)),AF45,"") | N45: =IF(ISNUMBER($AF45),1*$AF45,"") | P45: {=XLOOKUP(B45,Weight!B:B,Weight!D:D,"#N/A",0)} -> 140 | Q45: =IF(AF45="","",AF45*P45) | S45: 392620 | T45: 12 | U45: 60 | X45: =SUMIFS('Transit Shipment'!$B$10:$B$1048462,'Transit Shipment'!$A$10:$A$1048462,B45,'Transit Shipment'!$C$10:$C$1048462,AA45) -> 0 | Y45: =IF(SUMIFS(DIH!$S$2:$S833,DIH!$D$2:$D833,B45,DIH!$U$2:$U833,AA45)>0,SUMIFS(DIH!$S$2:$S833,DIH!$D$2:$D833,B45,DIH!$U$2:$U833,AA45),0) -> 0 | Z45: =SUM(X45:Y45) -> 0 | AA45: DEL4 | AB45: =IF(ISNA(VLOOKUP($B45,'Business Report'!$D$2:$J$202,2,0)),"",VLOOKUP($B45,'Business Report'!$D$2:$J$202,2,0)) -> 12 | AC45: =SUMIFS(AFS!$P$2:$P$6260,AFS!$N$2:$N$6260,B45,AFS!$AT$2:$AT$6260,AA45) -> 0 | AD45: =CEILING(AC45/$W$2*$X$2,1)-sum(X45:Y45) -> 0 | AF45: =IF(ISNUMBER(AD45),IF(AD45<=0,"",IF(F45="","",E45*$AC$2+IF(F45>0,$AC$2,0))))
A46: APR- Red | B46: Apron_Red | C46: CRASOME Polyester Kitchen Apron for Men Women Chef Cooking Restaurants gardening workshop, barbers With Pockets and Adjustable Strap ( Red ) | D46: Apron | E46: =IF(ISNUMBER(AD46),IF(AD46>=0,IF(AD46=0,1,INT(AD46/$AC$2)),""),"") -> 1 | F46: =IF(E46="","",IF(AD46=0,0,AD46/$AC$2-E46)) -> 0 | G46: =IF(ISERROR(SEARCH("Apron",D46)),AF46,"") | N46: =IF(ISNUMBER($AF46),1*$AF46,"") -> 2 | P46: {=XLOOKUP(B46,Weight!B:B,Weight!D:D,"#N/A",0)} -> 140 | Q46: =IF(AF46="","",AF46*P46) -> 280 | S46: 392620 | T46: 12 | U46: 60 | X46: =SUMIFS('Transit Shipment'!$B$10:$B$1048462,'Transit Shipment'!$A$10:$A$1048462,B46,'Transit Shipment'!$C$10:$C$1048462,AA46) -> 0 | Y46: =IF(SUMIFS(DIH!$S$2:$S833,DIH!$D$2:$D833,B46,DIH!$U$2:$U833,AA46)>0,SUMIFS(DIH!$S$2:$S833,DIH!$D$2:$D833,B46,DIH!$U$2:$U833,AA46),0) -> 0 | Z46: =SUM(X46:Y46) -> 0 | AA46: DEL5 | AB46: =IF(ISNA(VLOOKUP($B46,'Business Report'!$D$2:$J$202,2,0)),"",VLOOKUP($B46,'Business Report'!$D$2:$J$202,2,0)) -> 12 | AC46: =SUMIFS(AFS!$P$2:$P$6260,AFS!$N$2:$N$6260,B46,AFS!$AT$2:$AT$6260,AA46) -> 1 | AD46: =CEILING(AC46/$W$2*$X$2,1)-sum(X46:Y46) -> 2 | AF46: =IF(ISNUMBER(AD46),IF(AD46<=0,"",IF(F46="","",E46*$AC$2+IF(F46>0,$AC$2,0)))) -> 2
A47: APR- Red | B47: Apron_Red | C47: CRASOME Polyester Kitchen Apron for Men Women Chef Cooking Restaurants gardening workshop, barbers With Pockets and Adjustable Strap ( Red ) | D47: Apron | E47: =IF(ISNUMBER(AD47),IF(AD47>=0,IF(AD47=0,1,INT(AD47/$AC$2)),""),"") -> 1 | F47: =IF(E47="","",IF(AD47=0,0,AD47/$AC$2-E47)) -> 0.5 | G47: =IF(ISERROR(SEARCH("Apron",D47)),AF47,"") | N47: =IF(ISNUMBER($AF47),1*$AF47,"") -> 4 | P47: {=XLOOKUP(B47,Weight!B:B,Weight!D:D,"#N/A",0)} -> 140 | Q47: =IF(AF47="","",AF47*P47) -> 560 | S47: 392620 | T47: 12 | U47: 60 | X47: =SUMIFS('Transit Shipment'!$B$10:$B$1048462,'Transit Shipment'!$A$10:$A$1048462,B47,'Transit Shipment'!$C$10:$C$1048462,AA47) -> 0 | Y47: =IF(SUMIFS(DIH!$S$2:$S833,DIH!$D$2:$D833,B47,DIH!$U$2:$U833,AA47)>0,SUMIFS(DIH!$S$2:$S833,DIH!$D$2:$D833,B47,DIH!$U$2:$U833,AA47),0) -> 0 | Z47: =SUM(X47:Y47) -> 0 | AA47: BOM5 | AB47: =IF(ISNA(VLOOKUP($B47,'Business Report'!$D$2:$J$202,2,0)),"",VLOOKUP($B47,'Business Report'!$D$2:$J$202,2,0)) -> 12 | AC47: =SUMIFS(AFS!$P$2:$P$6260,AFS!$N$2:$N$6260,B47,AFS!$AT$2:$AT$6260,AA47) -> 2 | AD47: =CEILING(AC47/$W$2*$X$2,1)-sum(X47:Y47) -> 3 | AF47: =IF(ISNUMBER(AD47),IF(AD47<=0,"",IF(F47="","",E47*$AC$2+IF(F47>0,$AC$2,0)))) -> 4
A48: APR- Red | B48: Apron_Red | C48: CRASOME Polyester Kitchen Apron for Men Women Chef Cooking Restaurants gardening workshop, barbers With Pockets and Adjustable Strap ( Red ) | D48: Apron | E48: =IF(ISNUMBER(AD48),IF(AD48>=0,IF(AD48=0,1,INT(AD48/$AC$2)),""),"") -> 1 | F48: =IF(E48="","",IF(AD48=0,0,AD48/$AC$2-E48)) -> 0 | G48: =IF(ISERROR(SEARCH("Apron",D48)),AF48,"") | N48: =IF(ISNUMBER($AF48),1*$AF48,"") | P48: {=XLOOKUP(B48,Weight!B:B,Weight!D:D,"#N/A",0)} -> 140 | Q48: =IF(AF48="","",AF48*P48) | S48: 392620 | T48: 12 | U48: 60 | X48: =SUMIFS('Transit Shipment'!$B$10:$B$1048462,'Transit Shipment'!$A$10:$A$1048462,B48,'Transit Shipment'!$C$10:$C$1048462,AA48) -> 0 | Y48: =IF(SUMIFS(DIH!$S$2:$S833,DIH!$D$2:$D833,B48,DIH!$U$2:$U833,AA48)>0,SUMIFS(DIH!$S$2:$S833,DIH!$D$2:$D833,B48,DIH!$U$2:$U833,AA48),0) -> 0 | Z48: =SUM(X48:Y48) -> 0 | AA48: BOM7 | AB48: =IF(ISNA(VLOOKUP($B48,'Business Report'!$D$2:$J$202,2,0)),"",VLOOKUP($B48,'Business Report'!$D$2:$J$202,2,0)) -> 12 | AC48: =SUMIFS(AFS!$P$2:$P$6260,AFS!$N$2:$N$6260,B48,AFS!$AT$2:$AT$6260,AA48) -> 0 | AD48: =CEILING(AC48/$W$2*$X$2,1)-sum(X48:Y48) -> 0 | AE48: =SUM(AD40:AD48) -> 9 | AF48: =IF(ISNUMBER(AD48),IF(AD48<=0,"",IF(F48="","",E48*$AC$2+IF(F48>0,$AC$2,0))))
A49: APR- Tan | B49: CRM_AP_TAN | C49: CRASOME Apron for Men Women Chef Cooking Restaurants Gardening Workshop, Barbers with Adjustable Strap and Two Pockets | D49: Apron | E49: =IF(ISNUMBER(AD49),IF(AD49>=0,IF(AD49=0,1,INT(AD49/$AC$2)),""),"") -> 1 | F49: =IF(E49="","",IF(AD49=0,0,AD49/$AC$2-E49)) -> 0 | G49: =IF(ISERROR(SEARCH("Apron",D49)),AF49,"") | L49: =IF(ISNUMBER($AF49),1*$AF49,"") -> 2 | P49: {=XLOOKUP(B49,Weight!B:B,Weight!D:D,"#N/A",0)} -> 140 | Q49: =IF(AF49="","",AF49*P49) -> 280 | S49: 392620 | T49: 12 | U49: 60 | V49: =B49 -> CRM_AP_TAN | W49: =C49 -> CRASOME Apron for Men Women Chef Cooking Restaurants Gardening Workshop, Barbers with Adjustable Strap and Two Pockets | X49: =SUMIFS('Transit Shipment'!$B$10:$B$1048462,'Transit Shipment'!$A$10:$A$1048462,B49,'Transit Shipment'!$C$10:$C$1048462,AA49) -> 0 | Y49: =IF(SUMIFS(DIH!$S$2:$S833,DIH!$D$2:$D833,B49,DIH!$U$2:$U833,AA49)>0,SUMIFS(DIH!$S$2:$S833,DIH!$D$2:$D833,B49,DIH!$U$2:$U833,AA49),0) -> 0 | Z49: =SUM(X49:Y49) -> 0 | AA49: AMD2 | AB49: =IF(ISNA(VLOOKUP($B49,'Business Report'!$D$2:$J$202,2,0)),"",VLOOKUP($B49,'Business Report'!$D$2:$J$202,2,0)) -> 60 | AC49: =SUMIFS(AFS!$P$2:$P$6260,AFS!$N$2:$N$6260,B49,AFS!$AT$2:$AT$6260,AA49) -> 1 | AD49: =CEILING(AC49/$W$2*$X$2,1)-sum(X49:Y49) -> 2 | AF49: =IF(ISNUMBER(AD49),IF(AD49<=0,"",IF(F49="","",E49*$AC$2+IF(F49>0,$AC$2,0)))) -> 2
A50: APR- Tan | B50: CRM_AP_TAN | C50: CRASOME Apron for Men Women Chef Cooking Restaurants Gardening Workshop, Barbers with Adjustable Strap and Two Pockets | D50: Apron | E50: =IF(ISNUMBER(AD50),IF(AD50>=0,IF(AD50=0,1,INT(AD50/$AC$2)),""),"") -> 8 | F50: =IF(E50="","",IF(AD50=0,0,AD50/$AC$2-E50)) -> 0.5 | G50: =IF(ISERROR(SEARCH("Apron",D50)),AF50,"") | L50: =IF(ISNUMBER($AF50),1*$AF50,"") -> 18 | P50: {=XLOOKUP(B50,Weight!B:B,Weight!D:D,"#N/A",0)} -> 140 | Q50: =IF(AF50="","",AF50*P50) -> 2520 | S50: 392620 | T50: 12 | U50: 60 | X50: =SUMIFS('Transit Shipment'!$B$10:$B$1048462,'Transit Shipment'!$A$10:$A$1048462,B50,'Transit Shipment'!$C$10:$C$1048462,AA50) -> 0 | Y50: =IF(SUMIFS(DIH!$S$2:$S833,DIH!$D$2:$D833,B50,DIH!$U$2:$U833,AA50)>0,SUMIFS(DIH!$S$2:$S833,DIH!$D$2:$D833,B50,DIH!$U$2:$U833,AA50),0) -> 1 | Z50: =SUM(X50:Y50) -> 1 | AA50: BLR8 | AB50: =IF(ISNA(VLOOKUP($B50,'Business Report'!$D$2:$J$202,2,0)),"",VLOOKUP($B50,'Business Report'!$D$2:$J$202,2,0)) -> 60 | AC50: =SUMIFS(AFS!$P$2:$P$6260,AFS!$N$2:$N$6260,B50,AFS!$AT$2:$AT$6260,AA50) -> 13 | AD50: =CEILING(AC50/$W$2*$X$2,1)-sum(X50:Y50) -> 17 | AF50: =IF(ISNUMBER(AD50),IF(AD50<=0,"",IF(F50="","",E50*$AC$2+IF(F50>0,$AC$2,0)))) -> 18
A51: APR- Tan | B51: CRM_AP_TAN | C51: CRASOME Apron for Men Women Chef Cooking Restaurants Gardening Workshop, Barbers with Adjustable Strap and Two Pockets | D51: Apron | E51: =IF(ISNUMBER(AD51),IF(AD51>=0,IF(AD51=0,1,INT(AD51/$AC$2)),""),"") -> 12 | F51: =IF(E51="","",IF(AD51=0,0,AD51/$AC$2-E51)) -> 0.5 | G51: =IF(ISERROR(SEARCH("Apron",D51)),AF51,"") | L51: =IF(ISNUMBER($AF51),1*$AF51,"") -> 26 | P51: {=XLOOKUP(B51,Weight!B:B,Weight!D:D,"#N/A",0)} -> 140 | Q51: =IF(AF51="","",AF51*P51) -> 3640 | S51: 392620 | T51: 12 | U51: 60 | X51: =SUMIFS('Transit Shipment'!$B$10:$B$1048462,'Transit Shipment'!$A$10:$A$1048462,B51,'Transit Shipment'!$C$10:$C$1048462,AA51) -> 0 | Y51: =IF(SUMIFS(DIH!$S$2:$S833,DIH!$D$2:$D833,B51,DIH!$U$2:$U833,AA51)>0,SUMIFS(DIH!$S$2:$S833,DIH!$D$2:$D833,B51,DIH!$U$2:$U833,AA51),0) -> 3 | Z51: =SUM(X51:Y51) -> 3 | AA51: BLR7 | AB51: =IF(ISNA(VLOOKUP($B51,'Business Report'!$D$2:$J$202,2,0)),"",VLOOKUP($B51,'Business Report'!$D$2:$J$202,2,0)) -> 60 | AC51: =SUMIFS(AFS!$P$2:$P$6260,AFS!$N$2:$N$6260,B51,AFS!$AT$2:$AT$6260,AA51) -> 21 | AD51: =CEILING(AC51/$W$2*$X$2,1)-sum(X51:Y51) -> 25 | AF51: =IF(ISNUMBER(AD51),IF(AD51<=0,"",IF(F51="","",E51*$AC$2+IF(F51>0,$AC$2,0)))) -> 26
A52: APR- Tan | B52: CRM_AP_TAN | C52: CRASOME Apron for Men Women Chef Cooking Restaurants Gardening Workshop, Barbers with Adjustable Strap and Two Pockets | D52: Apron | E52: =IF(ISNUMBER(AD52),IF(AD52>=0,IF(AD52=0,1,INT(AD52/$AC$2)),""),"") -> 1 | F52: =IF(E52="","",IF(AD52=0,0,AD52/$AC$2-E52)) -> 0 | G52: =IF(ISERROR(SEARCH("Apron",D52)),AF52,"") | L52: =IF(ISNUMBER($AF52),1*$AF52,"") | P52: {=XLOOKUP(B52,Weight!B:B,Weight!D:D,"#N/A",0)} -> 140 | Q52: =IF(AF52="","",AF52*P52) | S52: 392620 | T52: 12 | U52: 60 | X52: =SUMIFS('Transit Shipment'!$B$10:$B$1048462,'Transit Shipment'!$A$10:$A$1048462,B52,'Transit Shipment'!$C$10:$C$1048462,AA52) -> 0 | Y52: =IF(SUMIFS(DIH!$S$2:$S833,DIH!$D$2:$D833,B52,DIH!$U$2:$U833,AA52)>0,SUMIFS(DIH!$S$2:$S833,DIH!$D$2:$D833,B52,DIH!$U$2:$U833,AA52),0) -> 2 | Z52: =SUM(X52:Y52) -> 2 | AA52: CJB1 | AB52: =IF(ISNA(VLOOKUP($B52,'Business Report'!$D$2:$J$202,2,0)),"",VLOOKUP($B52,'Business Report'!$D$2:$J$202,2,0)) -> 60 | AC52: =SUMIFS(AFS!$P$2:$P$6260,AFS!$N$2:$N$6260,B52,AFS!$AT$2:$AT$6260,AA52) -> 1 | AD52: =CEILING(AC52/$W$2*$X$2,1)-sum(X52:Y52) -> 0 | AF52: =IF(ISNUMBER(AD52),IF(AD52<=0,"",IF(F52="","",E52*$AC$2+IF(F52>0,$AC$2,0))))
A53: APR- Tan | B53: CRM_AP_TAN | C53: CRASOME Apron for Men Women Chef Cooking Restaurants Gardening Workshop, Barbers with Adjustable Strap and Two Pockets | D53: Apron | E53: =IF(ISNUMBER(AD53),IF(AD53>=0,IF(AD53=0,1,INT(AD53/$AC$2)),""),"") -> 1 | F53: =IF(E53="","",IF(AD53=0,0,AD53/$AC$2-E53)) -> 0 | G53: =IF(ISERROR(SEARCH("Apron",D53)),AF53,"") | L53: =IF(ISNUMBER($AF53),1*$AF53,"") | P53: {=XLOOKUP(B53,Weight!B:B,Weight!D:D,"#N/A",0)} -> 140 | Q53: =IF(AF53="","",AF53*P53) | S53: 392620 | T53: 12 | U53: 60 | X53: =SUMIFS('Transit Shipment'!$B$10:$B$1048462,'Transit Shipment'!$A$10:$A$1048462,B53,'Transit Shipment'!$C$10:$C$1048462,AA53) -> 0 | Y53: =IF(SUMIFS(DIH!$S$2:$S833,DIH!$D$2:$D833,B53,DIH!$U$2:$U833,AA53)>0,SUMIFS(DIH!$S$2:$S833,DIH!$D$2:$D833,B53,DIH!$U$2:$U833,AA53),0) -> 7 | Z53: =SUM(X53:Y53) -> 7 | AA53: MAA4 | AB53: =IF(ISNA(VLOOKUP($B53,'Business Report'!$D$2:$J$202,2,0)),"",VLOOKUP($B53,'Business Report'!$D$2:$J$202,2,0)) -> 60 | AC53: =SUMIFS(AFS!$P$2:$P$6260,AFS!$N$2:$N$6260,B53,AFS!$AT$2:$AT$6260,AA53) -> 5 | AD53: =CEILING(AC53/$W$2*$X$2,1)-sum(X53:Y53) -> 0 | AF53: =IF(ISNUMBER(AD53),IF(AD53<=0,"",IF(F53="","",E53*$AC$2+IF(F53>0,$AC$2,0))))
A54: APR- Tan | B54: CRM_AP_TAN | C54: CRASOME Apron for Men Women Chef Cooking Restaurants Gardening Workshop, Barbers with Adjustable Strap and Two Pockets | D54: Apron | E54: =IF(ISNUMBER(AD54),IF(AD54>=0,IF(AD54=0,1,INT(AD54/$AC$2)),""),"") -> 7 | F54: =IF(E54="","",IF(AD54=0,0,AD54/$AC$2-E54)) -> 0.5 | G54: =IF(ISERROR(SEARCH("Apron",D54)),AF54,"") | L54: =IF(ISNUMBER($AF54),1*$AF54,"") -> 16 | P54: {=XLOOKUP(B54,Weight!B:B,Weight!D:D,"#N/A",0)} -> 140 | Q54: =IF(AF54="","",AF54*P54) -> 2240 | S54: 392620 | T54: 12 | U54: 60 | X54: =SUMIFS('Transit Shipment'!$B$10:$B$1048462,'Transit Shipment'!$A$10:$A$1048462,B54,'Transit Shipment'!$C$10:$C$1048462,AA54) -> 0 | Y54: =IF(SUMIFS(DIH!$S$2:$S833,DIH!$D$2:$D833,B54,DIH!$U$2:$U833,AA54)>0,SUMIFS(DIH!$S$2:$S833,DIH!$D$2:$D833,B54,DIH!$U$2:$U833,AA54),0) -> 8 | Z54: =SUM(X54:Y54) -> 8 | AA54: DEL4 | AB54: =IF(ISNA(VLOOKUP($B54,'Business Report'!$D$2:$J$202,2,0)),"",VLOOKUP($B54,'Business Report'!$D$2:$J$202,2,0)) -> 60 | AC54: =SUMIFS(AFS!$P$2:$P$6260,AFS!$N$2:$N$6260,B54,AFS!$AT$2:$AT$6260,AA54) -> 17 | AD54: =CEILING(AC54/$W$2*$X$2,1)-sum(X54:Y54) -> 15 | AF54: =IF(ISNUMBER(AD54),IF(AD54<=0,"",IF(F54="","",E54*$AC$2+IF(F54>0,$AC$2,0)))) -> 16
A55: APR- Tan | B55: CRM_AP_TAN | C55: CRASOME Apron for Men Women Chef Cooking Restaurants Gardening Workshop, Barbers with Adjustable Strap and Two Pockets | D55: Apron | E55: =IF(ISNUMBER(AD55),IF(AD55>=0,IF(AD55=0,1,INT(AD55/$AC$2)),""),"") -> 1 | F55: =IF(E55="","",IF(AD55=0,0,AD55/$AC$2-E55)) -> 0.5 | G55: =IF(ISERROR(SEARCH("Apron",D55)),AF55,"") | L55: =IF(ISNUMBER($AF55),1*$AF55,"") -> 4 | P55: {=XLOOKUP(B55,Weight!B:B,Weight!D:D,"#N/A",0)} -> 140 | Q55: =IF(AF55="","",AF55*P55) -> 560 | S55: 392620 | T55: 12 | U55: 60 | X55: =SUMIFS('Transit Shipment'!$B$10:$B$1048462,'Transit Shipment'!$A$10:$A$1048462,B55,'Transit Shipment'!$C$10:$C$1048462,AA55) -> 0 | Y55: =IF(SUMIFS(DIH!$S$2:$S833,DIH!$D$2:$D833,B55,DIH!$U$2:$U833,AA55)>0,SUMIFS(DIH!$S$2:$S833,DIH!$D$2:$D833,B55,DIH!$U$2:$U833,AA55),0) -> 0 | Z55: =SUM(X55:Y55) -> 0 | AA55: DEL5 | AB55: =IF(ISNA(VLOOKUP($B55,'Business Report'!$D$2:$J$202,2,0)),"",VLOOKUP($B55,'Business Report'!$D$2:$J$202,2,0)) -> 60 | AC55: =SUMIFS(AFS!$P$2:$P$6260,AFS!$N$2:$N$6260,B55,AFS!$AT$2:$AT$6260,AA55) -> 2 | AD55: =CEILING(AC55/$W$2*$X$2,1)-sum(X55:Y55) -> 3 | AF55: =IF(ISNUMBER(AD55),IF(AD55<=0,"",IF(F55="","",E55*$AC$2+IF(F55>0,$AC$2,0)))) -> 4
A56: APR- Tan | B56: CRM_AP_TAN | C56: CRASOME Apron for Men Women Chef Cooking Restaurants Gardening Workshop, Barbers with Adjustable Strap and Two Pockets | D56: Apron | E56: =IF(ISNUMBER(AD56),IF(AD56>=0,IF(AD56=0,1,INT(AD56/$AC$2)),""),"") -> 2 | F56: =IF(E56="","",IF(AD56=0,0,AD56/$AC$2-E56)) -> 0.5 | G56: =IF(ISERROR(SEARCH("Apron",D56)),AF56,"") | L56: =IF(ISNUMBER($AF56),1*$AF56,"") -> 6 | P56: {=XLOOKUP(B56,Weight!B:B,Weight!D:D,"#N/A",0)} -> 140 | Q56: =IF(AF56="","",AF56*P56) -> 840 | S56: 392620 | T56: 12 | U56: 60 | X56: =SUMIFS('Transit Shipment'!$B$10:$B$1048462,'Transit Shipment'!$A$10:$A$1048462,B56,'Transit Shipment'!$C$10:$C$1048462,AA56) -> 0 | Y56: =IF(SUMIFS(DIH!$S$2:$S833,DIH!$D$2:$D833,B56,DIH!$U$2:$U833,AA56)>0,SUMIFS(DIH!$S$2:$S833,DIH!$D$2:$D833,B56,DIH!$U$2:$U833,AA56),0) -> 1 | Z56: =SUM(X56:Y56) -> 1 | AA56: BOM5 | AB56: =IF(ISNA(VLOOKUP($B56,'Business Report'!$D$2:$J$202,2,0)),"",VLOOKUP($B56,'Business Report'!$D$2:$J$202,2,0)) -> 60 | AC56: =SUMIFS(AFS!$P$2:$P$6260,AFS!$N$2:$N$6260,B56,AFS!$AT$2:$AT$6260,AA56) -> 4 | AD56: =CEILING(AC56/$W$2*$X$2,1)-sum(X56:Y56) -> 5 | AF56: =IF(ISNUMBER(AD56),IF(AD56<=0,"",IF(F56="","",E56*$AC$2+IF(F56>0,$AC$2,0)))) -> 6
A57: APR- Tan | B57: CRM_AP_TAN | C57: CRASOME Apron for Men Women Chef Cooking Restaurants Gardening Workshop, Barbers with Adjustable Strap and Two Pockets | D57: Apron | E57: =IF(ISNUMBER(AD57),IF(AD57>=0,IF(AD57=0,1,INT(AD57/$AC$2)),""),"") -> 0 | F57: =IF(E57="","",IF(AD57=0,0,AD57/$AC$2-E57)) -> 0.5 | G57: =IF(ISERROR(SEARCH("Apron",D57)),AF57,"") | L57: =IF(ISNUMBER($AF57),1*$AF57,"") -> 2 | P57: {=XLOOKUP(B57,Weight!B:B,Weight!D:D,"#N/A",0)} -> 140 | Q57: =IF(AF57="","",AF57*P57) -> 280 | S57: 392620 | T57: 12 | U57: 60 | X57: =SUMIFS('Transit Shipment'!$B$10:$B$1048462,'Transit Shipment'!$A$10:$A$1048462,B57,'Transit Shipment'!$C$10:$C$1048462,AA57) -> 0 | Y57: =IF(SUMIFS(DIH!$S$2:$S833,DIH!$D$2:$D833,B57,DIH!$U$2:$U833,AA57)>0,SUMIFS(DIH!$S$2:$S833,DIH!$D$2:$D833,B57,DIH!$U$2:$U833,AA57),0) -> 1 | Z57: =SUM(X57:Y57) -> 1 | AA57: BOM7 | AB57: =IF(ISNA(VLOOKUP($B57,'Business Report'!$D$2:$J$202,2,0)),"",VLOOKUP($B57,'Business Report'!$D$2:$J$202,2,0)) -> 60 | AC57: =SUMIFS(AFS!$P$2:$P$6260,AFS!$N$2:$N$6260,B57,AFS!$AT$2:$AT$6260,AA57) -> 1 | AD57: =CEILING(AC57/$W$2*$X$2,1)-sum(X57:Y57) -> 1 | AE57: =SUM(AD49:AD57) -> 68 | AF57: =IF(ISNUMBER(AD57),IF(AD57<=0,"",IF(F57="","",E57*$AC$2+IF(F57>0,$AC$2,0)))) -> 2
A58: APR- Green | B58: CRM_AP_GREEN | C58: CRASOME Apron for Men Women Chef Cooking Restaurants Gardening Workshop, Barbers with Adjustable Strap and Two Pockets | D58: Apron | E58: =IF(ISNUMBER(AD58),IF(AD58>=0,IF(AD58=0,1,INT(AD58/$AC$2)),""),"") | F58: =IF(E58="","",IF(AD58=0,0,AD58/$AC$2-E58)) | G58: =IF(ISERROR(SEARCH("Apron",D58)),AF58,"") | K58: =IF(ISNUMBER($AF58),1*$AF58,"") | P58: {=XLOOKUP(B58,Weight!B:B,Weight!D:D,"#N/A",0)} -> 140 | Q58: =IF(AF58="","",AF58*P58) | S58: 392620 | T58: 12 | U58: 60 | V58: =B58 -> CRM_AP_GREEN | W58: =C58 -> CRASOME Apron for Men Women Chef Cooking Restaurants Gardening Workshop, Barbers with Adjustable Strap and Two Pockets | X58: =SUMIFS('Transit Shipment'!$B$10:$B$1048462,'Transit Shipment'!$A$10:$A$1048462,B58,'Transit Shipment'!$C$10:$C$1048462,AA58) -> 0 | Y58: =IF(SUMIFS(DIH!$S$2:$S833,DIH!$D$2:$D833,B58,DIH!$U$2:$U833,AA58)>0,SUMIFS(DIH!$S$2:$S833,DIH!$D$2:$D833,B58,DIH!$U$2:$U833,AA58),0) -> 6 | Z58: =SUM(X58:Y58) -> 6 | AA58: AMD2 | AB58: =IF(ISNA(VLOOKUP($B58,'Business Report'!$D$2:$J$202,2,0)),"",VLOOKUP($B58,'Business Report'!$D$2:$J$202,2,0)) -> 27 | AC58: =SUMIFS(AFS!$P$2:$P$6260,AFS!$N$2:$N$6260,B58,AFS!$AT$2:$AT$6260,AA58) -> 1 | AD58: =CEILING(AC58/$W$2*$X$2,1)-sum(X58:Y58) -> -4 | AF58: =IF(ISNUMBER(AD58),IF(AD58<=0,"",IF(F58="","",E58*$AC$2+IF(F58>0,$AC$2,0))))
A59: APR- Green | B59: CRM_AP_GREEN | C59: CRASOME Apron for Men Women Chef Cooking Restaurants Gardening Workshop, Barbers with Adjustable Strap and Two Pockets | D59: Apron | E59: =IF(ISNUMBER(AD59),IF(AD59>=0,IF(AD59=0,1,INT(AD59/$AC$2)),""),"") | F59: =IF(E59="","",IF(AD59=0,0,AD59/$AC$2-E59)) | G59: =IF(ISERROR(SEARCH("Apron",D59)),AF59,"") | K59: =IF(ISNUMBER($AF59),1*$AF59,"") | P59: {=XLOOKUP(B59,Weight!B:B,Weight!D:D,"#N/A",0)} -> 140 | Q59: =IF(AF59="","",AF59*P59) | S59: 392620 | T59: 12 | U59: 60 | X59: =SUMIFS('Transit Shipment'!$B$10:$B$1048462,'Transit Shipment'!$A$10:$A$1048462,B59,'Transit Shipment'!$C$10:$C$1048462,AA59) -> 0 | Y59: =IF(SUMIFS(DIH!$S$2:$S833,DIH!$D$2:$D833,B59,DIH!$U$2:$U833,AA59)>0,SUMIFS(DIH!$S$2:$S833,DIH!$D$2:$D833,B59,DIH!$U$2:$U833,AA59),0) -> 25 | Z59: =SUM(X59:Y59) -> 25 | AA59: BLR8 | AB59: =IF(ISNA(VLOOKUP($B59,'Business Report'!$D$2:$J$202,2,0)),"",VLOOKUP($B59,'Business Report'!$D$2:$J$202,2,0)) -> 27 | AC59: =SUMIFS(AFS!$P$2:$P$6260,AFS!$N$2:$N$6260,B59,AFS!$AT$2:$AT$6260,AA59) -> 1 | AD59: =CEILING(AC59/$W$2*$X$2,1)-sum(X59:Y59) -> -23 | AF59: =IF(ISNUMBER(AD59),IF(AD59<=0,"",IF(F59="","",E59*$AC$2+IF(F59>0,$AC$2,0))))
A60: APR- Green | B60: CRM_AP_GREEN | C60: CRASOME Apron for Men Women Chef Cooking Restaurants Gardening Workshop, Barbers with Adjustable Strap and Two Pockets | D60: Apron | E60: =IF(ISNUMBER(AD60),IF(AD60>=0,IF(AD60=0,1,INT(AD60/$AC$2)),""),"") -> 5 | F60: =IF(E60="","",IF(AD60=0,0,AD60/$AC$2-E60)) -> 0.5 | G60: =IF(ISERROR(SEARCH("Apron",D60)),AF60,"") | K60: =IF(ISNUMBER($AF60),1*$AF60,"") -> 12 | P60: {=XLOOKUP(B60,Weight!B:B,Weight!D:D,"#N/A",0)} -> 140 | Q60: =IF(AF60="","",AF60*P60) -> 1680 | S60: 392620 | T60: 12 | U60: 60 | X60: =SUMIFS('Transit Shipment'!$B$10:$B$1048462,'Transit Shipment'!$A$10:$A$1048462,B60,'Transit Shipment'!$C$10:$C$1048462,AA60) -> 0 | Y60: =IF(SUMIFS(DIH!$S$2:$S833,DIH!$D$2:$D833,B60,DIH!$U$2:$U833,AA60)>0,SUMIFS(DIH!$S$2:$S833,DIH!$D$2:$D833,B60,DIH!$U$2:$U833,AA60),0) -> 8 | Z60: =SUM(X60:Y60) -> 8 | AA60: BLR7 | AB60: =IF(ISNA(VLOOKUP($B60,'Business Report'!$D$2:$J$202,2,0)),"",VLOOKUP($B60,'Business Report'!$D$2:$J$202,2,0)) -> 27 | AC60: =SUMIFS(AFS!$P$2:$P$6260,AFS!$N$2:$N$6260,B60,AFS!$AT$2:$AT$6260,AA60) -> 14 | AD60: =CEILING(AC60/$W$2*$X$2,1)-sum(X60:Y60) -> 11 | AF60: =IF(ISNUMBER(AD60),IF(AD60<=0,"",IF(F60="","",E60*$AC$2+IF(F60>0,$AC$2,0)))) -> 12
A61: APR- Green | B61: CRM_AP_GREEN | C61: CRASOME Apron for Men Women Chef Cooking Restaurants Gardening Workshop, Barbers with Adjustable Strap and Two Pockets | D61: Apron | E61: =IF(ISNUMBER(AD61),IF(AD61>=0,IF(AD61=0,1,INT(AD61/$AC$2)),""),"") | F61: =IF(E61="","",IF(AD61=0,0,AD61/$AC$2-E61)) | G61: =IF(ISERROR(SEARCH("Apron",D61)),AF61,"") | K61: =IF(ISNUMBER($AF61),1*$AF61,"") | P61: {=XLOOKUP(B61,Weight!B:B,Weight!D:D,"#N/A",0)} -> 140 | Q61: =IF(AF61="","",AF61*P61) | S61: 392620 | T61: 12 | U61: 60 | X61: =SUMIFS('Transit Shipment'!$B$10:$B$1048462,'Transit Shipment'!$A$10:$A$1048462,B61,'Transit Shipment'!$C$10:$C$1048462,AA61) -> 0 | Y61: =IF(SUMIFS(DIH!$S$2:$S833,DIH!$D$2:$D833,B61,DIH!$U$2:$U833,AA61)>0,SUMIFS(DIH!$S$2:$S833,DIH!$D$2:$D833,B61,DIH!$U$2:$U833,AA61),0) -> 1 | Z61: =SUM(X61:Y61) -> 1 | AA61: CJB1 | AB61: =IF(ISNA(VLOOKUP($B61,'Business Report'!$D$2:$J$202,2,0)),"",VLOOKUP($B61,'Business Report'!$D$2:$J$202,2,0)) -> 27 | AC61: =SUMIFS(AFS!$P$2:$P$6260,AFS!$N$2:$N$6260,B61,AFS!$AT$2:$AT$6260,AA61) -> 0 | AD61: =CEILING(AC61/$W$2*$X$2,1)-sum(X61:Y61) -> -1 | AF61: =IF(ISNUMBER(AD61),IF(AD61<=0,"",IF(F61="","",E61*$AC$2+IF(F61>0,$AC$2,0))))
A62: APR- Green | B62: CRM_AP_GREEN | C62: CRASOME Apron for Men Women Chef Cooking Restaurants Gardening Workshop, Barbers with Adjustable Strap and Two Pockets | D62: Apron | E62: =IF(ISNUMBER(AD62),IF(AD62>=0,IF(AD62=0,1,INT(AD62/$AC$2)),""),"") | F62: =IF(E62="","",IF(AD62=0,0,AD62/$AC$2-E62)) | G62: =IF(ISERROR(SEARCH("Apron",D62)),AF62,"") | K62: =IF(ISNUMBER($AF62),1*$AF62,"") | P62: {=XLOOKUP(B62,Weight!B:B,Weight!D:D,"#N/A",0)} -> 140 | Q62: =IF(AF62="","",AF62*P62) | S62: 392620 | T62: 12 | U62: 60 | X62: =SUMIFS('Transit Shipment'!$B$10:$B$1048462,'Transit Shipment'!$A$10:$A$1048462,B62,'Transit Shipment'!$C$10:$C$1048462,AA62) -> 0 | Y62: =IF(SUMIFS(DIH!$S$2:$S833,DIH!$D$2:$D833,B62,DIH!$U$2:$U833,AA62)>0,SUMIFS(DIH!$S$2:$S833,DIH!$D$2:$D833,B62,DIH!$U$2:$U833,AA62),0) -> 7 | Z62: =SUM(X62:Y62) -> 7 | AA62: MAA4 | AB62: =IF(ISNA(VLOOKUP($B62,'Business Report'!$D$2:$J$202,2,0)),"",VLOOKUP($B62,'Business Report'!$D$2:$J$202,2,0)) -> 27 | AC62: =SUMIFS(AFS!$P$2:$P$6260,AFS!$N$2:$N$6260,B62,AFS!$AT$2:$AT$6260,AA62) -> 0 | AD62: =CEILING(AC62/$W$2*$X$2,1)-sum(X62:Y62) -> -7 | AF62: =IF(ISNUMBER(AD62),IF(AD62<=0,"",IF(F62="","",E62*$AC$2+IF(F62>0,$AC$2,0))))
A63: APR- Green | B63: CRM_AP_GREEN | C63: CRASOME Apron for Men Women Chef Cooking Restaurants Gardening Workshop, Barbers with Adjustable Strap and Two Pockets | D63: Apron | E63: =IF(ISNUMBER(AD63),IF(AD63>=0,IF(AD63=0,1,INT(AD63/$AC$2)),""),"") | F63: =IF(E63="","",IF(AD63=0,0,AD63/$AC$2-E63)) | G63: =IF(ISERROR(SEARCH("Apron",D63)),AF63,"") | K63: =IF(ISNUMBER($AF63),1*$AF63,"") | P63: {=XLOOKUP(B63,Weight!B:B,Weight!D:D,"#N/A",0)} -> 140 | Q63: =IF(AF63="","",AF63*P63) | S63: 392620 | T63: 12 | U63: 60 | X63: =SUMIFS('Transit Shipment'!$B$10:$B$1048462,'Transit Shipment'!$A$10:$A$1048462,B63,'Transit Shipment'!$C$10:$C$1048462,AA63) -> 0 | Y63: =IF(SUMIFS(DIH!$S$2:$S833,DIH!$D$2:$D833,B63,DIH!$U$2:$U833,AA63)>0,SUMIFS(DIH!$S$2:$S833,DIH!$D$2:$D833,B63,DIH!$U$2:$U833,AA63),0) -> 5 | Z63: =SUM(X63:Y63) -> 5 | AA63: DEL4 | AB63: =IF(ISNA(VLOOKUP($B63,'Business Report'!$D$2:$J$202,2,0)),"",VLOOKUP($B63,'Business Report'!$D$2:$J$202,2,0)) -> 27 | AC63: =SUMIFS(AFS!$P$2:$P$6260,AFS!$N$2:$N$6260,B63,AFS!$AT$2:$AT$6260,AA63) -> 2 | AD63: =CEILING(AC63/$W$2*$X$2,1)-sum(X63:Y63) -> -2 | AF63: =IF(ISNUMBER(AD63),IF(AD63<=0,"",IF(F63="","",E63*$AC$2+IF(F63>0,$AC$2,0))))
A64: APR- Green | B64: CRM_AP_GREEN | C64: CRASOME Apron for Men Women Chef Cooking Restaurants Gardening Workshop, Barbers with Adjustable Strap and Two Pockets | D64: Apron | E64: =IF(ISNUMBER(AD64),IF(AD64>=0,IF(AD64=0,1,INT(AD64/$AC$2)),""),"") -> 6 | F64: =IF(E64="","",IF(AD64=0,0,AD64/$AC$2-E64)) -> 0.5 | G64: =IF(ISERROR(SEARCH("Apron",D64)),AF64,"") | K64: =IF(ISNUMBER($AF64),1*$AF64,"") -> 14 | P64: {=XLOOKUP(B64,Weight!B:B,Weight!D:D,"#N/A",0)} -> 140 | Q64: =IF(AF64="","",AF64*P64) -> 1960 | S64: 392620 | T64: 12 | U64: 60 | X64: =SUMIFS('Transit Shipment'!$B$10:$B$1048462,'Transit Shipment'!$A$10:$A$1048462,B64,'Transit Shipment'!$C$10:$C$1048462,AA64) -> 0 | Y64: =IF(SUMIFS(DIH!$S$2:$S833,DIH!$D$2:$D833,B64,DIH!$U$2:$U833,AA64)>0,SUMIFS(DIH!$S$2:$S833,DIH!$D$2:$D833,B64,DIH!$U$2:$U833,AA64),0) -> 1 | Z64: =SUM(X64:Y64) -> 1 | AA64: DEL5 | AB64: =IF(ISNA(VLOOKUP($B64,'Business Report'!$D$2:$J$202,2,0)),"",VLOOKUP($B64,'Business Report'!$D$2:$J$202,2,0)) -> 27 | AC64: =SUMIFS(AFS!$P$2:$P$6260,AFS!$N$2:$N$6260,B64,AFS!$AT$2:$AT$6260,AA64) -> 10 | AD64: =CEILING(AC64/$W$2*$X$2,1)-sum(X64:Y64) -> 13 | AF64: =IF(ISNUMBER(AD64),IF(AD64<=0,"",IF(F64="","",E64*$AC$2+IF(F64>0,$AC$2,0)))) -> 14
A65: APR- Green | B65: CRM_AP_GREEN | C65: CRASOME Apron for Men Women Chef Cooking Restaurants Gardening Workshop, Barbers with Adjustable Strap and Two Pockets | D65: Apron | E65: =IF(ISNUMBER(AD65),IF(AD65>=0,IF(AD65=0,1,INT(AD65/$AC$2)),""),"") | F65: =IF(E65="","",IF(AD65=0,0,AD65/$AC$2-E65)) | G65: =IF(ISERROR(SEARCH("Apron",D65)),AF65,"") | K65: =IF(ISNUMBER($AF65),1*$AF65,"") | P65: {=XLOOKUP(B65,Weight!B:B,Weight!D:D,"#N/A",0)} -> 140 | Q65: =IF(AF65="","",AF65*P65) | S65: 392620 | T65: 12 | U65: 60 | X65: =SUMIFS('Transit Shipment'!$B$10:$B$1048462,'Transit Shipment'!$A$10:$A$1048462,B65,'Transit Shipment'!$C$10:$C$1048462,AA65) -> 0 | Y65: =IF(SUMIFS(DIH!$S$2:$S833,DIH!$D$2:$D833,B65,DIH!$U$2:$U833,AA65)>0,SUMIFS(DIH!$S$2:$S833,DIH!$D$2:$D833,B65,DIH!$U$2:$U833,AA65),0) -> 4 | Z65: =SUM(X65:Y65) -> 4 | AA65: BOM5 | AB65: =IF(ISNA(VLOOKUP($B65,'Business Report'!$D$2:$J$202,2,0)),"",VLOOKUP($B65,'Business Report'!$D$2:$J$202,2,0)) -> 27 | AC65: =SUMIFS(AFS!$P$2:$P$6260,AFS!$N$2:$N$6260,B65,AFS!$AT$2:$AT$6260,AA65) -> 0 | AD65: =CEILING(AC65/$W$2*$X$2,1)-sum(X65:Y65) -> -4 | AF65: =IF(ISNUMBER(AD65),IF(AD65<=0,"",IF(F65="","",E65*$AC$2+IF(F65>0,$AC$2,0))))
A66: APR- Green | B66: CRM_AP_GREEN | C66: CRASOME Apron for Men Women Chef Cooking Restaurants Gardening Workshop, Barbers with Adjustable Strap and Two Pockets | D66: Apron | E66: =IF(ISNUMBER(AD66),IF(AD66>=0,IF(AD66=0,1,INT(AD66/$AC$2)),""),"") -> 1 | F66: =IF(E66="","",IF(AD66=0,0,AD66/$AC$2-E66)) -> 0 | G66: =IF(ISERROR(SEARCH("Apron",D66)),AF66,"") | K66: =IF(ISNUMBER($AF66),1*$AF66,"") | P66: {=XLOOKUP(B66,Weight!B:B,Weight!D:D,"#N/A",0)} -> 140 | Q66: =IF(AF66="","",AF66*P66) | S66: 392620 | T66: 12 | U66: 60 | X66: =SUMIFS('Transit Shipment'!$B$10:$B$1048462,'Transit Shipment'!$A$10:$A$1048462,B66,'Transit Shipment'!$C$10:$C$1048462,AA66) -> 0 | Y66: =IF(SUMIFS(DIH!$S$2:$S833,DIH!$D$2:$D833,B66,DIH!$U$2:$U833,AA66)>0,SUMIFS(DIH!$S$2:$S833,DIH!$D$2:$D833,B66,DIH!$U$2:$U833,AA66),0) -> 2 | Z66: =SUM(X66:Y66) -> 2 | AA66: BOM7 | AB66: =IF(ISNA(VLOOKUP($B66,'Business Report'!$D$2:$J$202,2,0)),"",VLOOKUP($B66,'Business Report'!$D$2:$J$202,2,0)) -> 27 | AC66: =SUMIFS(AFS!$P$2:$P$6260,AFS!$N$2:$N$6260,B66,AFS!$AT$2:$AT$6260,AA66) -> 1 | AD66: =CEILING(AC66/$W$2*$X$2,1)-sum(X66:Y66) -> 0 | AE66: =SUM(AD58:AD66) -> -17 | AF66: =IF(ISNUMBER(AD66),IF(AD66<=0,"",IF(F66="","",E66*$AC$2+IF(F66>0,$AC$2,0))))
A67: APR- Black | B67: CRM_AP_BLACK_PACK OF 2 | C67: CRASOME Apron for Men Women Chef Cooking Restaurants Gardening Workshop, Barbers with Adjustable Strap and Two Pockets (Black_Pack of 2) | D67: Apron | E67: =IF(ISNUMBER(AD67),IF(AD67>=0,IF(AD67=0,1,INT(AD67/$AC$2)),""),"") -> 1 | F67: =IF(E67="","",IF(AD67=0,0,AD67/$AC$2-E67)) -> 0.5 | G67: =IF(ISERROR(SEARCH("Apron",D67)),AF67,"") | M67: =IF(ISNUMBER($AF67),2*$AF67,"") -> 8 | P67: {=XLOOKUP(B67,Weight!B:B,Weight!D:D,"#N/A",0)} -> 220 | Q67: =IF(AF67="","",AF67*P67) -> 880 | S67: 392620 | T67: 12 | U67: 120 | V67: =B67 -> CRM_AP_BLACK_PACK OF 2 | W67: =C67 -> CRASOME Apron for Men Women Chef Cooking Restaurants Gardening Workshop, Barbers with Adjustable Strap and Two Pockets (Black_Pack of 2) | X67: =SUMIFS('Transit Shipment'!$B$10:$B$1048462,'Transit Shipment'!$A$10:$A$1048462,B67,'Transit Shipment'!$C$10:$C$1048462,AA67) -> 0 | Y67: =IF(SUMIFS(DIH!$S$2:$S833,DIH!$D$2:$D833,B67,DIH!$U$2:$U833,AA67)>0,SUMIFS(DIH!$S$2:$S833,DIH!$D$2:$D833,B67,DIH!$U$2:$U833,AA67),0) -> 1 | Z67: =SUM(X67:Y67) -> 1 | AA67: AMD2 | AB67: =IF(ISNA(VLOOKUP($B67,'Business Report'!$D$2:$J$202,2,0)),"",VLOOKUP($B67,'Business Report'!$D$2:$J$202,2,0)) -> 89 | AC67: =SUMIFS(AFS!$P$2:$P$6260,AFS!$N$2:$N$6260,B67,AFS!$AT$2:$AT$6260,AA67) -> 3 | AD67: =CEILING(AC67/$W$2*$X$2,1)-sum(X67:Y67) -> 3 | AF67: =IF(ISNUMBER(AD67),IF(AD67<=0,"",IF(F67="","",E67*$AC$2+IF(F67>0,$AC$2,0)))) -> 4
A68: APR- Black | B68: CRM_AP_BLACK_PACK OF 2 | C68: CRASOME Apron for Men Women Chef Cooking Restaurants Gardening Workshop, Barbers with Adjustable Strap and Two Pockets (Black_Pack of 2) | D68: Apron | E68: =IF(ISNUMBER(AD68),IF(AD68>=0,IF(AD68=0,1,INT(AD68/$AC$2)),""),"") | F68: =IF(E68="","",IF(AD68=0,0,AD68/$AC$2-E68)) | G68: =IF(ISERROR(SEARCH("Apron",D68)),AF68,"") | M68: =IF(ISNUMBER($AF68),2*$AF68,"") | P68: {=XLOOKUP(B68,Weight!B:B,Weight!D:D,"#N/A",0)} -> 220 | Q68: =IF(AF68="","",AF68*P68) | S68: 392620 | T68: 12 | U68: 120 | X68: =SUMIFS('Transit Shipment'!$B$10:$B$1048462,'Transit Shipment'!$A$10:$A$1048462,B68,'Transit Shipment'!$C$10:$C$1048462,AA68) -> 0 | Y68: =IF(SUMIFS(DIH!$S$2:$S833,DIH!$D$2:$D833,B68,DIH!$U$2:$U833,AA68)>0,SUMIFS(DIH!$S$2:$S833,DIH!$D$2:$D833,B68,DIH!$U$2:$U833,AA68),0) -> 11 | Z68: =SUM(X68:Y68) -> 11 | AA68: BLR8 | AB68: =IF(ISNA(VLOOKUP($B68,'Business Report'!$D$2:$J$202,2,0)),"",VLOOKUP($B68,'Business Report'!$D$2:$J$202,2,0)) -> 89 | AC68: =SUMIFS(AFS!$P$2:$P$6260,AFS!$N$2:$N$6260,B68,AFS!$AT$2:$AT$6260,AA68) -> 2 | AD68: =CEILING(AC68/$W$2*$X$2,1)-sum(X68:Y68) -> -8 | AF68: =IF(ISNUMBER(AD68),IF(AD68<=0,"",IF(F68="","",E68*$AC$2+IF(F68>0,$AC$2,0))))
A69: APR- Black | B69: CRM_AP_BLACK_PACK OF 2 | C69: CRASOME Apron for Men Women Chef Cooking Restaurants Gardening Workshop, Barbers with Adjustable Strap and Two Pockets (Black_Pack of 2) | D69: Apron | E69: =IF(ISNUMBER(AD69),IF(AD69>=0,IF(AD69=0,1,INT(AD69/$AC$2)),""),"") | F69: =IF(E69="","",IF(AD69=0,0,AD69/$AC$2-E69)) | G69: =IF(ISERROR(SEARCH("Apron",D69)),AF69,"") | M69: =IF(ISNUMBER($AF69),2*$AF69,"") | P69: {=XLOOKUP(B69,Weight!B:B,Weight!D:D,"#N/A",0)} -> 220 | Q69: =IF(AF69="","",AF69*P69) | S69: 392620 | T69: 12 | U69: 120 | X69: =SUMIFS('Transit Shipment'!$B$10:$B$1048462,'Transit Shipment'!$A$10:$A$1048462,B69,'Transit Shipment'!$C$10:$C$1048462,AA69) -> 0 | Y69: =IF(SUMIFS(DIH!$S$2:$S833,DIH!$D$2:$D833,B69,DIH!$U$2:$U833,AA69)>0,SUMIFS(DIH!$S$2:$S833,DIH!$D$2:$D833,B69,DIH!$U$2:$U833,AA69),0) -> 12 | Z69: =SUM(X69:Y69) -> 12 | AA69: BLR7 | AB69: =IF(ISNA(VLOOKUP($B69,'Business Report'!$D$2:$J$202,2,0)),"",VLOOKUP($B69,'Business Report'!$D$2:$J$202,2,0)) -> 89 | AC69: =SUMIFS(AFS!$P$2:$P$6260,AFS!$N$2:$N$6260,B69,AFS!$AT$2:$AT$6260,AA69) -> 8 | AD69: =CEILING(AC69/$W$2*$X$2,1)-sum(X69:Y69) -> -1 | AF69: =IF(ISNUMBER(AD69),IF(AD69<=0,"",IF(F69="","",E69*$AC$2+IF(F69>0,$AC$2,0))))
A70: APR- Black | B70: CRM_AP_BLACK_PACK OF 2 | C70: CRASOME Apron for Men Women Chef Cooking Restaurants Gardening Workshop, Barbers with Adjustable Strap and Two Pockets (Black_Pack of 2) | D70: Apron | E70: =IF(ISNUMBER(AD70),IF(AD70>=0,IF(AD70=0,1,INT(AD70/$AC$2)),""),"") -> 2 | F70: =IF(E70="","",IF(AD70=0,0,AD70/$AC$2-E70)) -> 0.5 | G70: =IF(ISERROR(SEARCH("Apron",D70)),AF70,"") | M70: =IF(ISNUMBER($AF70),2*$AF70,"") -> 12 | P70: {=XLOOKUP(B70,Weight!B:B,Weight!D:D,"#N/A",0)} -> 220 | Q70: =IF(AF70="","",AF70*P70) -> 1320 | S70: 392620 | T70: 12 | U70: 120 | X70: =SUMIFS('Transit Shipment'!$B$10:$B$1048462,'Transit Shipment'!$A$10:$A$1048462,B70,'Transit Shipment'!$C$10:$C$1048462,AA70) -> 0 | Y70: =IF(SUMIFS(DIH!$S$2:$S833,DIH!$D$2:$D833,B70,DIH!$U$2:$U833,AA70)>0,SUMIFS(DIH!$S$2:$S833,DIH!$D$2:$D833,B70,DIH!$U$2:$U833,AA70),0) -> 2 | Z70: =SUM(X70:Y70) -> 2 | AA70: CJB1 | AB70: =IF(ISNA(VLOOKUP($B70,'Business Report'!$D$2:$J$202,2,0)),"",VLOOKUP($B70,'Business Report'!$D$2:$J$202,2,0)) -> 89 | AC70: =SUMIFS(AFS!$P$2:$P$6260,AFS!$N$2:$N$6260,B70,AFS!$AT$2:$AT$6260,AA70) -> 5 | AD70: =CEILING(AC70/$W$2*$X$2,1)-sum(X70:Y70) -> 5 | AF70: =IF(ISNUMBER(AD70),IF(AD70<=0,"",IF(F70="","",E70*$AC$2+IF(F70>0,$AC$2,0)))) -> 6
A71: APR- Black | B71: CRM_AP_BLACK_PACK OF 2 | C71: CRASOME Apron for Men Women Chef Cooking Restaurants Gardening Workshop, Barbers with Adjustable Strap and Two Pockets (Black_Pack of 2) | D71: Apron | E71: =IF(ISNUMBER(AD71),IF(AD71>=0,IF(AD71=0,1,INT(AD71/$AC$2)),""),"") -> 2 | F71: =IF(E71="","",IF(AD71=0,0,AD71/$AC$2-E71)) -> 0 | G71: =IF(ISERROR(SEARCH("Apron",D71)),AF71,"") | M71: =IF(ISNUMBER($AF71),2*$AF71,"") -> 8 | P71: {=XLOOKUP(B71,Weight!B:B,Weight!D:D,"#N/A",0)} -> 220 | Q71: =IF(AF71="","",AF71*P71) -> 880 | S71: 392620 | T71: 12 | U71: 120 | X71: =SUMIFS('Transit Shipment'!$B$10:$B$1048462,'Transit Shipment'!$A$10:$A$1048462,B71,'Transit Shipment'!$C$10:$C$1048462,AA71) -> 0 | Y71: =IF(SUMIFS(DIH!$S$2:$S833,DIH!$D$2:$D833,B71,DIH!$U$2:$U833,AA71)>0,SUMIFS(DIH!$S$2:$S833,DIH!$D$2:$D833,B71,DIH!$U$2:$U833,AA71),0) -> 8 | Z71: =SUM(X71:Y71) -> 8 | AA71: MAA4 | AB71: =IF(ISNA(VLOOKUP($B71,'Business Report'!$D$2:$J$202,2,0)),"",VLOOKUP($B71,'Business Report'!$D$2:$J$202,2,0)) -> 89 | AC71: =SUMIFS(AFS!$P$2:$P$6260,AFS!$N$2:$N$6260,B71,AFS!$AT$2:$AT$6260,AA71) -> 9 | AD71: =CEILING(AC71/$W$2*$X$2,1)-sum(X71:Y71) -> 4 | AF71: =IF(ISNUMBER(AD71),IF(AD71<=0,"",IF(F71="","",E71*$AC$2+IF(F71>0,$AC$2,0)))) -> 4
A72: APR- Black | B72: CRM_AP_BLACK_PACK OF 2 | C72: CRASOME Apron for Men Women Chef Cooking Restaurants Gardening Workshop, Barbers with Adjustable Strap and Two Pockets (Black_Pack of 2) | D72: Apron | E72: =IF(ISNUMBER(AD72),IF(AD72>=0,IF(AD72=0,1,INT(AD72/$AC$2)),""),"") -> 5 | F72: =IF(E72="","",IF(AD72=0,0,AD72/$AC$2-E72)) -> 0 | G72: =IF(ISERROR(SEARCH("Apron",D72)),AF72,"") | M72: =IF(ISNUMBER($AF72),2*$AF72,"") -> 20 | P72: {=XLOOKUP(B72,Weight!B:B,Weight!D:D,"#N/A",0)} -> 220 | Q72: =IF(AF72="","",AF72*P72) -> 2200 | S72: 392620 | T72: 12 | U72: 120 | X72: =SUMIFS('Transit Shipment'!$B$10:$B$1048462,'Transit Shipment'!$A$10:$A$1048462,B72,'Transit Shipment'!$C$10:$C$1048462,AA72) -> 0 | Y72: =IF(SUMIFS(DIH!$S$2:$S833,DIH!$D$2:$D833,B72,DIH!$U$2:$U833,AA72)>0,SUMIFS(DIH!$S$2:$S833,DIH!$D$2:$D833,B72,DIH!$U$2:$U833,AA72),0) -> 4 | Z72: =SUM(X72:Y72) -> 4 | AA72: DEL4 | AB72: =IF(ISNA(VLOOKUP($B72,'Business Report'!$D$2:$J$202,2,0)),"",VLOOKUP($B72,'Business Report'!$D$2:$J$202,2,0)) -> 89 | AC72: =SUMIFS(AFS!$P$2:$P$6260,AFS!$N$2:$N$6260,B72,AFS!$AT$2:$AT$6260,AA72) -> 10 | AD72: =CEILING(AC72/$W$2*$X$2,1)-sum(X72:Y72) -> 10 | AF72: =IF(ISNUMBER(AD72),IF(AD72<=0,"",IF(F72="","",E72*$AC$2+IF(F72>0,$AC$2,0)))) -> 10
A73: APR- Black | B73: CRM_AP_BLACK_PACK OF 2 | C73: CRASOME Apron for Men Women Chef Cooking Restaurants Gardening Workshop, Barbers with Adjustable Strap and Two Pockets (Black_Pack of 2) | D73: Apron | E73: =IF(ISNUMBER(AD73),IF(AD73>=0,IF(AD73=0,1,INT(AD73/$AC$2)),""),"") -> 4 | F73: =IF(E73="","",IF(AD73=0,0,AD73/$AC$2-E73)) -> 0 | G73: =IF(ISERROR(SEARCH("Apron",D73)),AF73,"") | M73: =IF(ISNUMBER($AF73),2*$AF73,"") -> 16 | P73: {=XLOOKUP(B73,Weight!B:B,Weight!D:D,"#N/A",0)} -> 220 | Q73: =IF(AF73="","",AF73*P73) -> 1760 | S73: 392620 | T73: 12 | U73: 120 | X73: =SUMIFS('Transit Shipment'!$B$10:$B$1048462,'Transit Shipment'!$A$10:$A$1048462,B73,'Transit Shipment'!$C$10:$C$1048462,AA73) -> 0 | Y73: =IF(SUMIFS(DIH!$S$2:$S833,DIH!$D$2:$D833,B73,DIH!$U$2:$U833,AA73)>0,SUMIFS(DIH!$S$2:$S833,DIH!$D$2:$D833,B73,DIH!$U$2:$U833,AA73),0) -> 3 | Z73: =SUM(X73:Y73) -> 3 | AA73: DEL5 | AB73: =IF(ISNA(VLOOKUP($B73,'Business Report'!$D$2:$J$202,2,0)),"",VLOOKUP($B73,'Business Report'!$D$2:$J$202,2,0)) -> 89 | AC73: =SUMIFS(AFS!$P$2:$P$6260,AFS!$N$2:$N$6260,B73,AFS!$AT$2:$AT$6260,AA73) -> 8 | AD73: =CEILING(AC73/$W$2*$X$2,1)-sum(X73:Y73) -> 8 | AF73: =IF(ISNUMBER(AD73),IF(AD73<=0,"",IF(F73="","",E73*$AC$2+IF(F73>0,$AC$2,0)))) -> 8
A74: APR- Black | B74: CRM_AP_BLACK_PACK OF 2 | C74: CRASOME Apron for Men Women Chef Cooking Restaurants Gardening Workshop, Barbers with Adjustable Strap and Two Pockets (Black_Pack of 2) | D74: Apron | E74: =IF(ISNUMBER(AD74),IF(AD74>=0,IF(AD74=0,1,INT(AD74/$AC$2)),""),"") | F74: =IF(E74="","",IF(AD74=0,0,AD74/$AC$2-E74)) | G74: =IF(ISERROR(SEARCH("Apron",D74)),AF74,"") | M74: =IF(ISNUMBER($AF74),2*$AF74,"") | P74: {=XLOOKUP(B74,Weight!B:B,Weight!D:D,"#N/A",0)} -> 220 | Q74: =IF(AF74="","",AF74*P74) | S74: 392620 | T74: 12 | U74: 120 | X74: =SUMIFS('Transit Shipment'!$B$10:$B$1048462,'Transit Shipment'!$A$10:$A$1048462,B74,'Transit Shipment'!$C$10:$C$1048462,AA74) -> 0 | Y74: =IF(SUMIFS(DIH!$S$2:$S833,DIH!$D$2:$D833,B74,DIH!$U$2:$U833,AA74)>0,SUMIFS(DIH!$S$2:$S833,DIH!$D$2:$D833,B74,DIH!$U$2:$U833,AA74),0) -> 10 | Z74: =SUM(X74:Y74) -> 10 | AA74: BOM5 | AB74: =IF(ISNA(VLOOKUP($B74,'Business Report'!$D$2:$J$202,2,0)),"",VLOOKUP($B74,'Business Report'!$D$2:$J$202,2,0)) -> 89 | AC74: =SUMIFS(AFS!$P$2:$P$6260,AFS!$N$2:$N$6260,B74,AFS!$AT$2:$AT$6260,AA74) -> 6 | AD74: =CEILING(AC74/$W$2*$X$2,1)-sum(X74:Y74) -> -2 | AF74: =IF(ISNUMBER(AD74),IF(AD74<=0,"",IF(F74="","",E74*$AC$2+IF(F74>0,$AC$2,0))))
A75: APR- Black | B75: CRM_AP_BLACK_PACK OF 2 | C75: CRASOME Apron for Men Women Chef Cooking Restaurants Gardening Workshop, Barbers with Adjustable Strap and Two Pockets (Black_Pack of 2) | D75: Apron | E75: =IF(ISNUMBER(AD75),IF(AD75>=0,IF(AD75=0,1,INT(AD75/$AC$2)),""),"") -> 1 | F75: =IF(E75="","",IF(AD75=0,0,AD75/$AC$2-E75)) -> 0 | G75: =IF(ISERROR(SEARCH("Apron",D75)),AF75,"") | M75: =IF(ISNUMBER($AF75),2*$AF75,"") | P75: {=XLOOKUP(B75,Weight!B:B,Weight!D:D,"#N/A",0)} -> 220 | Q75: =IF(AF75="","",AF75*P75) | S75: 392620 | T75: 12 | U75: 120 | X75: =SUMIFS('Transit Shipment'!$B$10:$B$1048462,'Transit Shipment'!$A$10:$A$1048462,B75,'Transit Shipment'!$C$10:$C$1048462,AA75) -> 0 | Y75: =IF(SUMIFS(DIH!$S$2:$S833,DIH!$D$2:$D833,B75,DIH!$U$2:$U833,AA75)>0,SUMIFS(DIH!$S$2:$S833,DIH!$D$2:$D833,B75,DIH!$U$2:$U833,AA75),0) -> 0 | Z75: =SUM(X75:Y75) -> 0 | AA75: BOM7 | AB75: =IF(ISNA(VLOOKUP($B75,'Business Report'!$D$2:$J$202,2,0)),"",VLOOKUP($B75,'Business Report'!$D$2:$J$202,2,0)) -> 89 | AC75: =SUMIFS(AFS!$P$2:$P$6260,AFS!$N$2:$N$6260,B75,AFS!$AT$2:$AT$6260,AA75) -> 0 | AD75: =CEILING(AC75/$W$2*$X$2,1)-sum(X75:Y75) -> 0 | AE75: =SUM(AD67:AD75) -> 19 | AF75: =IF(ISNUMBER(AD75),IF(AD75<=0,"",IF(F75="","",E75*$AC$2+IF(F75>0,$AC$2,0))))
A76: APR- Dark Blue | B76: CRM_AP_BLUE_PACK OF 2 | C76: CRASOME Apron for Men Women Chef Cooking Restaurants Gardening Workshop, Barbers with Adjustable Strap and Two Pockets ( Blue_Pack of 2) | D76: Apron | E76: =IF(ISNUMBER(AD76),IF(AD76>=0,IF(AD76=0,1,INT(AD76/$AC$2)),""),"") -> 1 | F76: =IF(E76="","",IF(AD76=0,0,AD76/$AC$2-E76)) -> 0 | G76: =IF(ISERROR(SEARCH("Apron",D76)),AF76,"") | I76: =IF(ISNUMBER($AF76),2*$AF76,"") -> 4 | P76: {=XLOOKUP(B76,Weight!B:B,Weight!D:D,"#N/A",0)} -> 220 | Q76: =IF(AF76="","",AF76*P76) -> 440 | S76: 392620 | T76: 12 | U76: 120 | V76: =B76 -> CRM_AP_BLUE_PACK OF 2 | W76: =C76 -> CRASOME Apron for Men Women Chef Cooking Restaurants Gardening Workshop, Barbers with Adjustable Strap and Two Pockets ( Blue_Pack of 2) | X76: =SUMIFS('Transit Shipment'!$B$10:$B$1048462,'Transit Shipment'!$A$10:$A$1048462,B76,'Transit Shipment'!$C$10:$C$1048462,AA76) -> 0 | Y76: =IF(SUMIFS(DIH!$S$2:$S833,DIH!$D$2:$D833,B76,DIH!$U$2:$U833,AA76)>0,SUMIFS(DIH!$S$2:$S833,DIH!$D$2:$D833,B76,DIH!$U$2:$U833,AA76),0) -> 0 | Z76: =SUM(X76:Y76) -> 0 | AA76: AMD2 | AB76: =IF(ISNA(VLOOKUP($B76,'Business Report'!$D$2:$J$202,2,0)),"",VLOOKUP($B76,'Business Report'!$D$2:$J$202,2,0)) -> 55 | AC76: =SUMIFS(AFS!$P$2:$P$6260,AFS!$N$2:$N$6260,B76,AFS!$AT$2:$AT$6260,AA76) -> 1 | AD76: =CEILING(AC76/$W$2*$X$2,1)-sum(X76:Y76) -> 2 | AF76: =IF(ISNUMBER(AD76),IF(AD76<=0,"",IF(F76="","",E76*$AC$2+IF(F76>0,$AC$2,0)))) -> 2
A77: APR- Dark Blue | B77: CRM_AP_BLUE_PACK OF 2 | C77: CRASOME Apron for Men Women Chef Cooking Restaurants Gardening Workshop, Barbers with Adjustable Strap and Two Pockets ( Blue_Pack of 2) | D77: Apron | E77: =IF(ISNUMBER(AD77),IF(AD77>=0,IF(AD77=0,1,INT(AD77/$AC$2)),""),"") -> 1 | F77: =IF(E77="","",IF(AD77=0,0,AD77/$AC$2-E77)) -> 0 | G77: =IF(ISERROR(SEARCH("Apron",D77)),AF77,"") | I77: =IF(ISNUMBER($AF77),2*$AF77,"") | P77: {=XLOOKUP(B77,Weight!B:B,Weight!D:D,"#N/A",0)} -> 220 | Q77: =IF(AF77="","",AF77*P77) | S77: 392620 | T77: 12 | U77: 120 | X77: =SUMIFS('Transit Shipment'!$B$10:$B$1048462,'Transit Shipment'!$A$10:$A$1048462,B77,'Transit Shipment'!$C$10:$C$1048462,AA77) -> 0 | Y77: =IF(SUMIFS(DIH!$S$2:$S833,DIH!$D$2:$D833,B77,DIH!$U$2:$U833,AA77)>0,SUMIFS(DIH!$S$2:$S833,DIH!$D$2:$D833,B77,DIH!$U$2:$U833,AA77),0) -> 0 | Z77: =SUM(X77:Y77) -> 0 | AA77: BLR8 | AB77: =IF(ISNA(VLOOKUP($B77,'Business Report'!$D$2:$J$202,2,0)),"",VLOOKUP($B77,'Business Report'!$D$2:$J$202,2,0)) -> 55 | AC77: =SUMIFS(AFS!$P$2:$P$6260,AFS!$N$2:$N$6260,B77,AFS!$AT$2:$AT$6260,AA77) -> 0 | AD77: =CEILING(AC77/$W$2*$X$2,1)-sum(X77:Y77) -> 0 | AF77: =IF(ISNUMBER(AD77),IF(AD77<=0,"",IF(F77="","",E77*$AC$2+IF(F77>0,$AC$2,0))))
A78: APR- Dark Blue | B78: CRM_AP_BLUE_PACK OF 2 | C78: CRASOME Apron for Men Women Chef Cooking Restaurants Gardening Workshop, Barbers with Adjustable Strap and Two Pockets ( Blue_Pack of 2) | D78: Apron | E78: =IF(ISNUMBER(AD78),IF(AD78>=0,IF(AD78=0,1,INT(AD78/$AC$2)),""),"") -> 1 | F78: =IF(E78="","",IF(AD78=0,0,AD78/$AC$2-E78)) -> 0.5 | G78: =IF(ISERROR(SEARCH("Apron",D78)),AF78,"") | I78: =IF(ISNUMBER($AF78),2*$AF78,"") -> 8 | P78: {=XLOOKUP(B78,Weight!B:B,Weight!D:D,"#N/A",0)} -> 220 | Q78: =IF(AF78="","",AF78*P78) -> 880 | S78: 392620 | T78: 12 | U78: 120 | X78: =SUMIFS('Transit Shipment'!$B$10:$B$1048462,'Transit Shipment'!$A$10:$A$1048462,B78,'Transit Shipment'!$C$10:$C$1048462,AA78) -> 0 | Y78: =IF(SUMIFS(DIH!$S$2:$S833,DIH!$D$2:$D833,B78,DIH!$U$2:$U833,AA78)>0,SUMIFS(DIH!$S$2:$S833,DIH!$D$2:$D833,B78,DIH!$U$2:$U833,AA78),0) -> 0 | Z78: =SUM(X78:Y78) -> 0 | AA78: BLR7 | AB78: =IF(ISNA(VLOOKUP($B78,'Business Report'!$D$2:$J$202,2,0)),"",VLOOKUP($B78,'Business Report'!$D$2:$J$202,2,0)) -> 55 | AC78: =SUMIFS(AFS!$P$2:$P$6260,AFS!$N$2:$N$6260,B78,AFS!$AT$2:$AT$6260,AA78) -> 2 | AD78: =CEILING(AC78/$W$2*$X$2,1)-sum(X78:Y78) -> 3 | AF78: =IF(ISNUMBER(AD78),IF(AD78<=0,"",IF(F78="","",E78*$AC$2+IF(F78>0,$AC$2,0)))) -> 4
A79: APR- Dark Blue | B79: CRM_AP_BLUE_PACK OF 2 | C79: CRASOME Apron for Men Women Chef Cooking Restaurants Gardening Workshop, Barbers with Adjustable Strap and Two Pockets ( Blue_Pack of 2) | D79: Apron | E79: =IF(ISNUMBER(AD79),IF(AD79>=0,IF(AD79=0,1,INT(AD79/$AC$2)),""),"") -> 2 | F79: =IF(E79="","",IF(AD79=0,0,AD79/$AC$2-E79)) -> 0 | G79: =IF(ISERROR(SEARCH("Apron",D79)),AF79,"") | I79: =IF(ISNUMBER($AF79),2*$AF79,"") -> 8 | P79: {=XLOOKUP(B79,Weight!B:B,Weight!D:D,"#N/A",0)} -> 220 | Q79: =IF(AF79="","",AF79*P79) -> 880 | S79: 392620 | T79: 12 | U79: 120 | X79: =SUMIFS('Transit Shipment'!$B$10:$B$1048462,'Transit Shipment'!$A$10:$A$1048462,B79,'Transit Shipment'!$C$10:$C$1048462,AA79) -> 0 | Y79: =IF(SUMIFS(DIH!$S$2:$S833,DIH!$D$2:$D833,B79,DIH!$U$2:$U833,AA79)>0,SUMIFS(DIH!$S$2:$S833,DIH!$D$2:$D833,B79,DIH!$U$2:$U833,AA79),0) -> 3 | Z79: =SUM(X79:Y79) -> 3 | AA79: CJB1 | AB79: =IF(ISNA(VLOOKUP($B79,'Business Report'!$D$2:$J$202,2,0)),"",VLOOKUP($B79,'Business Report'!$D$2:$J$202,2,0)) -> 55 | AC79: =SUMIFS(AFS!$P$2:$P$6260,AFS!$N$2:$N$6260,B79,AFS!$AT$2:$AT$6260,AA79) -> 5 | AD79: =CEILING(AC79/$W$2*$X$2,1)-sum(X79:Y79) -> 4 | AF79: =IF(ISNUMBER(AD79),IF(AD79<=0,"",IF(F79="","",E79*$AC$2+IF(F79>0,$AC$2,0)))) -> 4
A80: APR- Dark Blue | B80: CRM_AP_BLUE_PACK OF 2 | C80: CRASOME Apron for Men Women Chef Cooking Restaurants Gardening Workshop, Barbers with Adjustable Strap and Two Pockets ( Blue_Pack of 2) | D80: Apron | E80: =IF(ISNUMBER(AD80),IF(AD80>=0,IF(AD80=0,1,INT(AD80/$AC$2)),""),"") -> 3 | F80: =IF(E80="","",IF(AD80=0,0,AD80/$AC$2-E80)) -> 0.5 | G80: =IF(ISERROR(SEARCH("Apron",D80)),AF80,"") | I80: =IF(ISNUMBER($AF80),2*$AF80,"") -> 16 | P80: {=XLOOKUP(B80,Weight!B:B,Weight!D:D,"#N/A",0)} -> 220 | Q80: =IF(AF80="","",AF80*P80) -> 1760 | S80: 392620 | T80: 12 | U80: 120 | X80: =SUMIFS('Transit Shipment'!$B$10:$B$1048462,'Transit Shipment'!$A$10:$A$1048462,B80,'Transit Shipment'!$C$10:$C$1048462,AA80) -> 0 | Y80: =IF(SUMIFS(DIH!$S$2:$S833,DIH!$D$2:$D833,B80,DIH!$U$2:$U833,AA80)>0,SUMIFS(DIH!$S$2:$S833,DIH!$D$2:$D833,B80,DIH!$U$2:$U833,AA80),0) -> 0 | Z80: =SUM(X80:Y80) -> 0 | AA80: MAA4 | AB80: =IF(ISNA(VLOOKUP($B80,'Business Report'!$D$2:$J$202,2,0)),"",VLOOKUP($B80,'Business Report'!$D$2:$J$202,2,0)) -> 55 | AC80: =SUMIFS(AFS!$P$2:$P$6260,AFS!$N$2:$N$6260,B80,AFS!$AT$2:$AT$6260,AA80) -> 5 | AD80: =CEILING(AC80/$W$2*$X$2,1)-sum(X80:Y80) -> 7 | AF80: =IF(ISNUMBER(AD80),IF(AD80<=0,"",IF(F80="","",E80*$AC$2+IF(F80>0,$AC$2,0)))) -> 8
A81: APR- Dark Blue | B81: CRM_AP_BLUE_PACK OF 2 | C81: CRASOME Apron for Men Women Chef Cooking Restaurants Gardening Workshop, Barbers with Adjustable Strap and Two Pockets ( Blue_Pack of 2) | D81: Apron | E81: =IF(ISNUMBER(AD81),IF(AD81>=0,IF(AD81=0,1,INT(AD81/$AC$2)),""),"") -> 1 | F81: =IF(E81="","",IF(AD81=0,0,AD81/$AC$2-E81)) -> 0 | G81: =IF(ISERROR(SEARCH("Apron",D81)),AF81,"") | I81: =IF(ISNUMBER($AF81),2*$AF81,"") | P81: {=XLOOKUP(B81,Weight!B:B,Weight!D:D,"#N/A",0)} -> 220 | Q81: =IF(AF81="","",AF81*P81) | S81: 392620 | T81: 12 | U81: 120 | X81: =SUMIFS('Transit Shipment'!$B$10:$B$1048462,'Transit Shipment'!$A$10:$A$1048462,B81,'Transit Shipment'!$C$10:$C$1048462,AA81) -> 0 | Y81: =IF(SUMIFS(DIH!$S$2:$S833,DIH!$D$2:$D833,B81,DIH!$U$2:$U833,AA81)>0,SUMIFS(DIH!$S$2:$S833,DIH!$D$2:$D833,B81,DIH!$U$2:$U833,AA81),0) -> 0 | Z81: =SUM(X81:Y81) -> 0 | AA81: DEL4 | AB81: =IF(ISNA(VLOOKUP($B81,'Business Report'!$D$2:$J$202,2,0)),"",VLOOKUP($B81,'Business Report'!$D$2:$J$202,2,0)) -> 55 | AC81: =SUMIFS(AFS!$P$2:$P$6260,AFS!$N$2:$N$6260,B81,AFS!$AT$2:$AT$6260,AA81) -> 0 | AD81: =CEILING(AC81/$W$2*$X$2,1)-sum(X81:Y81) -> 0 | AF81: =IF(ISNUMBER(AD81),IF(AD81<=0,"",IF(F81="","",E81*$AC$2+IF(F81>0,$AC$2,0))))
A82: APR- Dark Blue | B82: CRM_AP_BLUE_PACK OF 2 | C82: CRASOME Apron for Men Women Chef Cooking Restaurants Gardening Workshop, Barbers with Adjustable Strap and Two Pockets ( Blue_Pack of 2) | D82: Apron | E82: =IF(ISNUMBER(AD82),IF(AD82>=0,IF(AD82=0,1,INT(AD82/$AC$2)),""),"") -> 1 | F82: =IF(E82="","",IF(AD82=0,0,AD82/$AC$2-E82)) -> 0 | G82: =IF(ISERROR(SEARCH("Apron",D82)),AF82,"") | I82: =IF(ISNUMBER($AF82),2*$AF82,"") | P82: {=XLOOKUP(B82,Weight!B:B,Weight!D:D,"#N/A",0)} -> 220 | Q82: =IF(AF82="","",AF82*P82) | S82: 392620 | T82: 12 | U82: 120 | X82: =SUMIFS('Transit Shipment'!$B$10:$B$1048462,'Transit Shipment'!$A$10:$A$1048462,B82,'Transit Shipment'!$C$10:$C$1048462,AA82) -> 0 | Y82: =IF(SUMIFS(DIH!$S$2:$S833,DIH!$D$2:$D833,B82,DIH!$U$2:$U833,AA82)>0,SUMIFS(DIH!$S$2:$S833,DIH!$D$2:$D833,B82,DIH!$U$2:$U833,AA82),0) -> 0 | Z82: =SUM(X82:Y82) -> 0 | AA82: DEL5 | AB82: =IF(ISNA(VLOOKUP($B82,'Business Report'!$D$2:$J$202,2,0)),"",VLOOKUP($B82,'Business Report'!$D$2:$J$202,2,0)) -> 55 | AC82: =SUMIFS(AFS!$P$2:$P$6260,AFS!$N$2:$N$6260,B82,AFS!$AT$2:$AT$6260,AA82) -> 0 | AD82: =CEILING(AC82/$W$2*$X$2,1)-sum(X82:Y82) -> 0 | AF82: =IF(ISNUMBER(AD82),IF(AD82<=0,"",IF(F82="","",E82*$AC$2+IF(F82>0,$AC$2,0))))
A83: APR- Dark Blue | B83: CRM_AP_BLUE_PACK OF 2 | C83: CRASOME Apron for Men Women Chef Cooking Restaurants Gardening Workshop, Barbers with Adjustable Strap and Two Pockets ( Blue_Pack of 2) | D83: Apron | E83: =IF(ISNUMBER(AD83),IF(AD83>=0,IF(AD83=0,1,INT(AD83/$AC$2)),""),"") -> 2 | F83: =IF(E83="","",IF(AD83=0,0,AD83/$AC$2-E83)) -> 0 | G83: =IF(ISERROR(SEARCH("Apron",D83)),AF83,"") | I83: =IF(ISNUMBER($AF83),2*$AF83,"") -> 8 | P83: {=XLOOKUP(B83,Weight!B:B,Weight!D:D,"#N/A",0)} -> 220 | Q83: =IF(AF83="","",AF83*P83) -> 880 | S83: 392620 | T83: 12 | U83: 120 | X83: =SUMIFS('Transit Shipment'!$B$10:$B$1048462,'Transit Shipment'!$A$10:$A$1048462,B83,'Transit Shipment'!$C$10:$C$1048462,AA83) -> 0 | Y83: =IF(SUMIFS(DIH!$S$2:$S833,DIH!$D$2:$D833,B83,DIH!$U$2:$U833,AA83)>0,SUMIFS(DIH!$S$2:$S833,DIH!$D$2:$D833,B83,DIH!$U$2:$U833,AA83),0) -> 0 | Z83: =SUM(X83:Y83) -> 0 | AA83: BOM5 | AB83: =IF(ISNA(VLOOKUP($B83,'Business Report'!$D$2:$J$202,2,0)),"",VLOOKUP($B83,'Business Report'!$D$2:$J$202,2,0)) -> 55 | AC83: =SUMIFS(AFS!$P$2:$P$6260,AFS!$N$2:$N$6260,B83,AFS!$AT$2:$AT$6260,AA83) -> 3 | AD83: =CEILING(AC83/$W$2*$X$2,1)-sum(X83:Y83) -> 4 | AF83: =IF(ISNUMBER(AD83),IF(AD83<=0,"",IF(F83="","",E83*$AC$2+IF(F83>0,$AC$2,0)))) -> 4
A84: APR- Dark Blue | B84: CRM_AP_BLUE_PACK OF 2 | C84: CRASOME Apron for Men Women Chef Cooking Restaurants Gardening Workshop, Barbers with Adjustable Strap and Two Pockets ( Blue_Pack of 2) | D84: Apron | E84: =IF(ISNUMBER(AD84),IF(AD84>=0,IF(AD84=0,1,INT(AD84/$AC$2)),""),"") -> 1 | F84: =IF(E84="","",IF(AD84=0,0,AD84/$AC$2-E84)) -> 0 | G84: =IF(ISERROR(SEARCH("Apron",D84)),AF84,"") | I84: =IF(ISNUMBER($AF84),2*$AF84,"") | P84: {=XLOOKUP(B84,Weight!B:B,Weight!D:D,"#N/A",0)} -> 220 | Q84: =IF(AF84="","",AF84*P84) | S84: 392620 | T84: 12 | U84: 120 | X84: =SUMIFS('Transit Shipment'!$B$10:$B$1048462,'Transit Shipment'!$A$10:$A$1048462,B84,'Transit Shipment'!$C$10:$C$1048462,AA84) -> 0 | Y84: =IF(SUMIFS(DIH!$S$2:$S833,DIH!$D$2:$D833,B84,DIH!$U$2:$U833,AA84)>0,SUMIFS(DIH!$S$2:$S833,DIH!$D$2:$D833,B84,DIH!$U$2:$U833,AA84),0) -> 0 | Z84: =SUM(X84:Y84) -> 0 | AA84: BOM7 | AB84: =IF(ISNA(VLOOKUP($B84,'Business Report'!$D$2:$J$202,2,0)),"",VLOOKUP($B84,'Business Report'!$D$2:$J$202,2,0)) -> 55 | AC84: =SUMIFS(AFS!$P$2:$P$6260,AFS!$N$2:$N$6260,B84,AFS!$AT$2:$AT$6260,AA84) -> 0 | AD84: =CEILING(AC84/$W$2*$X$2,1)-sum(X84:Y84) -> 0 | AE84: =SUM(AD76:AD84) -> 20 | AF84: =IF(ISNUMBER(AD84),IF(AD84<=0,"",IF(F84="","",E84*$AC$2+IF(F84>0,$AC$2,0))))
A85: APR- Brown | B85: CRM_AP_BROWN_PACK OF 2 | C85: CRASOME Apron for Men Women Chef Cooking Restaurants Gardening Workshop, Barbers with Adjustable Strap and Two Pockets ( Brown_Pack of 2) | D85: Apron | E85: =IF(ISNUMBER(AD85),IF(AD85>=0,IF(AD85=0,1,INT(AD85/$AC$2)),""),"") | F85: =IF(E85="","",IF(AD85=0,0,AD85/$AC$2-E85)) | G85: =IF(ISERROR(SEARCH("Apron",D85)),AF85,"") | J85: =IF(ISNUMBER($AF85),2*$AF85,"") | P85: {=XLOOKUP(B85,Weight!B:B,Weight!D:D,"#N/A",0)} -> 220 | Q85: =IF(AF85="","",AF85*P85) | S85: 392620 | T85: 12 | U85: 120 | V85: =B85 -> CRM_AP_BROWN_PACK OF 2 | W85: =C85 -> CRASOME Apron for Men Women Chef Cooking Restaurants Gardening Workshop, Barbers with Adjustable Strap and Two Pockets ( Brown_Pack of 2) | X85: =SUMIFS('Transit Shipment'!$B$10:$B$1048462,'Transit Shipment'!$A$10:$A$1048462,B85,'Transit Shipment'!$C$10:$C$1048462,AA85) -> 0 | Y85: =IF(SUMIFS(DIH!$S$2:$S833,DIH!$D$2:$D833,B85,DIH!$U$2:$U833,AA85)>0,SUMIFS(DIH!$S$2:$S833,DIH!$D$2:$D833,B85,DIH!$U$2:$U833,AA85),0) -> 1 | Z85: =SUM(X85:Y85) -> 1 | AA85: AMD2 | AB85: =IF(ISNA(VLOOKUP($B85,'Business Report'!$D$2:$J$202,2,0)),"",VLOOKUP($B85,'Business Report'!$D$2:$J$202,2,0)) -> 86 | AC85: =SUMIFS(AFS!$P$2:$P$6260,AFS!$N$2:$N$6260,B85,AFS!$AT$2:$AT$6260,AA85) -> 0 | AD85: =CEILING(AC85/$W$2*$X$2,1)-sum(X85:Y85) -> -1 | AF85: =IF(ISNUMBER(AD85),IF(AD85<=0,"",IF(F85="","",E85*$AC$2+IF(F85>0,$AC$2,0))))
A86: APR- Brown | B86: CRM_AP_BROWN_PACK OF 2 | C86: CRASOME Apron for Men Women Chef Cooking Restaurants Gardening Workshop, Barbers with Adjustable Strap and Two Pockets ( Brown_Pack of 2) | D86: Apron | E86: =IF(ISNUMBER(AD86),IF(AD86>=0,IF(AD86=0,1,INT(AD86/$AC$2)),""),"") -> 1 | F86: =IF(E86="","",IF(AD86=0,0,AD86/$AC$2-E86)) -> 0 | G86: =IF(ISERROR(SEARCH("Apron",D86)),AF86,"") | J86: =IF(ISNUMBER($AF86),2*$AF86,"") | P86: {=XLOOKUP(B86,Weight!B:B,Weight!D:D,"#N/A",0)} -> 220 | Q86: =IF(AF86="","",AF86*P86) | S86: 392620 | T86: 12 | U86: 120 | X86: =SUMIFS('Transit Shipment'!$B$10:$B$1048462,'Transit Shipment'!$A$10:$A$1048462,B86,'Transit Shipment'!$C$10:$C$1048462,AA86) -> 0 | Y86: =IF(SUMIFS(DIH!$S$2:$S833,DIH!$D$2:$D833,B86,DIH!$U$2:$U833,AA86)>0,SUMIFS(DIH!$S$2:$S833,DIH!$D$2:$D833,B86,DIH!$U$2:$U833,AA86),0) -> 3 | Z86: =SUM(X86:Y86) -> 3 | AA86: BLR8 | AB86: =IF(ISNA(VLOOKUP($B86,'Business Report'!$D$2:$J$202,2,0)),"",VLOOKUP($B86,'Business Report'!$D$2:$J$202,2,0)) -> 86 | AC86: =SUMIFS(AFS!$P$2:$P$6260,AFS!$N$2:$N$6260,B86,AFS!$AT$2:$AT$6260,AA86) -> 2 | AD86: =CEILING(AC86/$W$2*$X$2,1)-sum(X86:Y86) -> 0 | AF86: =IF(ISNUMBER(AD86),IF(AD86<=0,"",IF(F86="","",E86*$AC$2+IF(F86>0,$AC$2,0))))
A87: APR- Brown | B87: CRM_AP_BROWN_PACK OF 2 | C87: CRASOME Apron for Men Women Chef Cooking Restaurants Gardening Workshop, Barbers with Adjustable Strap and Two Pockets ( Brown_Pack of 2) | D87: Apron | E87: =IF(ISNUMBER(AD87),IF(AD87>=0,IF(AD87=0,1,INT(AD87/$AC$2)),""),"") -> 1 | F87: =IF(E87="","",IF(AD87=0,0,AD87/$AC$2-E87)) -> 0 | G87: =IF(ISERROR(SEARCH("Apron",D87)),AF87,"") | J87: =IF(ISNUMBER($AF87),2*$AF87,"") | P87: {=XLOOKUP(B87,Weight!B:B,Weight!D:D,"#N/A",0)} -> 220 | Q87: =IF(AF87="","",AF87*P87) | S87: 392620 | T87: 12 | U87: 120 | X87: =SUMIFS('Transit Shipment'!$B$10:$B$1048462,'Transit Shipment'!$A$10:$A$1048462,B87,'Transit Shipment'!$C$10:$C$1048462,AA87) -> 0 | Y87: =IF(SUMIFS(DIH!$S$2:$S833,DIH!$D$2:$D833,B87,DIH!$U$2:$U833,AA87)>0,SUMIFS(DIH!$S$2:$S833,DIH!$D$2:$D833,B87,DIH!$U$2:$U833,AA87),0) -> 3 | Z87: =SUM(X87:Y87) -> 3 | AA87: BLR7 | AB87: =IF(ISNA(VLOOKUP($B87,'Business Report'!$D$2:$J$202,2,0)),"",VLOOKUP($B87,'Business Report'!$D$2:$J$202,2,0)) -> 86 | AC87: =SUMIFS(AFS!$P$2:$P$6260,AFS!$N$2:$N$6260,B87,AFS!$AT$2:$AT$6260,AA87) -> 2 | AD87: =CEILING(AC87/$W$2*$X$2,1)-sum(X87:Y87) -> 0 | AF87: =IF(ISNUMBER(AD87),IF(AD87<=0,"",IF(F87="","",E87*$AC$2+IF(F87>0,$AC$2,0))))
A88: APR- Brown | B88: CRM_AP_BROWN_PACK OF 2 | C88: CRASOME Apron for Men Women Chef Cooking Restaurants Gardening Workshop, Barbers with Adjustable Strap and Two Pockets ( Brown_Pack of 2) | D88: Apron | E88: =IF(ISNUMBER(AD88),IF(AD88>=0,IF(AD88=0,1,INT(AD88/$AC$2)),""),"") -> 2 | F88: =IF(E88="","",IF(AD88=0,0,AD88/$AC$2-E88)) -> 0 | G88: =IF(ISERROR(SEARCH("Apron",D88)),AF88,"") | J88: =IF(ISNUMBER($AF88),2*$AF88,"") -> 8 | P88: {=XLOOKUP(B88,Weight!B:B,Weight!D:D,"#N/A",0)} -> 220 | Q88: =IF(AF88="","",AF88*P88) -> 880 | S88: 392620 | T88: 12 | U88: 120 | X88: =SUMIFS('Transit Shipment'!$B$10:$B$1048462,'Transit Shipment'!$A$10:$A$1048462,B88,'Transit Shipment'!$C$10:$C$1048462,AA88) -> 0 | Y88: =IF(SUMIFS(DIH!$S$2:$S833,DIH!$D$2:$D833,B88,DIH!$U$2:$U833,AA88)>0,SUMIFS(DIH!$S$2:$S833,DIH!$D$2:$D833,B88,DIH!$U$2:$U833,AA88),0) -> 0 | Z88: =SUM(X88:Y88) -> 0 | AA88: CJB1 | AB88: =IF(ISNA(VLOOKUP($B88,'Business Report'!$D$2:$J$202,2,0)),"",VLOOKUP($B88,'Business Report'!$D$2:$J$202,2,0)) -> 86 | AC88: =SUMIFS(AFS!$P$2:$P$6260,AFS!$N$2:$N$6260,B88,AFS!$AT$2:$AT$6260,AA88) -> 3 | AD88: =CEILING(AC88/$W$2*$X$2,1)-sum(X88:Y88) -> 4 | AF88: =IF(ISNUMBER(AD88),IF(AD88<=0,"",IF(F88="","",E88*$AC$2+IF(F88>0,$AC$2,0)))) -> 4
A89: APR- Brown | B89: CRM_AP_BROWN_PACK OF 2 | C89: CRASOME Apron for Men Women Chef Cooking Restaurants Gardening Workshop, Barbers with Adjustable Strap and Two Pockets ( Brown_Pack of 2) | D89: Apron | E89: =IF(ISNUMBER(AD89),IF(AD89>=0,IF(AD89=0,1,INT(AD89/$AC$2)),""),"") | F89: =IF(E89="","",IF(AD89=0,0,AD89/$AC$2-E89)) | G89: =IF(ISERROR(SEARCH("Apron",D89)),AF89,"") | J89: =IF(ISNUMBER($AF89),2*$AF89,"") | P89: {=XLOOKUP(B89,Weight!B:B,Weight!D:D,"#N/A",0)} -> 220 | Q89: =IF(AF89="","",AF89*P89) | S89: 392620 | T89: 12 | U89: 120 | X89: =SUMIFS('Transit Shipment'!$B$10:$B$1048462,'Transit Shipment'!$A$10:$A$1048462,B89,'Transit Shipment'!$C$10:$C$1048462,AA89) -> 0 | Y89: =IF(SUMIFS(DIH!$S$2:$S833,DIH!$D$2:$D833,B89,DIH!$U$2:$U833,AA89)>0,SUMIFS(DIH!$S$2:$S833,DIH!$D$2:$D833,B89,DIH!$U$2:$U833,AA89),0) -> 11 | Z89: =SUM(X89:Y89) -> 11 | AA89: MAA4 | AB89: =IF(ISNA(VLOOKUP($B89,'Business Report'!$D$2:$J$202,2,0)),"",VLOOKUP($B89,'Business Report'!$D$2:$J$202,2,0)) -> 86 | AC89: =SUMIFS(AFS!$P$2:$P$6260,AFS!$N$2:$N$6260,B89,AFS!$AT$2:$AT$6260,AA89) -> 5 | AD89: =CEILING(AC89/$W$2*$X$2,1)-sum(X89:Y89) -> -4 | AF89: =IF(ISNUMBER(AD89),IF(AD89<=0,"",IF(F89="","",E89*$AC$2+IF(F89>0,$AC$2,0))))
A90: APR- Brown | B90: CRM_AP_BROWN_PACK OF 2 | C90: CRASOME Apron for Men Women Chef Cooking Restaurants Gardening Workshop, Barbers with Adjustable Strap and Two Pockets ( Brown_Pack of 2) | D90: Apron | E90: =IF(ISNUMBER(AD90),IF(AD90>=0,IF(AD90=0,1,INT(AD90/$AC$2)),""),"") -> 1 | F90: =IF(E90="","",IF(AD90=0,0,AD90/$AC$2-E90)) -> 0 | G90: =IF(ISERROR(SEARCH("Apron",D90)),AF90,"") | J90: =IF(ISNUMBER($AF90),2*$AF90,"") | P90: {=XLOOKUP(B90,Weight!B:B,Weight!D:D,"#N/A",0)} -> 220 | Q90: =IF(AF90="","",AF90*P90) | S90: 392620 | T90: 12 | U90: 120 | X90: =SUMIFS('Transit Shipment'!$B$10:$B$1048462,'Transit Shipment'!$A$10:$A$1048462,B90,'Transit Shipment'!$C$10:$C$1048462,AA90) -> 0 | Y90: =IF(SUMIFS(DIH!$S$2:$S833,DIH!$D$2:$D833,B90,DIH!$U$2:$U833,AA90)>0,SUMIFS(DIH!$S$2:$S833,DIH!$D$2:$D833,B90,DIH!$U$2:$U833,AA90),0) -> 3 | Z90: =SUM(X90:Y90) -> 3 | AA90: DEL4 | AB90: =IF(ISNA(VLOOKUP($B90,'Business Report'!$D$2:$J$202,2,0)),"",VLOOKUP($B90,'Business Report'!$D$2:$J$202,2,0)) -> 86 | AC90: =SUMIFS(AFS!$P$2:$P$6260,AFS!$N$2:$N$6260,B90,AFS!$AT$2:$AT$6260,AA90) -> 2 | AD90: =CEILING(AC90/$W$2*$X$2,1)-sum(X90:Y90) -> 0 | AF90: =IF(ISNUMBER(AD90),IF(AD90<=0,"",IF(F90="","",E90*$AC$2+IF(F90>0,$AC$2,0))))
A91: APR- Brown | B91: CRM_AP_BROWN_PACK OF 2 | C91: CRASOME Apron for Men Women Chef Cooking Restaurants Gardening Workshop, Barbers with Adjustable Strap and Two Pockets ( Brown_Pack of 2) | D91: Apron | E91: =IF(ISNUMBER(AD91),IF(AD91>=0,IF(AD91=0,1,INT(AD91/$AC$2)),""),"") | F91: =IF(E91="","",IF(AD91=0,0,AD91/$AC$2-E91)) | G91: =IF(ISERROR(SEARCH("Apron",D91)),AF91,"") | J91: =IF(ISNUMBER($AF91),2*$AF91,"") | P91: {=XLOOKUP(B91,Weight!B:B,Weight!D:D,"#N/A",0)} -> 220 | Q91: =IF(AF91="","",AF91*P91) | S91: 392620 | T91: 12 | U91: 120 | X91: =SUMIFS('Transit Shipment'!$B$10:$B$1048462,'Transit Shipment'!$A$10:$A$1048462,B91,'Transit Shipment'!$C$10:$C$1048462,AA91) -> 0 | Y91: =IF(SUMIFS(DIH!$S$2:$S833,DIH!$D$2:$D833,B91,DIH!$U$2:$U833,AA91)>0,SUMIFS(DIH!$S$2:$S833,DIH!$D$2:$D833,B91,DIH!$U$2:$U833,AA91),0) -> 4 | Z91: =SUM(X91:Y91) -> 4 | AA91: DEL5 | AB91: =IF(ISNA(VLOOKUP($B91,'Business Report'!$D$2:$J$202,2,0)),"",VLOOKUP($B91,'Business Report'!$D$2:$J$202,2,0)) -> 86 | AC91: =SUMIFS(AFS!$P$2:$P$6260,AFS!$N$2:$N$6260,B91,AFS!$AT$2:$AT$6260,AA91) -> 1 | AD91: =CEILING(AC91/$W$2*$X$2,1)-sum(X91:Y91) -> -2 | AF91: =IF(ISNUMBER(AD91),IF(AD91<=0,"",IF(F91="","",E91*$AC$2+IF(F91>0,$AC$2,0))))
A92: APR- Brown | B92: CRM_AP_BROWN_PACK OF 2 | C92: CRASOME Apron for Men Women Chef Cooking Restaurants Gardening Workshop, Barbers with Adjustable Strap and Two Pockets ( Brown_Pack of 2) | D92: Apron | E92: =IF(ISNUMBER(AD92),IF(AD92>=0,IF(AD92=0,1,INT(AD92/$AC$2)),""),"") -> 2 | F92: =IF(E92="","",IF(AD92=0,0,AD92/$AC$2-E92)) -> 0.5 | G92: =IF(ISERROR(SEARCH("Apron",D92)),AF92,"") | J92: =IF(ISNUMBER($AF92),2*$AF92,"") -> 12 | P92: {=XLOOKUP(B92,Weight!B:B,Weight!D:D,"#N/A",0)} -> 220 | Q92: =IF(AF92="","",AF92*P92) -> 1320 | S92: 392620 | T92: 12 | U92: 120 | X92: =SUMIFS('Transit Shipment'!$B$10:$B$1048462,'Transit Shipment'!$A$10:$A$1048462,B92,'Transit Shipment'!$C$10:$C$1048462,AA92) -> 0 | Y92: =IF(SUMIFS(DIH!$S$2:$S833,DIH!$D$2:$D833,B92,DIH!$U$2:$U833,AA92)>0,SUMIFS(DIH!$S$2:$S833,DIH!$D$2:$D833,B92,DIH!$U$2:$U833,AA92),0) -> 2 | Z92: =SUM(X92:Y92) -> 2 | AA92: BOM5 | AB92: =IF(ISNA(VLOOKUP($B92,'Business Report'!$D$2:$J$202,2,0)),"",VLOOKUP($B92,'Business Report'!$D$2:$J$202,2,0)) -> 86 | AC92: =SUMIFS(AFS!$P$2:$P$6260,AFS!$N$2:$N$6260,B92,AFS!$AT$2:$AT$6260,AA92) -> 5 | AD92: =CEILING(AC92/$W$2*$X$2,1)-sum(X92:Y92) -> 5 | AF92: =IF(ISNUMBER(AD92),IF(AD92<=0,"",IF(F92="","",E92*$AC$2+IF(F92>0,$AC$2,0)))) -> 6
A93: APR- Brown | B93: CRM_AP_BROWN_PACK OF 2 | C93: CRASOME Apron for Men Women Chef Cooking Restaurants Gardening Workshop, Barbers with Adjustable Strap and Two Pockets ( Brown_Pack of 2) | D93: Apron | E93: =IF(ISNUMBER(AD93),IF(AD93>=0,IF(AD93=0,1,INT(AD93/$AC$2)),""),"") -> 1 | F93: =IF(E93="","",IF(AD93=0,0,AD93/$AC$2-E93)) -> 0 | G93: =IF(ISERROR(SEARCH("Apron",D93)),AF93,"") | J93: =IF(ISNUMBER($AF93),2*$AF93,"") | P93: {=XLOOKUP(B93,Weight!B:B,Weight!D:D,"#N/A",0)} -> 220 | Q93: =IF(AF93="","",AF93*P93) | S93: 392620 | T93: 12 | U93: 120 | X93: =SUMIFS('Transit Shipment'!$B$10:$B$1048462,'Transit Shipment'!$A$10:$A$1048462,B93,'Transit Shipment'!$C$10:$C$1048462,AA93) -> 0 | Y93: =IF(SUMIFS(DIH!$S$2:$S833,DIH!$D$2:$D833,B93,DIH!$U$2:$U833,AA93)>0,SUMIFS(DIH!$S$2:$S833,DIH!$D$2:$D833,B93,DIH!$U$2:$U833,AA93),0) -> 0 | Z93: =SUM(X93:Y93) -> 0 | AA93: BOM7 | AB93: =IF(ISNA(VLOOKUP($B93,'Business Report'!$D$2:$J$202,2,0)),"",VLOOKUP($B93,'Business Report'!$D$2:$J$202,2,0)) -> 86 | AC93: =SUMIFS(AFS!$P$2:$P$6260,AFS!$N$2:$N$6260,B93,AFS!$AT$2:$AT$6260,AA93) -> 0 | AD93: =CEILING(AC93/$W$2*$X$2,1)-sum(X93:Y93) -> 0 | AE93: =SUM(AD85:AD93) -> 2 | AF93: =IF(ISNUMBER(AD93),IF(AD93<=0,"",IF(F93="","",E93*$AC$2+IF(F93>0,$AC$2,0))))
A94: APR- Green | B94: CRM_AP_GREEN_PACK OF 2 | C94: CRASOME Apron for Men Women Chef Cooking Restaurants Gardening Workshop, Barbers with Adjustable Strap and Two Pockets ( Green_Pack of 2) | D94: Apron | E94: =IF(ISNUMBER(AD94),IF(AD94>=0,IF(AD94=0,1,INT(AD94/$AC$2)),""),"") | F94: =IF(E94="","",IF(AD94=0,0,AD94/$AC$2-E94)) | G94: =IF(ISERROR(SEARCH("Apron",D94)),AF94,"") | K94: =IF(ISNUMBER($AF94),2*$AF94,"") | P94: {=XLOOKUP(B94,Weight!B:B,Weight!D:D,"#N/A",0)} -> 220 | Q94: =IF(AF94="","",AF94*P94) | S94: 392620 | T94: 12 | U94: 120 | V94: =B94 -> CRM_AP_GREEN_PACK OF 2 | W94: =C94 -> CRASOME Apron for Men Women Chef Cooking Restaurants Gardening Workshop, Barbers with Adjustable Strap and Two Pockets ( Green_Pack of 2) | X94: =SUMIFS('Transit Shipment'!$B$10:$B$1048462,'Transit Shipment'!$A$10:$A$1048462,B94,'Transit Shipment'!$C$10:$C$1048462,AA94) -> 0 | Y94: =IF(SUMIFS(DIH!$S$2:$S833,DIH!$D$2:$D833,B94,DIH!$U$2:$U833,AA94)>0,SUMIFS(DIH!$S$2:$S833,DIH!$D$2:$D833,B94,DIH!$U$2:$U833,AA94),0) -> 1 | Z94: =SUM(X94:Y94) -> 1 | AA94: AMD2 | AB94: =IF(ISNA(VLOOKUP($B94,'Business Report'!$D$2:$J$202,2,0)),"",VLOOKUP($B94,'Business Report'!$D$2:$J$202,2,0)) -> 35 | AC94: =SUMIFS(AFS!$P$2:$P$6260,AFS!$N$2:$N$6260,B94,AFS!$AT$2:$AT$6260,AA94) -> 0 | AD94: =CEILING(AC94/$W$2*$X$2,1)-sum(X94:Y94) -> -1 | AF94: =IF(ISNUMBER(AD94),IF(AD94<=0,"",IF(F94="","",E94*$AC$2+IF(F94>0,$AC$2,0))))
A95: APR- Green | B95: CRM_AP_GREEN_PACK OF 2 | C95: CRASOME Apron for Men Women Chef Cooking Restaurants Gardening Workshop, Barbers with Adjustable Strap and Two Pockets ( Green_Pack of 2) | D95: Apron | E95: =IF(ISNUMBER(AD95),IF(AD95>=0,IF(AD95=0,1,INT(AD95/$AC$2)),""),"") -> 2 | F95: =IF(E95="","",IF(AD95=0,0,AD95/$AC$2-E95)) -> 0 | G95: =IF(ISERROR(SEARCH("Apron",D95)),AF95,"") | K95: =IF(ISNUMBER($AF95),2*$AF95,"") -> 8 | P95: {=XLOOKUP(B95,Weight!B:B,Weight!D:D,"#N/A",0)} -> 220 | Q95: =IF(AF95="","",AF95*P95) -> 880 | S95: 392620 | T95: 12 | U95: 120 | X95: =SUMIFS('Transit Shipment'!$B$10:$B$1048462,'Transit Shipment'!$A$10:$A$1048462,B95,'Transit Shipment'!$C$10:$C$1048462,AA95) -> 0 | Y95: =IF(SUMIFS(DIH!$S$2:$S833,DIH!$D$2:$D833,B95,DIH!$U$2:$U833,AA95)>0,SUMIFS(DIH!$S$2:$S833,DIH!$D$2:$D833,B95,DIH!$U$2:$U833,AA95),0) -> 3 | Z95: =SUM(X95:Y95) -> 3 | AA95: BLR8 | AB95: =IF(ISNA(VLOOKUP($B95,'Business Report'!$D$2:$J$202,2,0)),"",VLOOKUP($B95,'Business Report'!$D$2:$J$202,2,0)) -> 35 | AC95: =SUMIFS(AFS!$P$2:$P$6260,AFS!$N$2:$N$6260,B95,AFS!$AT$2:$AT$6260,AA95) -> 5 | AD95: =CEILING(AC95/$W$2*$X$2,1)-sum(X95:Y95) -> 4 | AF95: =IF(ISNUMBER(AD95),IF(AD95<=0,"",IF(F95="","",E95*$AC$2+IF(F95>0,$AC$2,0)))) -> 4
A96: APR- Green | B96: CRM_AP_GREEN_PACK OF 2 | C96: CRASOME Apron for Men Women Chef Cooking Restaurants Gardening Workshop, Barbers with Adjustable Strap and Two Pockets ( Green_Pack of 2) | D96: Apron | E96: =IF(ISNUMBER(AD96),IF(AD96>=0,IF(AD96=0,1,INT(AD96/$AC$2)),""),"") -> 2 | F96: =IF(E96="","",IF(AD96=0,0,AD96/$AC$2-E96)) -> 0 | G96: =IF(ISERROR(SEARCH("Apron",D96)),AF96,"") | K96: =IF(ISNUMBER($AF96),2*$AF96,"") -> 8 | P96: {=XLOOKUP(B96,Weight!B:B,Weight!D:D,"#N/A",0)} -> 220 | Q96: =IF(AF96="","",AF96*P96) -> 880 | S96: 392620 | T96: 12 | U96: 120 | X96: =SUMIFS('Transit Shipment'!$B$10:$B$1048462,'Transit Shipment'!$A$10:$A$1048462,B96,'Transit Shipment'!$C$10:$C$1048462,AA96) -> 0 | Y96: =IF(SUMIFS(DIH!$S$2:$S833,DIH!$D$2:$D833,B96,DIH!$U$2:$U833,AA96)>0,SUMIFS(DIH!$S$2:$S833,DIH!$D$2:$D833,B96,DIH!$U$2:$U833,AA96),0) -> 0 | Z96: =SUM(X96:Y96) -> 0 | AA96: BLR7 | AB96: =IF(ISNA(VLOOKUP($B96,'Business Report'!$D$2:$J$202,2,0)),"",VLOOKUP($B96,'Business Report'!$D$2:$J$202,2,0)) -> 35 | AC96: =SUMIFS(AFS!$P$2:$P$6260,AFS!$N$2:$N$6260,B96,AFS!$AT$2:$AT$6260,AA96) -> 3 | AD96: =CEILING(AC96/$W$2*$X$2,1)-sum(X96:Y96) -> 4 | AF96: =IF(ISNUMBER(AD96),IF(AD96<=0,"",IF(F96="","",E96*$AC$2+IF(F96>0,$AC$2,0)))) -> 4
A97: APR- Green | B97: CRM_AP_GREEN_PACK OF 2 | C97: CRASOME Apron for Men Women Chef Cooking Restaurants Gardening Workshop, Barbers with Adjustable Strap and Two Pockets ( Green_Pack of 2) | D97: Apron | E97: =IF(ISNUMBER(AD97),IF(AD97>=0,IF(AD97=0,1,INT(AD97/$AC$2)),""),"") -> 1 | F97: =IF(E97="","",IF(AD97=0,0,AD97/$AC$2-E97)) -> 0 | G97: =IF(ISERROR(SEARCH("Apron",D97)),AF97,"") | K97: =IF(ISNUMBER($AF97),2*$AF97,"") | P97: {=XLOOKUP(B97,Weight!B:B,Weight!D:D,"#N/A",0)} -> 220 | Q97: =IF(AF97="","",AF97*P97) | S97: 392620 | T97: 12 | U97: 120 | X97: =SUMIFS('Transit Shipment'!$B$10:$B$1048462,'Transit Shipment'!$A$10:$A$1048462,B97,'Transit Shipment'!$C$10:$C$1048462,AA97) -> 0 | Y97: =IF(SUMIFS(DIH!$S$2:$S833,DIH!$D$2:$D833,B97,DIH!$U$2:$U833,AA97)>0,SUMIFS(DIH!$S$2:$S833,DIH!$D$2:$D833,B97,DIH!$U$2:$U833,AA97),0) -> 0 | Z97: =SUM(X97:Y97) -> 0 | AA97: CJB1 | AB97: =IF(ISNA(VLOOKUP($B97,'Business Report'!$D$2:$J$202,2,0)),"",VLOOKUP($B97,'Business Report'!$D$2:$J$202,2,0)) -> 35 | AC97: =SUMIFS(AFS!$P$2:$P$6260,AFS!$N$2:$N$6260,B97,AFS!$AT$2:$AT$6260,AA97) -> 0 | AD97: =CEILING(AC97/$W$2*$X$2,1)-sum(X97:Y97) -> 0 | AF97: =IF(ISNUMBER(AD97),IF(AD97<=0,"",IF(F97="","",E97*$AC$2+IF(F97>0,$AC$2,0))))
A98: APR- Green | B98: CRM_AP_GREEN_PACK OF 2 | C98: CRASOME Apron for Men Women Chef Cooking Restaurants Gardening Workshop, Barbers with Adjustable Strap and Two Pockets ( Green_Pack of 2) | D98: Apron | E98: =IF(ISNUMBER(AD98),IF(AD98>=0,IF(AD98=0,1,INT(AD98/$AC$2)),""),"") | F98: =IF(E98="","",IF(AD98=0,0,AD98/$AC$2-E98)) | G98: =IF(ISERROR(SEARCH("Apron",D98)),AF98,"") | K98: =IF(ISNUMBER($AF98),2*$AF98,"") | P98: {=XLOOKUP(B98,Weight!B:B,Weight!D:D,"#N/A",0)} -> 220 | Q98: =IF(AF98="","",AF98*P98) | S98: 392620 | T98: 12 | U98: 120 | X98: =SUMIFS('Transit Shipment'!$B$10:$B$1048462,'Transit Shipment'!$A$10:$A$1048462,B98,'Transit Shipment'!$C$10:$C$1048462,AA98) -> 0 | Y98: =IF(SUMIFS(DIH!$S$2:$S833,DIH!$D$2:$D833,B98,DIH!$U$2:$U833,AA98)>0,SUMIFS(DIH!$S$2:$S833,DIH!$D$2:$D833,B98,DIH!$U$2:$U833,AA98),0) -> 1 | Z98: =SUM(X98:Y98) -> 1 | AA98: MAA4 | AB98: =IF(ISNA(VLOOKUP($B98,'Business Report'!$D$2:$J$202,2,0)),"",VLOOKUP($B98,'Business Report'!$D$2:$J$202,2,0)) -> 35 | AC98: =SUMIFS(AFS!$P$2:$P$6260,AFS!$N$2:$N$6260,B98,AFS!$AT$2:$AT$6260,AA98) -> 0 | AD98: =CEILING(AC98/$W$2*$X$2,1)-sum(X98:Y98) -> -1 | AF98: =IF(ISNUMBER(AD98),IF(AD98<=0,"",IF(F98="","",E98*$AC$2+IF(F98>0,$AC$2,0))))
A99: APR- Green | B99: CRM_AP_GREEN_PACK OF 2 | C99: CRASOME Apron for Men Women Chef Cooking Restaurants Gardening Workshop, Barbers with Adjustable Strap and Two Pockets ( Green_Pack of 2) | D99: Apron | E99: =IF(ISNUMBER(AD99),IF(AD99>=0,IF(AD99=0,1,INT(AD99/$AC$2)),""),"") -> 1 | F99: =IF(E99="","",IF(AD99=0,0,AD99/$AC$2-E99)) -> 0 | G99: =IF(ISERROR(SEARCH("Apron",D99)),AF99,"") | K99: =IF(ISNUMBER($AF99),2*$AF99,"") | P99: {=XLOOKUP(B99,Weight!B:B,Weight!D:D,"#N/A",0)} -> 220 | Q99: =IF(AF99="","",AF99*P99) | S99: 392620 | T99: 12 | U99: 120 | X99: =SUMIFS('Transit Shipment'!$B$10:$B$1048462,'Transit Shipment'!$A$10:$A$1048462,B99,'Transit Shipment'!$C$10:$C$1048462,AA99) -> 0 | Y99: =IF(SUMIFS(DIH!$S$2:$S833,DIH!$D$2:$D833,B99,DIH!$U$2:$U833,AA99)>0,SUMIFS(DIH!$S$2:$S833,DIH!$D$2:$D833,B99,DIH!$U$2:$U833,AA99),0) -> 0 | Z99: =SUM(X99:Y99) -> 0 | AA99: DEL4 | AB99: =IF(ISNA(VLOOKUP($B99,'Business Report'!$D$2:$J$202,2,0)),"",VLOOKUP($B99,'Business Report'!$D$2:$J$202,2,0)) -> 35 | AC99: =SUMIFS(AFS!$P$2:$P$6260,AFS!$N$2:$N$6260,B99,AFS!$AT$2:$AT$6260,AA99) -> 0 | AD99: =CEILING(AC99/$W$2*$X$2,1)-sum(X99:Y99) -> 0 | AF99: =IF(ISNUMBER(AD99),IF(AD99<=0,"",IF(F99="","",E99*$AC$2+IF(F99>0,$AC$2,0))))
A100: APR- Green | B100: CRM_AP_GREEN_PACK OF 2 | C100: CRASOME Apron for Men Women Chef Cooking Restaurants Gardening Workshop, Barbers with Adjustable Strap and Two Pockets ( Green_Pack of 2) | D100: Apron | E100: =IF(ISNUMBER(AD100),IF(AD100>=0,IF(AD100=0,1,INT(AD100/$AC$2)),""),"") | F100: =IF(E100="","",IF(AD100=0,0,AD100/$AC$2-E100)) | G100: =IF(ISERROR(SEARCH("Apron",D100)),AF100,"") | K100: =IF(ISNUMBER($AF100),2*$AF100,"") | P100: {=XLOOKUP(B100,Weight!B:B,Weight!D:D,"#N/A",0)} -> 220 | Q100: =IF(AF100="","",AF100*P100) | S100: 392620 | T100: 12 | U100: 120 | X100: =SUMIFS('Transit Shipment'!$B$10:$B$1048462,'Transit Shipment'!$A$10:$A$1048462,B100,'Transit Shipment'!$C$10:$C$1048462,AA100) -> 0 | Y100: =IF(SUMIFS(DIH!$S$2:$S833,DIH!$D$2:$D833,B100,DIH!$U$2:$U833,AA100)>0,SUMIFS(DIH!$S$2:$S833,DIH!$D$2:$D833,B100,DIH!$U$2:$U833,AA100),0) -> 3 | Z100: =SUM(X100:Y100) -> 3 | AA100: DEL5 | AB100: =IF(ISNA(VLOOKUP($B100,'Business Report'!$D$2:$J$202,2,0)),"",VLOOKUP($B100,'Business Report'!$D$2:$J$202,2,0)) -> 35 | AC100: =SUMIFS(AFS!$P$2:$P$6260,AFS!$N$2:$N$6260,B100,AFS!$AT$2:$AT$6260,AA100) -> 1 | AD100: =CEILING(AC100/$W$2*$X$2,1)-sum(X100:Y100) -> -1 | AF100: =IF(ISNUMBER(AD100),IF(AD100<=0,"",IF(F100="","",E100*$AC$2+IF(F100>0,$AC$2,0))))
...

Sheet Sheet13
A1: Apron_Black | B1: {=UNIQUE(A1:A819)} -> Apron_Black
A2: Apron_Black | B2: Apron_Blue
A3: Apron_Black | B3: Apron_Brown
A4: Apron_Black | B4: Apron_Grey
A5: Apron_Black | B5: Apron_Red
A6: Apron_Black | B6: CRM_AP_TAN
A7: Apron_Black | B7: CRM_AP_GREEN
A8: Apron_Black | B8: CRM_AP_BLACK_PACK OF 2
A9: Apron_Black | B9: CRM_AP_BLUE_PACK OF 2
A10: Apron_Blue | B10: CRM_AP_BROWN_PACK OF 2
A11: Apron_Blue | B11: CRM_AP_GREEN_PACK OF 2
A12: Apron_Blue | B12: CRM_AP_GREY_PACK OF 2
A13: Apron_Blue | B13: CRM_AP_RED_PACK OF 2
... A91: CRM_AP_GREEN_PACK OF 2 | B91: CRM-Cube1-Grey-Pack3-1
A92: CRM_AP_GREEN_PACK OF 2
A93: CRM_AP_GREEN_PACK OF 2
A94: CRM_AP_GREEN_PACK OF 2
A95: CRM_AP_GREEN_PACK OF 2
A96: CRM_AP_GREEN_PACK OF 2
A97: CRM_AP_GREEN_PACK OF 2
A98: CRM_AP_GREEN_PACK OF 2
A99: CRM_AP_GREEN_PACK OF 2
A100: CRM_AP_GREY_PACK OF 2
A101: CRM_AP_GREY_PACK OF 2
A102: CRM_AP_GREY_PACK OF 2
A103: CRM_AP_GREY_PACK OF 2
... A819: CRM-Cube1-Grey-Pack3-1

Sheet Stock
E1: Total Actual Qty | G1: =sum(F3:F1001) -> 3532 | I1: {=IF(OR(G1<>SUM(INDIRECT("Calculation!G3:O")), G1<>Boxes!C52), "Error", "")} -> Error | K1: Sep | L1: =IF(MONTH(DATEVALUE(K1&" 1"))<>MONTH(TODAY()), "Change Url Stock Manager", "") -> Change Url Stock Manager | M1: Url ----->> | N1: 1xsE5TY9L1oXdnssxXiLmdN0LEb2tXUlxQPtf5qE-9rI
A2: Model | B2: SKU | C2: Required Qty | E2: Model | F2: Required Qty | G2: Available Qty | H2: Diffrence | K2: =IFERROR(__xludf.DUMMYFUNCTION("IMPORTRANGE(N1,""Monthly Avg.!A1:T200"")"),"") | N2: =IFERROR(__xludf.DUMMYFUNCTION("""COMPUTED_VALUE"""),"CRASOME (Sep '25)") -> CRASOME (Sep '25) | X2: =IFERROR(__xludf.DUMMYFUNCTION("""COMPUTED_VALUE"""),"Total Debit of current month") -> Total Debit of current month | Y2: =IFERROR(__xludf.DUMMYFUNCTION("""COMPUTED_VALUE"""),"Aug '25 Closing Balance") -> Aug '25 Closing Balance
A3: APR- Sky Blue | C3: =sum(Calculation!$H$4:$H1001) -> 0 | E3: =IFERROR(__xludf.DUMMYFUNCTION("UNIQUE(FILTER(A3:A1001, C3:C1001 <> 0))"),"APR- Dark Blue") -> APR- Dark Blue | F3: =SUMIF(A:A,E3,C:C) -> 122 | G3: =XLOOKUP(E3,K:K,Q:Q) -> 1766 | H3: =G3-F3 -> 1644 | K3: =IFERROR(__xludf.DUMMYFUNCTION("""COMPUTED_VALUE"""),"Model") -> Model | M3: =IFERROR(__xludf.DUMMYFUNCTION("""COMPUTED_VALUE"""),"Category") -> Category | N3: =IFERROR(__xludf.DUMMYFUNCTION("""COMPUTED_VALUE"""),"Owner") -> Owner | O3: =IFERROR(__xludf.DUMMYFUNCTION("""COMPUTED_VALUE"""),"Req.Stock") -> Req.Stock | P3: =IFERROR(__xludf.DUMMYFUNCTION("""COMPUTED_VALUE"""),"Avg.") -> Avg. | Q3: =IFERROR(__xludf.DUMMYFUNCTION("""COMPUTED_VALUE"""),"Balance") -> Balance | R3: =IFERROR(__xludf.DUMMYFUNCTION("""COMPUTED_VALUE"""),"Total Month") -> Total Month | S3: =IFERROR(__xludf.DUMMYFUNCTION("""COMPUTED_VALUE"""),"Apr") -> Apr | T3: =IFERROR(__xludf.DUMMYFUNCTION("""COMPUTED_VALUE"""),"May") -> May | U3: =IFERROR(__xludf.DUMMYFUNCTION("""COMPUTED_VALUE"""),"June") -> June | V3: =IFERROR(__xludf.DUMMYFUNCTION("""COMPUTED_VALUE"""),"July") -> July | W3: =IFERROR(__xludf.DUMMYFUNCTION("""COMPUTED_VALUE"""),"Aug") -> Aug | Y3: =IFERROR(__xludf.DUMMYFUNCTION("""COMPUTED_VALUE"""),"Balance") -> Balance | AB3: =IFERROR(__xludf.DUMMYFUNCTION("""COMPUTED_VALUE"""),"Monthly Avg. Multipler (Advance Stock)") -> Monthly Avg. Multipler (Advance Stock)
A4: APR- Dark Blue | C4: =sum(Calculation!$I$4:$I1001) -> 122 | E4: =IFERROR(__xludf.DUMMYFUNCTION("""COMPUTED_VALUE"""),"APR- Brown") -> APR- Brown | F4: =SUMIF(A:A,E4,C:C) -> 102 | G4: =XLOOKUP(E4,K:K,Q:Q) -> 1363 | H4: =G4-F4 -> 1261 | K4: =IFERROR(__xludf.DUMMYFUNCTION("""COMPUTED_VALUE"""),"Ultra") -> Ultra | M4: =IFERROR(__xludf.DUMMYFUNCTION("""COMPUTED_VALUE"""),"Printer") -> Printer | N4: =IFERROR(__xludf.DUMMYFUNCTION("""COMPUTED_VALUE"""),"AG") -> AG | O4: =IFERROR(__xludf.DUMMYFUNCTION("""COMPUTED_VALUE"""),0.0) -> 0 | P4: =IFERROR(__xludf.DUMMYFUNCTION("""COMPUTED_VALUE"""),0.0) -> 0 | Q4: =IFERROR(__xludf.DUMMYFUNCTION("""COMPUTED_VALUE"""),0.0) -> 0 | R4: =IFERROR(__xludf.DUMMYFUNCTION("""COMPUTED_VALUE"""),5.0) -> 5 | S4: =IFERROR(__xludf.DUMMYFUNCTION("""COMPUTED_VALUE"""),0.0) -> 0 | T4: =IFERROR(__xludf.DUMMYFUNCTION("""COMPUTED_VALUE"""),0.0) -> 0 | U4: =IFERROR(__xludf.DUMMYFUNCTION("""COMPUTED_VALUE"""),0.0) -> 0 | V4: =IFERROR(__xludf.DUMMYFUNCTION("""COMPUTED_VALUE"""),0.0) -> 0 | W4: =IFERROR(__xludf.DUMMYFUNCTION("""COMPUTED_VALUE"""),0.0) -> 0 | X4: =IFERROR(__xludf.DUMMYFUNCTION("""COMPUTED_VALUE"""),0.0) -> 0 | Y4: =IFERROR(__xludf.DUMMYFUNCTION("""COMPUTED_VALUE"""),0.0) -> 0 | Z4: =IFERROR(__xludf.DUMMYFUNCTION("""COMPUTED_VALUE"""),"Discontinued") -> Discontinued
A5: APR- Brown | C5: =sum(Calculation!$J$4:$J1001) -> 102 | E5: =IFERROR(__xludf.DUMMYFUNCTION("""COMPUTED_VALUE"""),"APR- Green") -> APR- Green | F5: =SUMIF(A:A,E5,C:C) -> 64 | G5: =XLOOKUP(E5,K:K,Q:Q) -> 965 | H5: =G5-F5 -> 901 | K5: =IFERROR(__xludf.DUMMYFUNCTION("""COMPUTED_VALUE"""),"BAJAJ") -> BAJAJ | M5: =IFERROR(__xludf.DUMMYFUNCTION("""COMPUTED_VALUE"""),"Printer") -> Printer | N5: =IFERROR(__xludf.DUMMYFUNCTION("""COMPUTED_VALUE"""),"AG") -> AG | O5: =IFERROR(__xludf.DUMMYFUNCTION("""COMPUTED_VALUE"""),-14.0) -> -14 | P5: =IFERROR(__xludf.DUMMYFUNCTION("""COMPUTED_VALUE"""),221.0) -> 221 | Q5: =IFERROR(__xludf.DUMMYFUNCTION("""COMPUTED_VALUE"""),235.0) -> 235 | R5: =IFERROR(__xludf.DUMMYFUNCTION("""COMPUTED_VALUE"""),5.0) -> 5 | S5: =IFERROR(__xludf.DUMMYFUNCTION("""COMPUTED_VALUE"""),182.0) -> 182 | T5: =IFERROR(__xludf.DUMMYFUNCTION("""COMPUTED_VALUE"""),37.0) -> 37 | U5: =IFERROR(__xludf.DUMMYFUNCTION("""COMPUTED_VALUE"""),93.0) -> 93 | V5: =IFERROR(__xludf.DUMMYFUNCTION("""COMPUTED_VALUE"""),140.0) -> 140 | W5: =IFERROR(__xludf.DUMMYFUNCTION("""COMPUTED_VALUE"""),283.0) -> 283 | X5: =IFERROR(__xludf.DUMMYFUNCTION("""COMPUTED_VALUE"""),151.0) -> 151 | Y5: =IFERROR(__xludf.DUMMYFUNCTION("""COMPUTED_VALUE"""),383.0) -> 383 | AB5: =IFERROR(__xludf.DUMMYFUNCTION("""COMPUTED_VALUE"""),1.5) -> 1.5
A6: APR- Green | C6: =sum(Calculation!$K$4:$K1001) -> 64 | E6: =IFERROR(__xludf.DUMMYFUNCTION("""COMPUTED_VALUE"""),"APR- Tan") -> APR- Tan | F6: =SUMIF(A:A,E6,C:C) -> 152 | G6: =XLOOKUP(E6,K:K,Q:Q) -> 1447 | H6: =G6-F6 -> 1295 | K6: =IFERROR(__xludf.DUMMYFUNCTION("""COMPUTED_VALUE"""),"WG") -> WG | M6: =IFERROR(__xludf.DUMMYFUNCTION("""COMPUTED_VALUE"""),"WG") -> WG | N6: =IFERROR(__xludf.DUMMYFUNCTION("""COMPUTED_VALUE"""),"AG") -> AG | O6: =IFERROR(__xludf.DUMMYFUNCTION("""COMPUTED_VALUE"""),-34.0) -> -34 | P6: =IFERROR(__xludf.DUMMYFUNCTION("""COMPUTED_VALUE"""),0.0) -> 0 | Q6: =IFERROR(__xludf.DUMMYFUNCTION("""COMPUTED_VALUE"""),34.0) -> 34 | R6: =IFERROR(__xludf.DUMMYFUNCTION("""COMPUTED_VALUE"""),5.0) -> 5 | S6: =IFERROR(__xludf.DUMMYFUNCTION("""COMPUTED_VALUE"""),0.0) -> 0 | T6: =IFERROR(__xludf.DUMMYFUNCTION("""COMPUTED_VALUE"""),0.0) -> 0 | U6: =IFERROR(__xludf.DUMMYFUNCTION("""COMPUTED_VALUE"""),0.0) -> 0 | V6: =IFERROR(__xludf.DUMMYFUNCTION("""COMPUTED_VALUE"""),0.0) -> 0 | W6: =IFERROR(__xludf.DUMMYFUNCTION("""COMPUTED_VALUE"""),0.0) -> 0 | X6: =IFERROR(__xludf.DUMMYFUNCTION("""COMPUTED_VALUE"""),0.0) -> 0 | Y6: =IFERROR(__xludf.DUMMYFUNCTION("""COMPUTED_VALUE"""),34.0) -> 34 | Z6: =IFERROR(__xludf.DUMMYFUNCTION("""COMPUTED_VALUE"""),"Discontinued") -> Discontinued
A7: APR- Tan | C7: =sum(Calculation!$L$4:$L1001) -> 152 | E7: =IFERROR(__xludf.DUMMYFUNCTION("""COMPUTED_VALUE"""),"APR- Black") -> APR- Black | F7: =SUMIF(A:A,E7,C:C) -> 128 | G7: =XLOOKUP(E7,K:K,Q:Q) -> 2649 | H7: =G7-F7 -> 2521
A8: APR- Black | C8: =sum(Calculation!$M$4:$M1001) -> 128 | E8: =IFERROR(__xludf.DUMMYFUNCTION("""COMPUTED_VALUE"""),"APR- Red") -> APR- Red | F8: =SUMIF(A:A,E8,C:C) -> 38 | G8: =XLOOKUP(E8,K:K,Q:Q) -> 892 | H8: =G8-F8 -> 854 | K8: =IFERROR(__xludf.DUMMYFUNCTION("""COMPUTED_VALUE"""),"M200") -> M200 | M8: =IFERROR(__xludf.DUMMYFUNCTION("""COMPUTED_VALUE"""),"Printer") -> Printer | N8: =IFERROR(__xludf.DUMMYFUNCTION("""COMPUTED_VALUE"""),"AG") -> AG | O8: =IFERROR(__xludf.DUMMYFUNCTION("""COMPUTED_VALUE"""),-3.0) -> -3 | P8: =IFERROR(__xludf.DUMMYFUNCTION("""COMPUTED_VALUE"""),0.0) -> 0 | Q8: =IFERROR(__xludf.DUMMYFUNCTION("""COMPUTED_VALUE"""),3.0) -> 3 | R8: =IFERROR(__xludf.DUMMYFUNCTION("""COMPUTED_VALUE"""),5.0) -> 5 | S8: =IFERROR(__xludf.DUMMYFUNCTION("""COMPUTED_VALUE"""),0.0) -> 0 | T8: =IFERROR(__xludf.DUMMYFUNCTION("""COMPUTED_VALUE"""),0.0) -> 0 | U8: =IFERROR(__xludf.DUMMYFUNCTION("""COMPUTED_VALUE"""),0.0) -> 0 | V8: =IFERROR(__xludf.DUMMYFUNCTION("""COMPUTED_VALUE"""),0.0) -> 0 | W8: =IFERROR(__xludf.DUMMYFUNCTION("""COMPUTED_VALUE"""),0.0) -> 0 | X8: =IFERROR(__xludf.DUMMYFUNCTION("""COMPUTED_VALUE"""),0.0) -> 0 | Y8: =IFERROR(__xludf.DUMMYFUNCTION("""COMPUTED_VALUE"""),3.0) -> 3 | Z8: =IFERROR(__xludf.DUMMYFUNCTION("""COMPUTED_VALUE"""),"Discontinued") -> Discontinued | AB8: =IFERROR(__xludf.DUMMYFUNCTION("""COMPUTED_VALUE"""),1.0) -> 1
A9: APR- Red | C9: =sum(Calculation!$N$4:$N1001) -> 38 | E9: =IFERROR(__xludf.DUMMYFUNCTION("""COMPUTED_VALUE"""),"APR- Grey") -> APR- Grey | F9: =SUMIF(A:A,E9,C:C) -> 28 | G9: =XLOOKUP(E9,K:K,Q:Q) -> 582 | H9: =G9-F9 -> 554 | K9: =IFERROR(__xludf.DUMMYFUNCTION("""COMPUTED_VALUE"""),"HP 3-4") -> HP 3-4 | M9: =IFERROR(__xludf.DUMMYFUNCTION("""COMPUTED_VALUE"""),"Printer") -> Printer | N9: =IFERROR(__xludf.DUMMYFUNCTION("""COMPUTED_VALUE"""),"AG") -> AG | O9: =IFERROR(__xludf.DUMMYFUNCTION("""COMPUTED_VALUE"""),-14.0) -> -14 | P9: =IFERROR(__xludf.DUMMYFUNCTION("""COMPUTED_VALUE"""),0.0) -> 0 | Q9: =IFERROR(__xludf.DUMMYFUNCTION("""COMPUTED_VALUE"""),14.0) -> 14 | R9: =IFERROR(__xludf.DUMMYFUNCTION("""COMPUTED_VALUE"""),5.0) -> 5 | S9: =IFERROR(__xludf.DUMMYFUNCTION("""COMPUTED_VALUE"""),0.0) -> 0 | T9: =IFERROR(__xludf.DUMMYFUNCTION("""COMPUTED_VALUE"""),0.0) -> 0 | U9: =IFERROR(__xludf.DUMMYFUNCTION("""COMPUTED_VALUE"""),0.0) -> 0 | V9: =IFERROR(__xludf.DUMMYFUNCTION("""COMPUTED_VALUE"""),0.0) -> 0 | W9: =IFERROR(__xludf.DUMMYFUNCTION("""COMPUTED_VALUE"""),0.0) -> 0 | X9: =IFERROR(__xludf.DUMMYFUNCTION("""COMPUTED_VALUE"""),0.0) -> 0 | Y9: =IFERROR(__xludf.DUMMYFUNCTION("""COMPUTED_VALUE"""),14.0) -> 14 | Z9: =IFERROR(__xludf.DUMMYFUNCTION("""COMPUTED_VALUE"""),"Discontinued") -> Discontinued | AB9: =IFERROR(__xludf.DUMMYFUNCTION("""COMPUTED_VALUE"""),1.0) -> 1
A10: APR- Grey | C10: =sum(Calculation!$O$4:$O1001) -> 28 | E10: =IFERROR(__xludf.DUMMYFUNCTION("""COMPUTED_VALUE"""),"BAJAJ") -> BAJAJ | F10: =SUMIF(A:A,E10,C:C) -> 158 | G10: =XLOOKUP(E10,K:K,Q:Q) -> 235 | H10: =G10-F10 -> 77 | K10: =IFERROR(__xludf.DUMMYFUNCTION("""COMPUTED_VALUE"""),"CanonG") -> CanonG | M10: =IFERROR(__xludf.DUMMYFUNCTION("""COMPUTED_VALUE"""),"Printer") -> Printer | N10: =IFERROR(__xludf.DUMMYFUNCTION("""COMPUTED_VALUE"""),"AG") -> AG | O10: =IFERROR(__xludf.DUMMYFUNCTION("""COMPUTED_VALUE"""),-70.0) -> -70 | P10: =IFERROR(__xludf.DUMMYFUNCTION("""COMPUTED_VALUE"""),2.0) -> 2 | Q10: =IFERROR(__xludf.DUMMYFUNCTION("""COMPUTED_VALUE"""),72.0) -> 72 | R10: =IFERROR(__xludf.DUMMYFUNCTION("""COMPUTED_VALUE"""),5.0) -> 5 | S10: =IFERROR(__xludf.DUMMYFUNCTION("""COMPUTED_VALUE"""),1.0) -> 1 | T10: =IFERROR(__xludf.DUMMYFUNCTION("""COMPUTED_VALUE"""),2.0) -> 2 | U10: =IFERROR(__xludf.DUMMYFUNCTION("""COMPUTED_VALUE"""),2.0) -> 2 | V10: =IFERROR(__xludf.DUMMYFUNCTION("""COMPUTED_VALUE"""),0.0) -> 0 | W10: =IFERROR(__xludf.DUMMYFUNCTION("""COMPUTED_VALUE"""),1.0) -> 1 | X10: =IFERROR(__xludf.DUMMYFUNCTION("""COMPUTED_VALUE"""),4.0) -> 4 | Y10: =IFERROR(__xludf.DUMMYFUNCTION("""COMPUTED_VALUE"""),75.0) -> 75 | Z10: =IFERROR(__xludf.DUMMYFUNCTION("""COMPUTED_VALUE"""),"Discontinued") -> Discontinued | AB10: =IFERROR(__xludf.DUMMYFUNCTION("""COMPUTED_VALUE"""),1.25) -> 1.25
A11: =IFERROR(__xludf.DUMMYFUNCTION("FILTER({Calculation!A4:A1001,Calculation!B4:B1001,Calculation!G4:G1001},Calculation!D4:D1001<>""Apron"",Calculation!G4:G1001<>"""",Calculation!G4:G1001<>""0"")"),"BAJAJ") -> BAJAJ | B11: =IFERROR(__xludf.DUMMYFUNCTION("""COMPUTED_VALUE"""),"Bajaj_2") -> Bajaj_2 | C11: =IFERROR(__xludf.DUMMYFUNCTION("""COMPUTED_VALUE"""),2.0) -> 2 | E11: =IFERROR(__xludf.DUMMYFUNCTION("""COMPUTED_VALUE"""),"Bajaj (Grey)") -> Bajaj (Grey) | F11: =SUMIF(A:A,E11,C:C) -> 464 | G11: =XLOOKUP(E11,K:K,Q:Q) -> 330 | H11: =G11-F11 -> -134 | K11: =IFERROR(__xludf.DUMMYFUNCTION("""COMPUTED_VALUE"""),"L3110") -> L3110 | M11: =IFERROR(__xludf.DUMMYFUNCTION("""COMPUTED_VALUE"""),"Printer") -> Printer | N11: =IFERROR(__xludf.DUMMYFUNCTION("""COMPUTED_VALUE"""),"AG") -> AG | O11: =IFERROR(__xludf.DUMMYFUNCTION("""COMPUTED_VALUE"""),21.0) -> 21 | P11: =IFERROR(__xludf.DUMMYFUNCTION("""COMPUTED_VALUE"""),29.0) -> 29 | Q11: =IFERROR(__xludf.DUMMYFUNCTION("""COMPUTED_VALUE"""),8.0) -> 8 | R11: =IFERROR(__xludf.DUMMYFUNCTION("""COMPUTED_VALUE"""),5.0) -> 5 | S11: =IFERROR(__xludf.DUMMYFUNCTION("""COMPUTED_VALUE"""),31.0) -> 31 | T11: =IFERROR(__xludf.DUMMYFUNCTION("""COMPUTED_VALUE"""),31.0) -> 31 | U11: =IFERROR(__xludf.DUMMYFUNCTION("""COMPUTED_VALUE"""),28.0) -> 28 | V11: =IFERROR(__xludf.DUMMYFUNCTION("""COMPUTED_VALUE"""),32.0) -> 32 | W11: =IFERROR(__xludf.DUMMYFUNCTION("""COMPUTED_VALUE"""),20.0) -> 20 | X11: =IFERROR(__xludf.DUMMYFUNCTION("""COMPUTED_VALUE"""),12.0) -> 12 | Y11: =IFERROR(__xludf.DUMMYFUNCTION("""COMPUTED_VALUE"""),14.0) -> 14 | Z11: =IFERROR(__xludf.DUMMYFUNCTION("""COMPUTED_VALUE"""),"Discontinued") -> Discontinued | AB11: =IFERROR(__xludf.DUMMYFUNCTION("""COMPUTED_VALUE"""),1.0) -> 1
A12: =IFERROR(__xludf.DUMMYFUNCTION("""COMPUTED_VALUE"""),"BAJAJ") -> BAJAJ | B12: =IFERROR(__xludf.DUMMYFUNCTION("""COMPUTED_VALUE"""),"Bajaj_2") -> Bajaj_2 | C12: =IFERROR(__xludf.DUMMYFUNCTION("""COMPUTED_VALUE"""),2.0) -> 2 | E12: =IFERROR(__xludf.DUMMYFUNCTION("""COMPUTED_VALUE"""),"Bajaj (Black)") -> Bajaj (Black) | F12: =SUMIF(A:A,E12,C:C) -> 168 | G12: =XLOOKUP(E12,K:K,Q:Q) -> 468 | H12: =G12-F12 -> 300 | K12: =IFERROR(__xludf.DUMMYFUNCTION("""COMPUTED_VALUE"""),"L380") -> L380 | M12: =IFERROR(__xludf.DUMMYFUNCTION("""COMPUTED_VALUE"""),"Printer") -> Printer | N12: =IFERROR(__xludf.DUMMYFUNCTION("""COMPUTED_VALUE"""),"AG") -> AG | O12: =IFERROR(__xludf.DUMMYFUNCTION("""COMPUTED_VALUE"""),17.0) -> 17 | P12: =IFERROR(__xludf.DUMMYFUNCTION("""COMPUTED_VALUE"""),16.0) -> 16 | Q12: =IFERROR(__xludf.DUMMYFUNCTION("""COMPUTED_VALUE"""),-1.0) -> -1 | R12: =IFERROR(__xludf.DUMMYFUNCTION("""COMPUTED_VALUE"""),5.0) -> 5 | S12: =IFERROR(__xludf.DUMMYFUNCTION("""COMPUTED_VALUE"""),1.0) -> 1 | T12: =IFERROR(__xludf.DUMMYFUNCTION("""COMPUTED_VALUE"""),22.0) -> 22 | U12: =IFERROR(__xludf.DUMMYFUNCTION("""COMPUTED_VALUE"""),21.0) -> 21 | V12: =IFERROR(__xludf.DUMMYFUNCTION("""COMPUTED_VALUE"""),27.0) -> 27 | W12: =IFERROR(__xludf.DUMMYFUNCTION("""COMPUTED_VALUE"""),7.0) -> 7 | X12: =IFERROR(__xludf.DUMMYFUNCTION("""COMPUTED_VALUE"""),9.0) -> 9 | Y12: =IFERROR(__xludf.DUMMYFUNCTION("""COMPUTED_VALUE"""),6.0) -> 6 | Z12: =IFERROR(__xludf.DUMMYFUNCTION("""COMPUTED_VALUE"""),"Discontinued") -> Discontinued | AB12: =IFERROR(__xludf.DUMMYFUNCTION("""COMPUTED_VALUE"""),1.0) -> 1
A13: =IFERROR(__xludf.DUMMYFUNCTION("""COMPUTED_VALUE"""),"BAJAJ") -> BAJAJ | B13: =IFERROR(__xludf.DUMMYFUNCTION("""COMPUTED_VALUE"""),"Bajaj_2") -> Bajaj_2 | C13: =IFERROR(__xludf.DUMMYFUNCTION("""COMPUTED_VALUE"""),2.0) -> 2 | E13: =IFERROR(__xludf.DUMMYFUNCTION("""COMPUTED_VALUE"""),"DC (NW Black)") -> DC (NW Black) | F13: =SUMIF(A:A,E13,C:C) -> 118 | G13: =XLOOKUP(E13,K:K,Q:Q) -> 539 | H13: =G13-F13 -> 421 | K13: =IFERROR(__xludf.DUMMYFUNCTION("""COMPUTED_VALUE"""),"L2321") -> L2321 | M13: =IFERROR(__xludf.DUMMYFUNCTION("""COMPUTED_VALUE"""),"Printer") -> Printer | N13: =IFERROR(__xludf.DUMMYFUNCTION("""COMPUTED_VALUE"""),"AG") -> AG | O13: =IFERROR(__xludf.DUMMYFUNCTION("""COMPUTED_VALUE"""),4.0) -> 4 | P13: =IFERROR(__xludf.DUMMYFUNCTION("""COMPUTED_VALUE"""),10.0) -> 10 | Q13: =IFERROR(__xludf.DUMMYFUNCTION("""COMPUTED_VALUE"""),6.0) -> 6 | R13: =IFERROR(__xludf.DUMMYFUNCTION("""COMPUTED_VALUE"""),5.0) -> 5 | S13: =IFERROR(__xludf.DUMMYFUNCTION("""COMPUTED_VALUE"""),34.0) -> 34 | T13: =IFERROR(__xludf.DUMMYFUNCTION("""COMPUTED_VALUE"""),2.0) -> 2 | U13: =IFERROR(__xludf.DUMMYFUNCTION("""COMPUTED_VALUE"""),1.0) -> 1 | V13: =IFERROR(__xludf.DUMMYFUNCTION("""COMPUTED_VALUE"""),4.0) -> 4 | W13: =IFERROR(__xludf.DUMMYFUNCTION("""COMPUTED_VALUE"""),7.0) -> 7 | X13: =IFERROR(__xludf.DUMMYFUNCTION("""COMPUTED_VALUE"""),5.0) -> 5 | Y13: =IFERROR(__xludf.DUMMYFUNCTION("""COMPUTED_VALUE"""),5.0) -> 5 | Z13: =IFERROR(__xludf.DUMMYFUNCTION("""COMPUTED_VALUE"""),"Discontinued") -> Discontinued | AB13: =IFERROR(__xludf.DUMMYFUNCTION("""COMPUTED_VALUE"""),1.0) -> 1
A14: =IFERROR(__xludf.DUMMYFUNCTION("""COMPUTED_VALUE"""),"BAJAJ") -> BAJAJ | B14: =IFERROR(__xludf.DUMMYFUNCTION("""COMPUTED_VALUE"""),"Bajaj_2") -> Bajaj_2 | C14: =IFERROR(__xludf.DUMMYFUNCTION("""COMPUTED_VALUE"""),2.0) -> 2 | E14: =IFERROR(__xludf.DUMMYFUNCTION("""COMPUTED_VALUE"""),"DC (NW Grey)") -> DC (NW Grey) | F14: =SUMIF(A:A,E14,C:C) -> 68 | G14: =XLOOKUP(E14,K:K,Q:Q) -> 202 | H14: =G14-F14 -> 134 | K14: =IFERROR(__xludf.DUMMYFUNCTION("""COMPUTED_VALUE"""),"M126nw") -> M126nw | M14: =IFERROR(__xludf.DUMMYFUNCTION("""COMPUTED_VALUE"""),"Printer") -> Printer | N14: =IFERROR(__xludf.DUMMYFUNCTION("""COMPUTED_VALUE"""),"AG") -> AG | O14: =IFERROR(__xludf.DUMMYFUNCTION("""COMPUTED_VALUE"""),0.0) -> 0 | P14: =IFERROR(__xludf.DUMMYFUNCTION("""COMPUTED_VALUE"""),0.0) -> 0 | Q14: =IFERROR(__xludf.DUMMYFUNCTION("""COMPUTED_VALUE"""),0.0) -> 0 | R14: =IFERROR(__xludf.DUMMYFUNCTION("""COMPUTED_VALUE"""),5.0) -> 5 | S14: =IFERROR(__xludf.DUMMYFUNCTION("""COMPUTED_VALUE"""),0.0) -> 0 | T14: =IFERROR(__xludf.DUMMYFUNCTION("""COMPUTED_VALUE"""),0.0) -> 0 | U14: =IFERROR(__xludf.DUMMYFUNCTION("""COMPUTED_VALUE"""),0.0) -> 0 | V14: =IFERROR(__xludf.DUMMYFUNCTION("""COMPUTED_VALUE"""),0.0) -> 0 | W14: =IFERROR(__xludf.DUMMYFUNCTION("""COMPUTED_VALUE"""),0.0) -> 0 | X14: =IFERROR(__xludf.DUMMYFUNCTION("""COMPUTED_VALUE"""),0.0) -> 0 | Y14: =IFERROR(__xludf.DUMMYFUNCTION("""COMPUTED_VALUE"""),30.0) -> 30 | Z14: =IFERROR(__xludf.DUMMYFUNCTION("""COMPUTED_VALUE"""),"Discontinued") -> Discontinued | AB14: =IFERROR(__xludf.DUMMYFUNCTION("""COMPUTED_VALUE"""),1.0) -> 1
A15: =IFERROR(__xludf.DUMMYFUNCTION("""COMPUTED_VALUE"""),"BAJAJ") -> BAJAJ | B15: =IFERROR(__xludf.DUMMYFUNCTION("""COMPUTED_VALUE"""),"Bajaj_2") -> Bajaj_2 | C15: =IFERROR(__xludf.DUMMYFUNCTION("""COMPUTED_VALUE"""),2.0) -> 2 | E15: =IFERROR(__xludf.DUMMYFUNCTION("""COMPUTED_VALUE"""),"DC-TS-NW-Black") -> DC-TS-NW-Black | F15: =SUMIF(A:A,E15,C:C) -> 10 | G15: =XLOOKUP(E15,K:K,Q:Q) -> 635 | H15: =G15-F15 -> 625 | K15: =IFERROR(__xludf.DUMMYFUNCTION("""COMPUTED_VALUE"""),"L2520D") -> L2520D | M15: =IFERROR(__xludf.DUMMYFUNCTION("""COMPUTED_VALUE"""),"Printer") -> Printer | N15: =IFERROR(__xludf.DUMMYFUNCTION("""COMPUTED_VALUE"""),"AG") -> AG | O15: =IFERROR(__xludf.DUMMYFUNCTION("""COMPUTED_VALUE"""),1.0) -> 1 | P15: =IFERROR(__xludf.DUMMYFUNCTION("""COMPUTED_VALUE"""),4.0) -> 4 | Q15: =IFERROR(__xludf.DUMMYFUNCTION("""COMPUTED_VALUE"""),3.0) -> 3 | R15: =IFERROR(__xludf.DUMMYFUNCTION("""COMPUTED_VALUE"""),5.0) -> 5 | S15: =IFERROR(__xludf.DUMMYFUNCTION("""COMPUTED_VALUE"""),3.0) -> 3 | T15: =IFERROR(__xludf.DUMMYFUNCTION("""COMPUTED_VALUE"""),4.0) -> 4 | U15: =IFERROR(__xludf.DUMMYFUNCTION("""COMPUTED_VALUE"""),3.0) -> 3 | V15: =IFERROR(__xludf.DUMMYFUNCTION("""COMPUTED_VALUE"""),5.0) -> 5 | W15: =IFERROR(__xludf.DUMMYFUNCTION("""COMPUTED_VALUE"""),5.0) -> 5 | X15: =IFERROR(__xludf.DUMMYFUNCTION("""COMPUTED_VALUE"""),1.0) -> 1 | Y15: =IFERROR(__xludf.DUMMYFUNCTION("""COMPUTED_VALUE"""),-6.0) -> -6 | Z15: =IFERROR(__xludf.DUMMYFUNCTION("""COMPUTED_VALUE"""),"Discontinued") -> Discontinued | AB15: =IFERROR(__xludf.DUMMYFUNCTION("""COMPUTED_VALUE"""),1.0) -> 1
A16: =IFERROR(__xludf.DUMMYFUNCTION("""COMPUTED_VALUE"""),"BAJAJ") -> BAJAJ | B16: =IFERROR(__xludf.DUMMYFUNCTION("""COMPUTED_VALUE"""),"Bajaj_3") -> Bajaj_3 | C16: =IFERROR(__xludf.DUMMYFUNCTION("""COMPUTED_VALUE"""),4.0) -> 4 | E16: =IFERROR(__xludf.DUMMYFUNCTION("""COMPUTED_VALUE"""),"DC-TS-NW-Grey") -> DC-TS-NW-Grey | F16: =SUMIF(A:A,E16,C:C) -> 84 | G16: =XLOOKUP(E16,K:K,Q:Q) -> 215 | H16: =G16-F16 -> 131 | K16: =IFERROR(__xludf.DUMMYFUNCTION("""COMPUTED_VALUE"""),"EMG") -> EMG | M16: =IFERROR(__xludf.DUMMYFUNCTION("""COMPUTED_VALUE"""),"Printer") -> Printer | N16: =IFERROR(__xludf.DUMMYFUNCTION("""COMPUTED_VALUE"""),"AG") -> AG | O16: =IFERROR(__xludf.DUMMYFUNCTION("""COMPUTED_VALUE"""),-9.0) -> -9 | P16: =IFERROR(__xludf.DUMMYFUNCTION("""COMPUTED_VALUE"""),5.0) -> 5 | Q16: =IFERROR(__xludf.DUMMYFUNCTION("""COMPUTED_VALUE"""),14.0) -> 14 | R16: =IFERROR(__xludf.DUMMYFUNCTION("""COMPUTED_VALUE"""),5.0) -> 5 | S16: =IFERROR(__xludf.DUMMYFUNCTION("""COMPUTED_VALUE"""),1.0) -> 1 | T16: =IFERROR(__xludf.DUMMYFUNCTION("""COMPUTED_VALUE"""),3.0) -> 3 | U16: =IFERROR(__xludf.DUMMYFUNCTION("""COMPUTED_VALUE"""),4.0) -> 4 | V16: =IFERROR(__xludf.DUMMYFUNCTION("""COMPUTED_VALUE"""),6.0) -> 6 | W16: =IFERROR(__xludf.DUMMYFUNCTION("""COMPUTED_VALUE"""),7.0) -> 7 | X16: =IFERROR(__xludf.DUMMYFUNCTION("""COMPUTED_VALUE"""),6.0) -> 6 | Y16: =IFERROR(__xludf.DUMMYFUNCTION("""COMPUTED_VALUE"""),18.0) -> 18 | Z16: =IFERROR(__xludf.DUMMYFUNCTION("""COMPUTED_VALUE"""),"Discontinued") -> Discontinued | AB16: =IFERROR(__xludf.DUMMYFUNCTION("""COMPUTED_VALUE"""),1.0) -> 1
A17: =IFERROR(__xludf.DUMMYFUNCTION("""COMPUTED_VALUE"""),"BAJAJ") -> BAJAJ | B17: =IFERROR(__xludf.DUMMYFUNCTION("""COMPUTED_VALUE"""),"Bajaj_3") -> Bajaj_3 | C17: =IFERROR(__xludf.DUMMYFUNCTION("""COMPUTED_VALUE"""),2.0) -> 2 | E17: =IFERROR(__xludf.DUMMYFUNCTION("""COMPUTED_VALUE"""),"L3110 (Grey)") -> L3110 (Grey) | F17: =SUMIF(A:A,E17,C:C) -> 68 | G17: =XLOOKUP(E17,K:K,Q:Q) -> 423 | H17: =G17-F17 -> 355 | K17: =IFERROR(__xludf.DUMMYFUNCTION("""COMPUTED_VALUE"""),"HP 4123") -> HP 4123 | M17: =IFERROR(__xludf.DUMMYFUNCTION("""COMPUTED_VALUE"""),"Printer") -> Printer | N17: =IFERROR(__xludf.DUMMYFUNCTION("""COMPUTED_VALUE"""),"AG") -> AG | O17: =IFERROR(__xludf.DUMMYFUNCTION("""COMPUTED_VALUE"""),-2.0) -> -2 | P17: =IFERROR(__xludf.DUMMYFUNCTION("""COMPUTED_VALUE"""),0.0) -> 0 | Q17: =IFERROR(__xludf.DUMMYFUNCTION("""COMPUTED_VALUE"""),2.0) -> 2 | R17: =IFERROR(__xludf.DUMMYFUNCTION("""COMPUTED_VALUE"""),5.0) -> 5 | S17: =IFERROR(__xludf.DUMMYFUNCTION("""COMPUTED_VALUE"""),0.0) -> 0 | T17: =IFERROR(__xludf.DUMMYFUNCTION("""COMPUTED_VALUE"""),0.0) -> 0 | U17: =IFERROR(__xludf.DUMMYFUNCTION("""COMPUTED_VALUE"""),0.0) -> 0 | V17: =IFERROR(__xludf.DUMMYFUNCTION("""COMPUTED_VALUE"""),0.0) -> 0 | W17: =IFERROR(__xludf.DUMMYFUNCTION("""COMPUTED_VALUE"""),0.0) -> 0 | X17: =IFERROR(__xludf.DUMMYFUNCTION("""COMPUTED_VALUE"""),0.0) -> 0 | Y17: =IFERROR(__xludf.DUMMYFUNCTION("""COMPUTED_VALUE"""),2.0) -> 2 | Z17: =IFERROR(__xludf.DUMMYFUNCTION("""COMPUTED_VALUE"""),"Discontinued") -> Discontinued | AB17: =IFERROR(__xludf.DUMMYFUNCTION("""COMPUTED_VALUE"""),1.0) -> 1
A18: =IFERROR(__xludf.DUMMYFUNCTION("""COMPUTED_VALUE"""),"BAJAJ") -> BAJAJ | B18: =IFERROR(__xludf.DUMMYFUNCTION("""COMPUTED_VALUE"""),"Bajaj_3") -> Bajaj_3 | C18: =IFERROR(__xludf.DUMMYFUNCTION("""COMPUTED_VALUE"""),4.0) -> 4 | E18: =IFERROR(__xludf.DUMMYFUNCTION("""COMPUTED_VALUE"""),"L3110 (Black)") -> L3110 (Black) | F18: =SUMIF(A:A,E18,C:C) -> 100 | G18: =XLOOKUP(E18,K:K,Q:Q) -> 430 | H18: =G18-F18 -> 330 | K18: =IFERROR(__xludf.DUMMYFUNCTION("""COMPUTED_VALUE"""),"HP 1020") -> HP 1020 | M18: =IFERROR(__xludf.DUMMYFUNCTION("""COMPUTED_VALUE"""),"Printer") -> Printer | N18: =IFERROR(__xludf.DUMMYFUNCTION("""COMPUTED_VALUE"""),"AG") -> AG | O18: =IFERROR(__xludf.DUMMYFUNCTION("""COMPUTED_VALUE"""),-11.0) -> -11 | P18: =IFERROR(__xludf.DUMMYFUNCTION("""COMPUTED_VALUE"""),0.0) -> 0 | Q18: =IFERROR(__xludf.DUMMYFUNCTION("""COMPUTED_VALUE"""),11.0) -> 11 | R18: =IFERROR(__xludf.DUMMYFUNCTION("""COMPUTED_VALUE"""),5.0) -> 5 | S18: =IFERROR(__xludf.DUMMYFUNCTION("""COMPUTED_VALUE"""),0.0) -> 0 | T18: =IFERROR(__xludf.DUMMYFUNCTION("""COMPUTED_VALUE"""),0.0) -> 0 | U18: =IFERROR(__xludf.DUMMYFUNCTION("""COMPUTED_VALUE"""),0.0) -> 0 | V18: =IFERROR(__xludf.DUMMYFUNCTION("""COMPUTED_VALUE"""),0.0) -> 0 | W18: =IFERROR(__xludf.DUMMYFUNCTION("""COMPUTED_VALUE"""),0.0) -> 0 | X18: =IFERROR(__xludf.DUMMYFUNCTION("""COMPUTED_VALUE"""),0.0) -> 0 | Y18: =IFERROR(__xludf.DUMMYFUNCTION("""COMPUTED_VALUE"""),11.0) -> 11 | Z18: =IFERROR(__xludf.DUMMYFUNCTION("""COMPUTED_VALUE"""),"Discontinued") -> Discontinued | AB18: =IFERROR(__xludf.DUMMYFUNCTION("""COMPUTED_VALUE"""),1.0) -> 1
A19: =IFERROR(__xludf.DUMMYFUNCTION("""COMPUTED_VALUE"""),"BAJAJ") -> BAJAJ | B19: =IFERROR(__xludf.DUMMYFUNCTION("""COMPUTED_VALUE"""),"Bajaj_3") -> Bajaj_3 | C19: =IFERROR(__xludf.DUMMYFUNCTION("""COMPUTED_VALUE"""),2.0) -> 2 | E19: =IFERROR(__xludf.DUMMYFUNCTION("""COMPUTED_VALUE"""),"Canon G (Grey)") -> Canon G (Grey) | F19: =SUMIF(A:A,E19,C:C) -> 90 | G19: =XLOOKUP(E19,K:K,Q:Q) -> 168 | H19: =G19-F19 -> 78 | K19: =IFERROR(__xludf.DUMMYFUNCTION("""COMPUTED_VALUE"""),"T700W") -> T700W | M19: =IFERROR(__xludf.DUMMYFUNCTION("""COMPUTED_VALUE"""),"Printer") -> Printer | N19: =IFERROR(__xludf.DUMMYFUNCTION("""COMPUTED_VALUE"""),"AG") -> AG | O19: =IFERROR(__xludf.DUMMYFUNCTION("""COMPUTED_VALUE"""),-42.0) -> -42 | P19: =IFERROR(__xludf.DUMMYFUNCTION("""COMPUTED_VALUE"""),0.0) -> 0 | Q19: =IFERROR(__xludf.DUMMYFUNCTION("""COMPUTED_VALUE"""),42.0) -> 42 | R19: =IFERROR(__xludf.DUMMYFUNCTION("""COMPUTED_VALUE"""),5.0) -> 5 | S19: =IFERROR(__xludf.DUMMYFUNCTION("""COMPUTED_VALUE"""),0.0) -> 0 | T19: =IFERROR(__xludf.DUMMYFUNCTION("""COMPUTED_VALUE"""),0.0) -> 0 | U19: =IFERROR(__xludf.DUMMYFUNCTION("""COMPUTED_VALUE"""),0.0) -> 0 | V19: =IFERROR(__xludf.DUMMYFUNCTION("""COMPUTED_VALUE"""),0.0) -> 0 | W19: =IFERROR(__xludf.DUMMYFUNCTION("""COMPUTED_VALUE"""),0.0) -> 0 | X19: =IFERROR(__xludf.DUMMYFUNCTION("""COMPUTED_VALUE"""),0.0) -> 0 | Y19: =IFERROR(__xludf.DUMMYFUNCTION("""COMPUTED_VALUE"""),42.0) -> 42 | Z19: =IFERROR(__xludf.DUMMYFUNCTION("""COMPUTED_VALUE"""),"Discontinued") -> Discontinued | AB19: =IFERROR(__xludf.DUMMYFUNCTION("""COMPUTED_VALUE"""),1.0) -> 1
A20: =IFERROR(__xludf.DUMMYFUNCTION("""COMPUTED_VALUE"""),"BAJAJ") -> BAJAJ | B20: =IFERROR(__xludf.DUMMYFUNCTION("""COMPUTED_VALUE"""),"Bajaj_4") -> Bajaj_4 | C20: =IFERROR(__xludf.DUMMYFUNCTION("""COMPUTED_VALUE"""),10.0) -> 10 | E20: =IFERROR(__xludf.DUMMYFUNCTION("""COMPUTED_VALUE"""),"Canon G (Black)") -> Canon G (Black) | F20: =SUMIF(A:A,E20,C:C) -> 214 | G20: =XLOOKUP(E20,K:K,Q:Q) -> 251 | H20: =G20-F20 -> 37 | K20: =IFERROR(__xludf.DUMMYFUNCTION("""COMPUTED_VALUE"""),"HP 4729") -> HP 4729 | M20: =IFERROR(__xludf.DUMMYFUNCTION("""COMPUTED_VALUE"""),"Printer") -> Printer | N20: =IFERROR(__xludf.DUMMYFUNCTION("""COMPUTED_VALUE"""),"AG") -> AG | O20: =IFERROR(__xludf.DUMMYFUNCTION("""COMPUTED_VALUE"""),-9.0) -> -9 | P20: =IFERROR(__xludf.DUMMYFUNCTION("""COMPUTED_VALUE"""),0.0) -> 0 | Q20: =IFERROR(__xludf.DUMMYFUNCTION("""COMPUTED_VALUE"""),9.0) -> 9 | R20: =IFERROR(__xludf.DUMMYFUNCTION("""COMPUTED_VALUE"""),5.0) -> 5 | S20: =IFERROR(__xludf.DUMMYFUNCTION("""COMPUTED_VALUE"""),0.0) -> 0 | T20: =IFERROR(__xludf.DUMMYFUNCTION("""COMPUTED_VALUE"""),0.0) -> 0 | U20: =IFERROR(__xludf.DUMMYFUNCTION("""COMPUTED_VALUE"""),0.0) -> 0 | V20: =IFERROR(__xludf.DUMMYFUNCTION("""COMPUTED_VALUE"""),0.0) -> 0 | W20: =IFERROR(__xludf.DUMMYFUNCTION("""COMPUTED_VALUE"""),0.0) -> 0 | X20: =IFERROR(__xludf.DUMMYFUNCTION("""COMPUTED_VALUE"""),0.0) -> 0 | Y20: =IFERROR(__xludf.DUMMYFUNCTION("""COMPUTED_VALUE"""),9.0) -> 9 | Z20: =IFERROR(__xludf.DUMMYFUNCTION("""COMPUTED_VALUE"""),"Discontinued") -> Discontinued | AB20: =IFERROR(__xludf.DUMMYFUNCTION("""COMPUTED_VALUE"""),1.0) -> 1
A21: =IFERROR(__xludf.DUMMYFUNCTION("""COMPUTED_VALUE"""),"BAJAJ") -> BAJAJ | B21: =IFERROR(__xludf.DUMMYFUNCTION("""COMPUTED_VALUE"""),"Bajaj_4") -> Bajaj_4 | C21: =IFERROR(__xludf.DUMMYFUNCTION("""COMPUTED_VALUE"""),10.0) -> 10 | E21: =IFERROR(__xludf.DUMMYFUNCTION("""COMPUTED_VALUE"""),"HP 136NW (Grey)") -> HP 136NW (Grey) | F21: =SUMIF(A:A,E21,C:C) -> 56 | G21: =XLOOKUP(E21,K:K,Q:Q) -> 42 | H21: =G21-F21 -> -14 | K21: =IFERROR(__xludf.DUMMYFUNCTION("""COMPUTED_VALUE"""),"E4270") -> E4270 | M21: =IFERROR(__xludf.DUMMYFUNCTION("""COMPUTED_VALUE"""),"Printer") -> Printer | N21: =IFERROR(__xludf.DUMMYFUNCTION("""COMPUTED_VALUE"""),"AG") -> AG | O21: =IFERROR(__xludf.DUMMYFUNCTION("""COMPUTED_VALUE"""),0.0) -> 0 | P21: =IFERROR(__xludf.DUMMYFUNCTION("""COMPUTED_VALUE"""),0.0) -> 0 | Q21: =IFERROR(__xludf.DUMMYFUNCTION("""COMPUTED_VALUE"""),0.0) -> 0 | R21: =IFERROR(__xludf.DUMMYFUNCTION("""COMPUTED_VALUE"""),5.0) -> 5 | S21: =IFERROR(__xludf.DUMMYFUNCTION("""COMPUTED_VALUE"""),0.0) -> 0 | T21: =IFERROR(__xludf.DUMMYFUNCTION("""COMPUTED_VALUE"""),0.0) -> 0 | U21: =IFERROR(__xludf.DUMMYFUNCTION("""COMPUTED_VALUE"""),0.0) -> 0 | V21: =IFERROR(__xludf.DUMMYFUNCTION("""COMPUTED_VALUE"""),0.0) -> 0 | W21: =IFERROR(__xludf.DUMMYFUNCTION("""COMPUTED_VALUE"""),0.0) -> 0 | X21: =IFERROR(__xludf.DUMMYFUNCTION("""COMPUTED_VALUE"""),0.0) -> 0 | Y21: =IFERROR(__xludf.DUMMYFUNCTION("""COMPUTED_VALUE"""),0.0) -> 0 | Z21: =IFERROR(__xludf.DUMMYFUNCTION("""COMPUTED_VALUE"""),"Discontinued") -> Discontinued | AB21: =IFERROR(__xludf.DUMMYFUNCTION("""COMPUTED_VALUE"""),1.0) -> 1
A22: =IFERROR(__xludf.DUMMYFUNCTION("""COMPUTED_VALUE"""),"BAJAJ") -> BAJAJ | B22: =IFERROR(__xludf.DUMMYFUNCTION("""COMPUTED_VALUE"""),"Bajaj_4") -> Bajaj_4 | C22: =IFERROR(__xludf.DUMMYFUNCTION("""COMPUTED_VALUE"""),2.0) -> 2 | E22: =IFERROR(__xludf.DUMMYFUNCTION("""COMPUTED_VALUE"""),"HP 136NW (Black)") -> HP 136NW (Black) | F22: =SUMIF(A:A,E22,C:C) -> 20 | G22: =XLOOKUP(E22,K:K,Q:Q) -> 133 | H22: =G22-F22 -> 113 | K22: =IFERROR(__xludf.DUMMYFUNCTION("""COMPUTED_VALUE"""),"G2010") -> G2010 | M22: =IFERROR(__xludf.DUMMYFUNCTION("""COMPUTED_VALUE"""),"Printer") -> Printer | N22: =IFERROR(__xludf.DUMMYFUNCTION("""COMPUTED_VALUE"""),"AG") -> AG | O22: =IFERROR(__xludf.DUMMYFUNCTION("""COMPUTED_VALUE"""),2.0) -> 2 | P22: =IFERROR(__xludf.DUMMYFUNCTION("""COMPUTED_VALUE"""),3.0) -> 3 | Q22: =IFERROR(__xludf.DUMMYFUNCTION("""COMPUTED_VALUE"""),1.0) -> 1 | R22: =IFERROR(__xludf.DUMMYFUNCTION("""COMPUTED_VALUE"""),5.0) -> 5 | S22: =IFERROR(__xludf.DUMMYFUNCTION("""COMPUTED_VALUE"""),4.0) -> 4 | T22: =IFERROR(__xludf.DUMMYFUNCTION("""COMPUTED_VALUE"""),6.0) -> 6 | U22: =IFERROR(__xludf.DUMMYFUNCTION("""COMPUTED_VALUE"""),2.0) -> 2 | V22: =IFERROR(__xludf.DUMMYFUNCTION("""COMPUTED_VALUE"""),2.0) -> 2 | W22: =IFERROR(__xludf.DUMMYFUNCTION("""COMPUTED_VALUE"""),1.0) -> 1 | X22: =IFERROR(__xludf.DUMMYFUNCTION("""COMPUTED_VALUE"""),0.0) -> 0 | Y22: =IFERROR(__xludf.DUMMYFUNCTION("""COMPUTED_VALUE"""),26.0) -> 26 | Z22: =IFERROR(__xludf.DUMMYFUNCTION("""COMPUTED_VALUE"""),"Discontinued") -> Discontinued | AB22: =IFERROR(__xludf.DUMMYFUNCTION("""COMPUTED_VALUE"""),1.0) -> 1
A23: =IFERROR(__xludf.DUMMYFUNCTION("""COMPUTED_VALUE"""),"BAJAJ") -> BAJAJ | B23: =IFERROR(__xludf.DUMMYFUNCTION("""COMPUTED_VALUE"""),"Bajaj_4") -> Bajaj_4 | C23: =IFERROR(__xludf.DUMMYFUNCTION("""COMPUTED_VALUE"""),18.0) -> 18 | E23: =IFERROR(__xludf.DUMMYFUNCTION("""COMPUTED_VALUE"""),"HP 4826 (Grey)") -> HP 4826 (Grey) | F23: =SUMIF(A:A,E23,C:C) -> 60 | G23: =XLOOKUP(E23,K:K,Q:Q) -> 208 | H23: =G23-F23 -> 148 | K23: =IFERROR(__xludf.DUMMYFUNCTION("""COMPUTED_VALUE"""),"G4010") -> G4010 | M23: =IFERROR(__xludf.DUMMYFUNCTION("""COMPUTED_VALUE"""),"Printer") -> Printer | N23: =IFERROR(__xludf.DUMMYFUNCTION("""COMPUTED_VALUE"""),"AG") -> AG | O23: =IFERROR(__xludf.DUMMYFUNCTION("""COMPUTED_VALUE"""),-21.0) -> -21 | P23: =IFERROR(__xludf.DUMMYFUNCTION("""COMPUTED_VALUE"""),0.0) -> 0 | Q23: =IFERROR(__xludf.DUMMYFUNCTION("""COMPUTED_VALUE"""),21.0) -> 21 | R23: =IFERROR(__xludf.DUMMYFUNCTION("""COMPUTED_VALUE"""),5.0) -> 5 | S23: =IFERROR(__xludf.DUMMYFUNCTION("""COMPUTED_VALUE"""),0.0) -> 0 | T23: =IFERROR(__xludf.DUMMYFUNCTION("""COMPUTED_VALUE"""),0.0) -> 0 | U23: =IFERROR(__xludf.DUMMYFUNCTION("""COMPUTED_VALUE"""),0.0) -> 0 | V23: =IFERROR(__xludf.DUMMYFUNCTION("""COMPUTED_VALUE"""),0.0) -> 0 | W23: =IFERROR(__xludf.DUMMYFUNCTION("""COMPUTED_VALUE"""),0.0) -> 0 | X23: =IFERROR(__xludf.DUMMYFUNCTION("""COMPUTED_VALUE"""),0.0) -> 0 | Y23: =IFERROR(__xludf.DUMMYFUNCTION("""COMPUTED_VALUE"""),21.0) -> 21 | Z23: =IFERROR(__xludf.DUMMYFUNCTION("""COMPUTED_VALUE"""),"Discontinued") -> Discontinued | AB23: =IFERROR(__xludf.DUMMYFUNCTION("""COMPUTED_VALUE"""),1.0) -> 1
A24: =IFERROR(__xludf.DUMMYFUNCTION("""COMPUTED_VALUE"""),"BAJAJ") -> BAJAJ | B24: =IFERROR(__xludf.DUMMYFUNCTION("""COMPUTED_VALUE"""),"Bajaj_4") -> Bajaj_4 | C24: =IFERROR(__xludf.DUMMYFUNCTION("""COMPUTED_VALUE"""),2.0) -> 2 | E24: =IFERROR(__xludf.DUMMYFUNCTION("""COMPUTED_VALUE"""),"G4770 (Black)") -> G4770 (Black) | F24: =SUMIF(A:A,E24,C:C) -> 32 | G24: =XLOOKUP(E24,K:K,Q:Q) -> 121 | H24: =G24-F24 -> 89 | K24: =IFERROR(__xludf.DUMMYFUNCTION("""COMPUTED_VALUE"""),"HP 5820") -> HP 5820 | M24: =IFERROR(__xludf.DUMMYFUNCTION("""COMPUTED_VALUE"""),"Printer") -> Printer | N24: =IFERROR(__xludf.DUMMYFUNCTION("""COMPUTED_VALUE"""),"AG") -> AG | O24: =IFERROR(__xludf.DUMMYFUNCTION("""COMPUTED_VALUE"""),-26.0) -> -26 | P24: =IFERROR(__xludf.DUMMYFUNCTION("""COMPUTED_VALUE"""),0.0) -> 0 | Q24: =IFERROR(__xludf.DUMMYFUNCTION("""COMPUTED_VALUE"""),26.0) -> 26 | R24: =IFERROR(__xludf.DUMMYFUNCTION("""COMPUTED_VALUE"""),5.0) -> 5 | S24: =IFERROR(__xludf.DUMMYFUNCTION("""COMPUTED_VALUE"""),0.0) -> 0 | T24: =IFERROR(__xludf.DUMMYFUNCTION("""COMPUTED_VALUE"""),0.0) -> 0 | U24: =IFERROR(__xludf.DUMMYFUNCTION("""COMPUTED_VALUE"""),0.0) -> 0 | V24: =IFERROR(__xludf.DUMMYFUNCTION("""COMPUTED_VALUE"""),0.0) -> 0 | W24: =IFERROR(__xludf.DUMMYFUNCTION("""COMPUTED_VALUE"""),0.0) -> 0 | X24: =IFERROR(__xludf.DUMMYFUNCTION("""COMPUTED_VALUE"""),0.0) -> 0 | Y24: =IFERROR(__xludf.DUMMYFUNCTION("""COMPUTED_VALUE"""),26.0) -> 26 | Z24: =IFERROR(__xludf.DUMMYFUNCTION("""COMPUTED_VALUE"""),"Discontinued") -> Discontinued | AB24: =IFERROR(__xludf.DUMMYFUNCTION("""COMPUTED_VALUE"""),1.0) -> 1
A25: =IFERROR(__xludf.DUMMYFUNCTION("""COMPUTED_VALUE"""),"BAJAJ") -> BAJAJ | B25: =IFERROR(__xludf.DUMMYFUNCTION("""COMPUTED_VALUE"""),"Bajaj_4") -> Bajaj_4 | C25: =IFERROR(__xludf.DUMMYFUNCTION("""COMPUTED_VALUE"""),6.0) -> 6 | E25: =IFERROR(__xludf.DUMMYFUNCTION("""COMPUTED_VALUE"""),"G4770 (Grey)") -> G4770 (Grey) | F25: =SUMIF(A:A,E25,C:C) -> 20 | G25: =XLOOKUP(E25,K:K,Q:Q) -> 162 | H25: =G25-F25 -> 142 | K25: =IFERROR(__xludf.DUMMYFUNCTION("""COMPUTED_VALUE"""),"L130") -> L130 | M25: =IFERROR(__xludf.DUMMYFUNCTION("""COMPUTED_VALUE"""),"Printer") -> Printer | N25: =IFERROR(__xludf.DUMMYFUNCTION("""COMPUTED_VALUE"""),"AG") -> AG | O25: =IFERROR(__xludf.DUMMYFUNCTION("""COMPUTED_VALUE"""),-1.0) -> -1 | P25: =IFERROR(__xludf.DUMMYFUNCTION("""COMPUTED_VALUE"""),0.0) -> 0 | Q25: =IFERROR(__xludf.DUMMYFUNCTION("""COMPUTED_VALUE"""),1.0) -> 1 | R25: =IFERROR(__xludf.DUMMYFUNCTION("""COMPUTED_VALUE"""),5.0) -> 5 | S25: =IFERROR(__xludf.DUMMYFUNCTION("""COMPUTED_VALUE"""),0.0) -> 0 | T25: =IFERROR(__xludf.DUMMYFUNCTION("""COMPUTED_VALUE"""),0.0) -> 0 | U25: =IFERROR(__xludf.DUMMYFUNCTION("""COMPUTED_VALUE"""),0.0) -> 0 | V25: =IFERROR(__xludf.DUMMYFUNCTION("""COMPUTED_VALUE"""),0.0) -> 0 | W25: =IFERROR(__xludf.DUMMYFUNCTION("""COMPUTED_VALUE"""),0.0) -> 0 | X25: =IFERROR(__xludf.DUMMYFUNCTION("""COMPUTED_VALUE"""),0.0) -> 0 | Y25: =IFERROR(__xludf.DUMMYFUNCTION("""COMPUTED_VALUE"""),1.0) -> 1 | Z25: =IFERROR(__xludf.DUMMYFUNCTION("""COMPUTED_VALUE"""),"Discontinued") -> Discontinued | AB25: =IFERROR(__xludf.DUMMYFUNCTION("""COMPUTED_VALUE"""),1.0) -> 1
A26: =IFERROR(__xludf.DUMMYFUNCTION("""COMPUTED_VALUE"""),"Bajaj (Grey)") -> Bajaj (Grey) | B26: =IFERROR(__xludf.DUMMYFUNCTION("""COMPUTED_VALUE"""),"CRM-WG-NW-Ultra-Grey") -> CRM-WG-NW-Ultra-Grey | C26: =IFERROR(__xludf.DUMMYFUNCTION("""COMPUTED_VALUE"""),2.0) -> 2 | E26: =IFERROR(__xludf.DUMMYFUNCTION("""COMPUTED_VALUE"""),"HP 750 (Grey)") -> HP 750 (Grey) | F26: =SUMIF(A:A,E26,C:C) -> 24 | G26: =XLOOKUP(E26,K:K,Q:Q) -> 86 | H26: =G26-F26 -> 62 | K26: =IFERROR(__xludf.DUMMYFUNCTION("""COMPUTED_VALUE"""),"L2541DW") -> L2541DW | M26: =IFERROR(__xludf.DUMMYFUNCTION("""COMPUTED_VALUE"""),"Printer") -> Printer | N26: =IFERROR(__xludf.DUMMYFUNCTION("""COMPUTED_VALUE"""),"AG") -> AG | O26: =IFERROR(__xludf.DUMMYFUNCTION("""COMPUTED_VALUE"""),-2.0) -> -2 | P26: =IFERROR(__xludf.DUMMYFUNCTION("""COMPUTED_VALUE"""),0.0) -> 0 | Q26: =IFERROR(__xludf.DUMMYFUNCTION("""COMPUTED_VALUE"""),2.0) -> 2 | R26: =IFERROR(__xludf.DUMMYFUNCTION("""COMPUTED_VALUE"""),5.0) -> 5 | S26: =IFERROR(__xludf.DUMMYFUNCTION("""COMPUTED_VALUE"""),0.0) -> 0 | T26: =IFERROR(__xludf.DUMMYFUNCTION("""COMPUTED_VALUE"""),0.0) -> 0 | U26: =IFERROR(__xludf.DUMMYFUNCTION("""COMPUTED_VALUE"""),0.0) -> 0 | V26: =IFERROR(__xludf.DUMMYFUNCTION("""COMPUTED_VALUE"""),0.0) -> 0 | W26: =IFERROR(__xludf.DUMMYFUNCTION("""COMPUTED_VALUE"""),0.0) -> 0 | X26: =IFERROR(__xludf.DUMMYFUNCTION("""COMPUTED_VALUE"""),0.0) -> 0 | Y26: =IFERROR(__xludf.DUMMYFUNCTION("""COMPUTED_VALUE"""),2.0) -> 2 | Z26: =IFERROR(__xludf.DUMMYFUNCTION("""COMPUTED_VALUE"""),"Discontinued") -> Discontinued | AB26: =IFERROR(__xludf.DUMMYFUNCTION("""COMPUTED_VALUE"""),1.0) -> 1
A27: =IFERROR(__xludf.DUMMYFUNCTION("""COMPUTED_VALUE"""),"Bajaj (Grey)") -> Bajaj (Grey) | B27: =IFERROR(__xludf.DUMMYFUNCTION("""COMPUTED_VALUE"""),"CRM-WG-NW-Ultra-Grey") -> CRM-WG-NW-Ultra-Grey | C27: =IFERROR(__xludf.DUMMYFUNCTION("""COMPUTED_VALUE"""),62.0) -> 62 | E27: =IFERROR(__xludf.DUMMYFUNCTION("""COMPUTED_VALUE"""),"HP 750 (Black)") -> HP 750 (Black) | F27: =SUMIF(A:A,E27,C:C) -> 12 | G27: =XLOOKUP(E27,K:K,Q:Q) -> 16 | H27: =G27-F27 -> 4 | K27: =IFERROR(__xludf.DUMMYFUNCTION("""COMPUTED_VALUE"""),"L5190") -> L5190 | M27: =IFERROR(__xludf.DUMMYFUNCTION("""COMPUTED_VALUE"""),"Printer") -> Printer | N27: =IFERROR(__xludf.DUMMYFUNCTION("""COMPUTED_VALUE"""),"AG") -> AG | O27: =IFERROR(__xludf.DUMMYFUNCTION("""COMPUTED_VALUE"""),-66.0) -> -66 | P27: =IFERROR(__xludf.DUMMYFUNCTION("""COMPUTED_VALUE"""),0.0) -> 0 | Q27: =IFERROR(__xludf.DUMMYFUNCTION("""COMPUTED_VALUE"""),66.0) -> 66 | R27: =IFERROR(__xludf.DUMMYFUNCTION("""COMPUTED_VALUE"""),5.0) -> 5 | S27: =IFERROR(__xludf.DUMMYFUNCTION("""COMPUTED_VALUE"""),0.0) -> 0 | T27: =IFERROR(__xludf.DUMMYFUNCTION("""COMPUTED_VALUE"""),0.0) -> 0 | U27: =IFERROR(__xludf.DUMMYFUNCTION("""COMPUTED_VALUE"""),0.0) -> 0 | V27: =IFERROR(__xludf.DUMMYFUNCTION("""COMPUTED_VALUE"""),0.0) -> 0 | W27: =IFERROR(__xludf.DUMMYFUNCTION("""COMPUTED_VALUE"""),0.0) -> 0 | X27: =IFERROR(__xludf.DUMMYFUNCTION("""COMPUTED_VALUE"""),0.0) -> 0 | Y27: =IFERROR(__xludf.DUMMYFUNCTION("""COMPUTED_VALUE"""),66.0) -> 66 | Z27: =IFERROR(__xludf.DUMMYFUNCTION("""COMPUTED_VALUE"""),"Discontinued") -> Discontinued | AB27: =IFERROR(__xludf.DUMMYFUNCTION("""COMPUTED_VALUE"""),1.0) -> 1
A28: =IFERROR(__xludf.DUMMYFUNCTION("""COMPUTED_VALUE"""),"Bajaj (Grey)") -> Bajaj (Grey) | B28: =IFERROR(__xludf.DUMMYFUNCTION("""COMPUTED_VALUE"""),"CRM-WG-NW-Ultra-Grey") -> CRM-WG-NW-Ultra-Grey | C28: =IFERROR(__xludf.DUMMYFUNCTION("""COMPUTED_VALUE"""),82.0) -> 82 | E28: =IFERROR(__xludf.DUMMYFUNCTION("""COMPUTED_VALUE"""),"HP 670 (Grey)") -> HP 670 (Grey) | F28: =SUMIF(A:A,E28,C:C) -> 94 | G28: =XLOOKUP(E28,K:K,Q:Q) -> 226 | H28: =G28-F28 -> 132 | K28: =IFERROR(__xludf.DUMMYFUNCTION("""COMPUTED_VALUE"""),"L805") -> L805 | M28: =IFERROR(__xludf.DUMMYFUNCTION("""COMPUTED_VALUE"""),"Printer") -> Printer | N28: =IFERROR(__xludf.DUMMYFUNCTION("""COMPUTED_VALUE"""),"AG") -> AG | O28: =IFERROR(__xludf.DUMMYFUNCTION("""COMPUTED_VALUE"""),-15.0) -> -15 | P28: =IFERROR(__xludf.DUMMYFUNCTION("""COMPUTED_VALUE"""),0.0) -> 0 | Q28: =IFERROR(__xludf.DUMMYFUNCTION("""COMPUTED_VALUE"""),15.0) -> 15 | R28: =IFERROR(__xludf.DUMMYFUNCTION("""COMPUTED_VALUE"""),5.0) -> 5 | S28: =IFERROR(__xludf.DUMMYFUNCTION("""COMPUTED_VALUE"""),0.0) -> 0 | T28: =IFERROR(__xludf.DUMMYFUNCTION("""COMPUTED_VALUE"""),0.0) -> 0 | U28: =IFERROR(__xludf.DUMMYFUNCTION("""COMPUTED_VALUE"""),0.0) -> 0 | V28: =IFERROR(__xludf.DUMMYFUNCTION("""COMPUTED_VALUE"""),0.0) -> 0 | W28: =IFERROR(__xludf.DUMMYFUNCTION("""COMPUTED_VALUE"""),0.0) -> 0 | X28: =IFERROR(__xludf.DUMMYFUNCTION("""COMPUTED_VALUE"""),0.0) -> 0 | Y28: =IFERROR(__xludf.DUMMYFUNCTION("""COMPUTED_VALUE"""),15.0) -> 15 | Z28: =IFERROR(__xludf.DUMMYFUNCTION("""COMPUTED_VALUE"""),"Discontinued") -> Discontinued | AB28: =IFERROR(__xludf.DUMMYFUNCTION("""COMPUTED_VALUE"""),1.0) -> 1
A29: =IFERROR(__xludf.DUMMYFUNCTION("""COMPUTED_VALUE"""),"Bajaj (Grey)") -> Bajaj (Grey) | B29: =IFERROR(__xludf.DUMMYFUNCTION("""COMPUTED_VALUE"""),"CRM-WG-NW-Ultra-Grey") -> CRM-WG-NW-Ultra-Grey | C29: =IFERROR(__xludf.DUMMYFUNCTION("""COMPUTED_VALUE"""),54.0) -> 54 | E29: =IFERROR(__xludf.DUMMYFUNCTION("""COMPUTED_VALUE"""),"HP 670 (Black)") -> HP 670 (Black) | F29: =SUMIF(A:A,E29,C:C) -> 156 | G29: =XLOOKUP(E29,K:K,Q:Q) -> 196 | H29: =G29-F29 -> 40 | K29: =IFERROR(__xludf.DUMMYFUNCTION("""COMPUTED_VALUE"""),"M1005") -> M1005 | M29: =IFERROR(__xludf.DUMMYFUNCTION("""COMPUTED_VALUE"""),"Printer") -> Printer | N29: =IFERROR(__xludf.DUMMYFUNCTION("""COMPUTED_VALUE"""),"AG") -> AG | O29: =IFERROR(__xludf.DUMMYFUNCTION("""COMPUTED_VALUE"""),-171.0) -> -171 | P29: =IFERROR(__xludf.DUMMYFUNCTION("""COMPUTED_VALUE"""),4.0) -> 4 | Q29: =IFERROR(__xludf.DUMMYFUNCTION("""COMPUTED_VALUE"""),175.0) -> 175 | R29: =IFERROR(__xludf.DUMMYFUNCTION("""COMPUTED_VALUE"""),5.0) -> 5 | S29: =IFERROR(__xludf.DUMMYFUNCTION("""COMPUTED_VALUE"""),0.0) -> 0 | T29: =IFERROR(__xludf.DUMMYFUNCTION("""COMPUTED_VALUE"""),4.0) -> 4 | U29: =IFERROR(__xludf.DUMMYFUNCTION("""COMPUTED_VALUE"""),0.0) -> 0 | V29: =IFERROR(__xludf.DUMMYFUNCTION("""COMPUTED_VALUE"""),12.0) -> 12 | W29: =IFERROR(__xludf.DUMMYFUNCTION("""COMPUTED_VALUE"""),1.0) -> 1 | X29: =IFERROR(__xludf.DUMMYFUNCTION("""COMPUTED_VALUE"""),1.0) -> 1 | Y29: =IFERROR(__xludf.DUMMYFUNCTION("""COMPUTED_VALUE"""),175.0) -> 175 | Z29: =IFERROR(__xludf.DUMMYFUNCTION("""COMPUTED_VALUE"""),"Discontinued") -> Discontinued | AB29: =IFERROR(__xludf.DUMMYFUNCTION("""COMPUTED_VALUE"""),1.0) -> 1
A30: =IFERROR(__xludf.DUMMYFUNCTION("""COMPUTED_VALUE"""),"Bajaj (Grey)") -> Bajaj (Grey) | B30: =IFERROR(__xludf.DUMMYFUNCTION("""COMPUTED_VALUE"""),"CRM-WG-NW-Ultra-Grey") -> CRM-WG-NW-Ultra-Grey | C30: =IFERROR(__xludf.DUMMYFUNCTION("""COMPUTED_VALUE"""),78.0) -> 78 | E30: =IFERROR(__xludf.DUMMYFUNCTION("""COMPUTED_VALUE"""),"HP 580 (Grey)") -> HP 580 (Grey) | F30: =SUMIF(A:A,E30,C:C) -> 306 | G30: =XLOOKUP(E30,K:K,Q:Q) -> 937 | H30: =G30-F30 -> 631 | K30: =IFERROR(__xludf.DUMMYFUNCTION("""COMPUTED_VALUE"""),"M1136") -> M1136 | M30: =IFERROR(__xludf.DUMMYFUNCTION("""COMPUTED_VALUE"""),"Printer") -> Printer | N30: =IFERROR(__xludf.DUMMYFUNCTION("""COMPUTED_VALUE"""),"AG") -> AG | O30: =IFERROR(__xludf.DUMMYFUNCTION("""COMPUTED_VALUE"""),0.0) -> 0 | P30: =IFERROR(__xludf.DUMMYFUNCTION("""COMPUTED_VALUE"""),0.0) -> 0 | Q30: =IFERROR(__xludf.DUMMYFUNCTION("""COMPUTED_VALUE"""),0.0) -> 0 | R30: =IFERROR(__xludf.DUMMYFUNCTION("""COMPUTED_VALUE"""),5.0) -> 5 | S30: =IFERROR(__xludf.DUMMYFUNCTION("""COMPUTED_VALUE"""),0.0) -> 0 | T30: =IFERROR(__xludf.DUMMYFUNCTION("""COMPUTED_VALUE"""),0.0) -> 0 | U30: =IFERROR(__xludf.DUMMYFUNCTION("""COMPUTED_VALUE"""),0.0) -> 0 | V30: =IFERROR(__xludf.DUMMYFUNCTION("""COMPUTED_VALUE"""),0.0) -> 0 | W30: =IFERROR(__xludf.DUMMYFUNCTION("""COMPUTED_VALUE"""),0.0) -> 0 | X30: =IFERROR(__xludf.DUMMYFUNCTION("""COMPUTED_VALUE"""),0.0) -> 0 | Y30: =IFERROR(__xludf.DUMMYFUNCTION("""COMPUTED_VALUE"""),0.0) -> 0 | Z30: =IFERROR(__xludf.DUMMYFUNCTION("""COMPUTED_VALUE"""),"Discontinued") -> Discontinued | AB30: =IFERROR(__xludf.DUMMYFUNCTION("""COMPUTED_VALUE"""),1.0) -> 1
A31: =IFERROR(__xludf.DUMMYFUNCTION("""COMPUTED_VALUE"""),"Bajaj (Grey)") -> Bajaj (Grey) | B31: =IFERROR(__xludf.DUMMYFUNCTION("""COMPUTED_VALUE"""),"CRM-WG-NW-Ultra-Grey") -> CRM-WG-NW-Ultra-Grey | C31: =IFERROR(__xludf.DUMMYFUNCTION("""COMPUTED_VALUE"""),22.0) -> 22 | E31: =IFERROR(__xludf.DUMMYFUNCTION("""COMPUTED_VALUE"""),"L2321") -> L2321 | F31: =SUMIF(A:A,E31,C:C) -> 2 | G31: =XLOOKUP(E31,K:K,Q:Q) -> 6 | H31: =G31-F31 -> 4 | K31: =IFERROR(__xludf.DUMMYFUNCTION("""COMPUTED_VALUE"""),"P1108") -> P1108 | M31: =IFERROR(__xludf.DUMMYFUNCTION("""COMPUTED_VALUE"""),"Printer") -> Printer | N31: =IFERROR(__xludf.DUMMYFUNCTION("""COMPUTED_VALUE"""),"AG") -> AG | O31: =IFERROR(__xludf.DUMMYFUNCTION("""COMPUTED_VALUE"""),-10.0) -> -10 | P31: =IFERROR(__xludf.DUMMYFUNCTION("""COMPUTED_VALUE"""),0.0) -> 0 | Q31: =IFERROR(__xludf.DUMMYFUNCTION("""COMPUTED_VALUE"""),10.0) -> 10 | R31: =IFERROR(__xludf.DUMMYFUNCTION("""COMPUTED_VALUE"""),5.0) -> 5 | S31: =IFERROR(__xludf.DUMMYFUNCTION("""COMPUTED_VALUE"""),0.0) -> 0 | T31: =IFERROR(__xludf.DUMMYFUNCTION("""COMPUTED_VALUE"""),0.0) -> 0 | U31: =IFERROR(__xludf.DUMMYFUNCTION("""COMPUTED_VALUE"""),0.0) -> 0 | V31: =IFERROR(__xludf.DUMMYFUNCTION("""COMPUTED_VALUE"""),0.0) -> 0 | W31: =IFERROR(__xludf.DUMMYFUNCTION("""COMPUTED_VALUE"""),0.0) -> 0 | X31: =IFERROR(__xludf.DUMMYFUNCTION("""COMPUTED_VALUE"""),0.0) -> 0 | Y31: =IFERROR(__xludf.DUMMYFUNCTION("""COMPUTED_VALUE"""),10.0) -> 10 | Z31: =IFERROR(__xludf.DUMMYFUNCTION("""COMPUTED_VALUE"""),"Discontinued") -> Discontinued | AB31: =IFERROR(__xludf.DUMMYFUNCTION("""COMPUTED_VALUE"""),1.0) -> 1
A32: =IFERROR(__xludf.DUMMYFUNCTION("""COMPUTED_VALUE"""),"Bajaj (Black)") -> Bajaj (Black) | B32: =IFERROR(__xludf.DUMMYFUNCTION("""COMPUTED_VALUE"""),"CRM-WG-NW-Ultra-Black") -> CRM-WG-NW-Ultra-Black | C32: =IFERROR(__xludf.DUMMYFUNCTION("""COMPUTED_VALUE"""),2.0) -> 2 | E32: =IFERROR(__xludf.DUMMYFUNCTION("""COMPUTED_VALUE"""),"HP 580 (Black)") -> HP 580 (Black) | F32: =SUMIF(A:A,E32,C:C) -> 128 | G32: =XLOOKUP(E32,K:K,Q:Q) -> 322 | H32: =G32-F32 -> 194 | K32: =IFERROR(__xludf.DUMMYFUNCTION("""COMPUTED_VALUE"""),"T500W") -> T500W | M32: =IFERROR(__xludf.DUMMYFUNCTION("""COMPUTED_VALUE"""),"Printer") -> Printer | N32: =IFERROR(__xludf.DUMMYFUNCTION("""COMPUTED_VALUE"""),"AG") -> AG | O32: =IFERROR(__xludf.DUMMYFUNCTION("""COMPUTED_VALUE"""),3.0) -> 3 | P32: =IFERROR(__xludf.DUMMYFUNCTION("""COMPUTED_VALUE"""),5.0) -> 5 | Q32: =IFERROR(__xludf.DUMMYFUNCTION("""COMPUTED_VALUE"""),2.0) -> 2 | R32: =IFERROR(__xludf.DUMMYFUNCTION("""COMPUTED_VALUE"""),5.0) -> 5 | S32: =IFERROR(__xludf.DUMMYFUNCTION("""COMPUTED_VALUE"""),3.0) -> 3 | T32: =IFERROR(__xludf.DUMMYFUNCTION("""COMPUTED_VALUE"""),6.0) -> 6 | U32: =IFERROR(__xludf.DUMMYFUNCTION("""COMPUTED_VALUE"""),3.0) -> 3 | V32: =IFERROR(__xludf.DUMMYFUNCTION("""COMPUTED_VALUE"""),6.0) -> 6 | W32: =IFERROR(__xludf.DUMMYFUNCTION("""COMPUTED_VALUE"""),7.0) -> 7 | X32: =IFERROR(__xludf.DUMMYFUNCTION("""COMPUTED_VALUE"""),3.0) -> 3 | Y32: =IFERROR(__xludf.DUMMYFUNCTION("""COMPUTED_VALUE"""),12.0) -> 12 | Z32: =IFERROR(__xludf.DUMMYFUNCTION("""COMPUTED_VALUE"""),"Discontinued") -> Discontinued | AB32: =IFERROR(__xludf.DUMMYFUNCTION("""COMPUTED_VALUE"""),1.0) -> 1
A33: =IFERROR(__xludf.DUMMYFUNCTION("""COMPUTED_VALUE"""),"Bajaj (Black)") -> Bajaj (Black) | B33: =IFERROR(__xludf.DUMMYFUNCTION("""COMPUTED_VALUE"""),"CRM-WG-NW-Ultra-Black") -> CRM-WG-NW-Ultra-Black | C33: =IFERROR(__xludf.DUMMYFUNCTION("""COMPUTED_VALUE"""),10.0) -> 10 | E33: =IFERROR(__xludf.DUMMYFUNCTION("""COMPUTED_VALUE"""),"HP 4826 (Black)") -> HP 4826 (Black) | F33: =SUMIF(A:A,E33,C:C) -> 20 | G33: =XLOOKUP(E33,K:K,Q:Q) -> 146 | H33: =G33-F33 -> 126 | K33: =IFERROR(__xludf.DUMMYFUNCTION("""COMPUTED_VALUE"""),"T820DW") -> T820DW | M33: =IFERROR(__xludf.DUMMYFUNCTION("""COMPUTED_VALUE"""),"Printer") -> Printer | N33: =IFERROR(__xludf.DUMMYFUNCTION("""COMPUTED_VALUE"""),"AG") -> AG | O33: =IFERROR(__xludf.DUMMYFUNCTION("""COMPUTED_VALUE"""),-1.0) -> -1 | P33: =IFERROR(__xludf.DUMMYFUNCTION("""COMPUTED_VALUE"""),0.0) -> 0 | Q33: =IFERROR(__xludf.DUMMYFUNCTION("""COMPUTED_VALUE"""),1.0) -> 1 | R33: =IFERROR(__xludf.DUMMYFUNCTION("""COMPUTED_VALUE"""),5.0) -> 5 | S33: =IFERROR(__xludf.DUMMYFUNCTION("""COMPUTED_VALUE"""),0.0) -> 0 | T33: =IFERROR(__xludf.DUMMYFUNCTION("""COMPUTED_VALUE"""),0.0) -> 0 | U33: =IFERROR(__xludf.DUMMYFUNCTION("""COMPUTED_VALUE"""),0.0) -> 0 | V33: =IFERROR(__xludf.DUMMYFUNCTION("""COMPUTED_VALUE"""),0.0) -> 0 | W33: =IFERROR(__xludf.DUMMYFUNCTION("""COMPUTED_VALUE"""),0.0) -> 0 | X33: =IFERROR(__xludf.DUMMYFUNCTION("""COMPUTED_VALUE"""),0.0) -> 0 | Y33: =IFERROR(__xludf.DUMMYFUNCTION("""COMPUTED_VALUE"""),1.0) -> 1 | Z33: =IFERROR(__xludf.DUMMYFUNCTION("""COMPUTED_VALUE"""),"Discontinued") -> Discontinued | AB33: =IFERROR(__xludf.DUMMYFUNCTION("""COMPUTED_VALUE"""),1.0) -> 1
A34: =IFERROR(__xludf.DUMMYFUNCTION("""COMPUTED_VALUE"""),"Bajaj (Black)") -> Bajaj (Black) | B34: =IFERROR(__xludf.DUMMYFUNCTION("""COMPUTED_VALUE"""),"CRM-WG-NW-Ultra-Black") -> CRM-WG-NW-Ultra-Black | C34: =IFERROR(__xludf.DUMMYFUNCTION("""COMPUTED_VALUE"""),12.0) -> 12 | E34: =IFERROR(__xludf.DUMMYFUNCTION("""COMPUTED_VALUE"""),"Canon TS207 - Grey") -> Canon TS207 - Grey | F34: =SUMIF(A:A,E34,C:C) -> 2 | G34: =XLOOKUP(E34,K:K,Q:Q) -> 60 | H34: =G34-F34 -> 58 | K34: =IFERROR(__xludf.DUMMYFUNCTION("""COMPUTED_VALUE"""),"2900B") -> 2900B | M34: =IFERROR(__xludf.DUMMYFUNCTION("""COMPUTED_VALUE"""),"Printer") -> Printer | N34: =IFERROR(__xludf.DUMMYFUNCTION("""COMPUTED_VALUE"""),"AG") -> AG | O34: =IFERROR(__xludf.DUMMYFUNCTION("""COMPUTED_VALUE"""),-6.0) -> -6 | P34: =IFERROR(__xludf.DUMMYFUNCTION("""COMPUTED_VALUE"""),0.0) -> 0 | Q34: =IFERROR(__xludf.DUMMYFUNCTION("""COMPUTED_VALUE"""),6.0) -> 6 | R34: =IFERROR(__xludf.DUMMYFUNCTION("""COMPUTED_VALUE"""),5.0) -> 5 | S34: =IFERROR(__xludf.DUMMYFUNCTION("""COMPUTED_VALUE"""),0.0) -> 0 | T34: =IFERROR(__xludf.DUMMYFUNCTION("""COMPUTED_VALUE"""),0.0) -> 0 | U34: =IFERROR(__xludf.DUMMYFUNCTION("""COMPUTED_VALUE"""),0.0) -> 0 | V34: =IFERROR(__xludf.DUMMYFUNCTION("""COMPUTED_VALUE"""),0.0) -> 0 | W34: =IFERROR(__xludf.DUMMYFUNCTION("""COMPUTED_VALUE"""),0.0) -> 0 | X34: =IFERROR(__xludf.DUMMYFUNCTION("""COMPUTED_VALUE"""),0.0) -> 0 | Y34: =IFERROR(__xludf.DUMMYFUNCTION("""COMPUTED_VALUE"""),22.0) -> 22 | Z34: =IFERROR(__xludf.DUMMYFUNCTION("""COMPUTED_VALUE"""),"Discontinued") -> Discontinued | AB34: =IFERROR(__xludf.DUMMYFUNCTION("""COMPUTED_VALUE"""),1.0) -> 1
A35: =IFERROR(__xludf.DUMMYFUNCTION("""COMPUTED_VALUE"""),"Bajaj (Black)") -> Bajaj (Black) | B35: =IFERROR(__xludf.DUMMYFUNCTION("""COMPUTED_VALUE"""),"CRM-WG-NW-Ultra-Black") -> CRM-WG-NW-Ultra-Black | C35: =IFERROR(__xludf.DUMMYFUNCTION("""COMPUTED_VALUE"""),4.0) -> 4 | E35: =IFERROR(__xludf.DUMMYFUNCTION("""COMPUTED_VALUE"""),"HP 2606sdw - Grey") -> HP 2606sdw - Grey | F35: =SUMIF(A:A,E35,C:C) -> 26 | G35: =XLOOKUP(E35,K:K,Q:Q) -> 269 | H35: =G35-F35 -> 243 | K35: =IFERROR(__xludf.DUMMYFUNCTION("""COMPUTED_VALUE"""),"HP 5075") -> HP 5075 | M35: =IFERROR(__xludf.DUMMYFUNCTION("""COMPUTED_VALUE"""),"Printer") -> Printer | N35: =IFERROR(__xludf.DUMMYFUNCTION("""COMPUTED_VALUE"""),"AG") -> AG | O35: =IFERROR(__xludf.DUMMYFUNCTION("""COMPUTED_VALUE"""),-127.0) -> -127 | P35: =IFERROR(__xludf.DUMMYFUNCTION("""COMPUTED_VALUE"""),0.0) -> 0 | Q35: =IFERROR(__xludf.DUMMYFUNCTION("""COMPUTED_VALUE"""),127.0) -> 127 | R35: =IFERROR(__xludf.DUMMYFUNCTION("""COMPUTED_VALUE"""),5.0) -> 5 | S35: =IFERROR(__xludf.DUMMYFUNCTION("""COMPUTED_VALUE"""),0.0) -> 0 | T35: =IFERROR(__xludf.DUMMYFUNCTION("""COMPUTED_VALUE"""),0.0) -> 0 | U35: =IFERROR(__xludf.DUMMYFUNCTION("""COMPUTED_VALUE"""),0.0) -> 0 | V35: =IFERROR(__xludf.DUMMYFUNCTION("""COMPUTED_VALUE"""),0.0) -> 0 | W35: =IFERROR(__xludf.DUMMYFUNCTION("""COMPUTED_VALUE"""),0.0) -> 0 | X35: =IFERROR(__xludf.DUMMYFUNCTION("""COMPUTED_VALUE"""),0.0) -> 0 | Y35: =IFERROR(__xludf.DUMMYFUNCTION("""COMPUTED_VALUE"""),127.0) -> 127 | Z35: =IFERROR(__xludf.DUMMYFUNCTION("""COMPUTED_VALUE"""),"Discontinued") -> Discontinued | AB35: =IFERROR(__xludf.DUMMYFUNCTION("""COMPUTED_VALUE"""),1.0) -> 1
A36: =IFERROR(__xludf.DUMMYFUNCTION("""COMPUTED_VALUE"""),"Bajaj (Black)") -> Bajaj (Black) | B36: =IFERROR(__xludf.DUMMYFUNCTION("""COMPUTED_VALUE"""),"CRM-WG-NW-Ultra-Black") -> CRM-WG-NW-Ultra-Black | C36: =IFERROR(__xludf.DUMMYFUNCTION("""COMPUTED_VALUE"""),30.0) -> 30 | E36: =IFERROR(__xludf.DUMMYFUNCTION("""COMPUTED_VALUE"""),"Cubes-Grey (5Q)") -> Cubes-Grey (5Q) | F36: =SUMIF(A:A,E36,C:C) -> 92 | G36: =XLOOKUP(E36,K:K,Q:Q) -> 235 | H36: =G36-F36 -> 143 | K36: =IFERROR(__xludf.DUMMYFUNCTION("""COMPUTED_VALUE"""),"HP 515") -> HP 515 | M36: =IFERROR(__xludf.DUMMYFUNCTION("""COMPUTED_VALUE"""),"Printer") -> Printer | N36: =IFERROR(__xludf.DUMMYFUNCTION("""COMPUTED_VALUE"""),"AG") -> AG | O36: =IFERROR(__xludf.DUMMYFUNCTION("""COMPUTED_VALUE"""),-21.0) -> -21 | P36: =IFERROR(__xludf.DUMMYFUNCTION("""COMPUTED_VALUE"""),0.0) -> 0 | Q36: =IFERROR(__xludf.DUMMYFUNCTION("""COMPUTED_VALUE"""),21.0) -> 21 | R36: =IFERROR(__xludf.DUMMYFUNCTION("""COMPUTED_VALUE"""),5.0) -> 5 | S36: =IFERROR(__xludf.DUMMYFUNCTION("""COMPUTED_VALUE"""),0.0) -> 0 | T36: =IFERROR(__xludf.DUMMYFUNCTION("""COMPUTED_VALUE"""),0.0) -> 0 | U36: =IFERROR(__xludf.DUMMYFUNCTION("""COMPUTED_VALUE"""),0.0) -> 0 | V36: =IFERROR(__xludf.DUMMYFUNCTION("""COMPUTED_VALUE"""),0.0) -> 0 | W36: =IFERROR(__xludf.DUMMYFUNCTION("""COMPUTED_VALUE"""),0.0) -> 0 | X36: =IFERROR(__xludf.DUMMYFUNCTION("""COMPUTED_VALUE"""),0.0) -> 0 | Y36: =IFERROR(__xludf.DUMMYFUNCTION("""COMPUTED_VALUE"""),21.0) -> 21 | Z36: =IFERROR(__xludf.DUMMYFUNCTION("""COMPUTED_VALUE"""),"Discontinued") -> Discontinued | AB36: =IFERROR(__xludf.DUMMYFUNCTION("""COMPUTED_VALUE"""),1.0) -> 1
A37: =IFERROR(__xludf.DUMMYFUNCTION("""COMPUTED_VALUE"""),"Bajaj (Black)") -> Bajaj (Black) | B37: =IFERROR(__xludf.DUMMYFUNCTION("""COMPUTED_VALUE"""),"CRM-WG-NW-Ultra-Black") -> CRM-WG-NW-Ultra-Black | C37: =IFERROR(__xludf.DUMMYFUNCTION("""COMPUTED_VALUE"""),4.0) -> 4 | E37: =IFERROR(__xludf.DUMMYFUNCTION("""COMPUTED_VALUE"""),"Cubes-Grey (12Q)") -> Cubes-Grey (12Q) | F37: =SUMIF(A:A,E37,C:C) -> 46 | G37: =XLOOKUP(E37,K:K,Q:Q) -> 15 | H37: =G37-F37 -> -31 | K37: =IFERROR(__xludf.DUMMYFUNCTION("""COMPUTED_VALUE"""),"HP 530") -> HP 530 | M37: =IFERROR(__xludf.DUMMYFUNCTION("""COMPUTED_VALUE"""),"Printer") -> Printer | N37: =IFERROR(__xludf.DUMMYFUNCTION("""COMPUTED_VALUE"""),"AG") -> AG | O37: =IFERROR(__xludf.DUMMYFUNCTION("""COMPUTED_VALUE"""),-1.0) -> -1 | P37: =IFERROR(__xludf.DUMMYFUNCTION("""COMPUTED_VALUE"""),1.0) -> 1 | Q37: =IFERROR(__xludf.DUMMYFUNCTION("""COMPUTED_VALUE"""),2.0) -> 2 | R37: =IFERROR(__xludf.DUMMYFUNCTION("""COMPUTED_VALUE"""),5.0) -> 5 | S37: =IFERROR(__xludf.DUMMYFUNCTION("""COMPUTED_VALUE"""),0.0) -> 0 | T37: =IFERROR(__xludf.DUMMYFUNCTION("""COMPUTED_VALUE"""),1.0) -> 1 | U37: =IFERROR(__xludf.DUMMYFUNCTION("""COMPUTED_VALUE"""),1.0) -> 1 | V37: =IFERROR(__xludf.DUMMYFUNCTION("""COMPUTED_VALUE"""),1.0) -> 1 | W37: =IFERROR(__xludf.DUMMYFUNCTION("""COMPUTED_VALUE"""),0.0) -> 0 | X37: =IFERROR(__xludf.DUMMYFUNCTION("""COMPUTED_VALUE"""),0.0) -> 0 | Y37: =IFERROR(__xludf.DUMMYFUNCTION("""COMPUTED_VALUE"""),2.0) -> 2 | Z37: =IFERROR(__xludf.DUMMYFUNCTION("""COMPUTED_VALUE"""),"Discontinued") -> Discontinued | AB37: =IFERROR(__xludf.DUMMYFUNCTION("""COMPUTED_VALUE"""),1.0) -> 1
A38: =IFERROR(__xludf.DUMMYFUNCTION("""COMPUTED_VALUE"""),"Bajaj (Black)") -> Bajaj (Black) | B38: =IFERROR(__xludf.DUMMYFUNCTION("""COMPUTED_VALUE"""),"CRM-WG-NW-Ultra-Black") -> CRM-WG-NW-Ultra-Black | C38: =IFERROR(__xludf.DUMMYFUNCTION("""COMPUTED_VALUE"""),8.0) -> 8 | E38: =IFERROR(__xludf.DUMMYFUNCTION("""COMPUTED_VALUE"""),"CP-1-Black") -> CP-1-Black | F38: =SUMIF(A:A,E38,C:C) -> 12 | G38: =XLOOKUP(E38,K:K,Q:Q) -> 96 | H38: =G38-F38 -> 84 | K38: =IFERROR(__xludf.DUMMYFUNCTION("""COMPUTED_VALUE"""),"HP 6075") -> HP 6075 | M38: =IFERROR(__xludf.DUMMYFUNCTION("""COMPUTED_VALUE"""),"Printer") -> Printer | N38: =IFERROR(__xludf.DUMMYFUNCTION("""COMPUTED_VALUE"""),"AG") -> AG | O38: =IFERROR(__xludf.DUMMYFUNCTION("""COMPUTED_VALUE"""),-1.0) -> -1 | P38: =IFERROR(__xludf.DUMMYFUNCTION("""COMPUTED_VALUE"""),0.0) -> 0 | Q38: =IFERROR(__xludf.DUMMYFUNCTION("""COMPUTED_VALUE"""),1.0) -> 1 | R38: =IFERROR(__xludf.DUMMYFUNCTION("""COMPUTED_VALUE"""),5.0) -> 5 | S38: =IFERROR(__xludf.DUMMYFUNCTION("""COMPUTED_VALUE"""),0.0) -> 0 | T38: =IFERROR(__xludf.DUMMYFUNCTION("""COMPUTED_VALUE"""),0.0) -> 0 | U38: =IFERROR(__xludf.DUMMYFUNCTION("""COMPUTED_VALUE"""),0.0) -> 0 | V38: =IFERROR(__xludf.DUMMYFUNCTION("""COMPUTED_VALUE"""),0.0) -> 0 | W38: =IFERROR(__xludf.DUMMYFUNCTION("""COMPUTED_VALUE"""),0.0) -> 0 | X38: =IFERROR(__xludf.DUMMYFUNCTION("""COMPUTED_VALUE"""),0.0) -> 0 | Y38: =IFERROR(__xludf.DUMMYFUNCTION("""COMPUTED_VALUE"""),1.0) -> 1 | Z38: =IFERROR(__xludf.DUMMYFUNCTION("""COMPUTED_VALUE"""),"Discontinued") -> Discontinued | AB38: =IFERROR(__xludf.DUMMYFUNCTION("""COMPUTED_VALUE"""),1.0) -> 1
A39: =IFERROR(__xludf.DUMMYFUNCTION("""COMPUTED_VALUE"""),"Bajaj (Black)") -> Bajaj (Black) | B39: =IFERROR(__xludf.DUMMYFUNCTION("""COMPUTED_VALUE"""),"CRM-WG-NW-Ultra-Black") -> CRM-WG-NW-Ultra-Black | C39: =IFERROR(__xludf.DUMMYFUNCTION("""COMPUTED_VALUE"""),8.0) -> 8 | E39: =IFERROR(__xludf.DUMMYFUNCTION("""COMPUTED_VALUE"""),"CP-2-Grey (2Q)") -> CP-2-Grey (2Q) | F39: =SUMIF(A:A,E39,C:C) -> 12 | G39: =XLOOKUP(E39,K:K,Q:Q) -> 80 | H39: =G39-F39 -> 68 | K39: =IFERROR(__xludf.DUMMYFUNCTION("""COMPUTED_VALUE"""),"HP 3835") -> HP 3835 | M39: =IFERROR(__xludf.DUMMYFUNCTION("""COMPUTED_VALUE"""),"Printer") -> Printer | N39: =IFERROR(__xludf.DUMMYFUNCTION("""COMPUTED_VALUE"""),"AG") -> AG | O39: =IFERROR(__xludf.DUMMYFUNCTION("""COMPUTED_VALUE"""),-101.0) -> -101 | P39: =IFERROR(__xludf.DUMMYFUNCTION("""COMPUTED_VALUE"""),0.0) -> 0 | Q39: =IFERROR(__xludf.DUMMYFUNCTION("""COMPUTED_VALUE"""),101.0) -> 101 | R39: =IFERROR(__xludf.DUMMYFUNCTION("""COMPUTED_VALUE"""),5.0) -> 5 | S39: =IFERROR(__xludf.DUMMYFUNCTION("""COMPUTED_VALUE"""),0.0) -> 0 | T39: =IFERROR(__xludf.DUMMYFUNCTION("""COMPUTED_VALUE"""),0.0) -> 0 | U39: =IFERROR(__xludf.DUMMYFUNCTION("""COMPUTED_VALUE"""),0.0) -> 0 | V39: =IFERROR(__xludf.DUMMYFUNCTION("""COMPUTED_VALUE"""),0.0) -> 0 | W39: =IFERROR(__xludf.DUMMYFUNCTION("""COMPUTED_VALUE"""),0.0) -> 0 | X39: =IFERROR(__xludf.DUMMYFUNCTION("""COMPUTED_VALUE"""),0.0) -> 0 | Y39: =IFERROR(__xludf.DUMMYFUNCTION("""COMPUTED_VALUE"""),101.0) -> 101 | Z39: =IFERROR(__xludf.DUMMYFUNCTION("""COMPUTED_VALUE"""),"Discontinued") -> Discontinued | AB39: =IFERROR(__xludf.DUMMYFUNCTION("""COMPUTED_VALUE"""),1.0) -> 1
A40: =IFERROR(__xludf.DUMMYFUNCTION("""COMPUTED_VALUE"""),"Bajaj (Grey)") -> Bajaj (Grey) | B40: =IFERROR(__xludf.DUMMYFUNCTION("""COMPUTED_VALUE"""),"CRM-WG-NW-Butterfly-Grey") -> CRM-WG-NW-Butterfly-Grey | C40: =IFERROR(__xludf.DUMMYFUNCTION("""COMPUTED_VALUE"""),10.0) -> 10 | E40: =IFERROR(__xludf.DUMMYFUNCTION("""COMPUTED_VALUE"""),"SC-Black (4Q)") -> SC-Black (4Q) | F40: =SUMIF(A:A,E40,C:C) -> 6 | G40: =XLOOKUP(E40,K:K,Q:Q) -> 29.5 | H40: =G40-F40 -> 23.5 | K40: =IFERROR(__xludf.DUMMYFUNCTION("""COMPUTED_VALUE"""),"HP 4675") -> HP 4675 | M40: =IFERROR(__xludf.DUMMYFUNCTION("""COMPUTED_VALUE"""),"Printer") -> Printer | N40: =IFERROR(__xludf.DUMMYFUNCTION("""COMPUTED_VALUE"""),"AG") -> AG | O40: =IFERROR(__xludf.DUMMYFUNCTION("""COMPUTED_VALUE"""),-4.0) -> -4 | P40: =IFERROR(__xludf.DUMMYFUNCTION("""COMPUTED_VALUE"""),0.0) -> 0 | Q40: =IFERROR(__xludf.DUMMYFUNCTION("""COMPUTED_VALUE"""),4.0) -> 4 | R40: =IFERROR(__xludf.DUMMYFUNCTION("""COMPUTED_VALUE"""),5.0) -> 5 | S40: =IFERROR(__xludf.DUMMYFUNCTION("""COMPUTED_VALUE"""),0.0) -> 0 | T40: =IFERROR(__xludf.DUMMYFUNCTION("""COMPUTED_VALUE"""),0.0) -> 0 | U40: =IFERROR(__xludf.DUMMYFUNCTION("""COMPUTED_VALUE"""),0.0) -> 0 | V40: =IFERROR(__xludf.DUMMYFUNCTION("""COMPUTED_VALUE"""),0.0) -> 0 | W40: =IFERROR(__xludf.DUMMYFUNCTION("""COMPUTED_VALUE"""),0.0) -> 0 | X40: =IFERROR(__xludf.DUMMYFUNCTION("""COMPUTED_VALUE"""),0.0) -> 0 | Y40: =IFERROR(__xludf.DUMMYFUNCTION("""COMPUTED_VALUE"""),4.0) -> 4 | Z40: =IFERROR(__xludf.DUMMYFUNCTION("""COMPUTED_VALUE"""),"Discontinued") -> Discontinued | AB40: =IFERROR(__xludf.DUMMYFUNCTION("""COMPUTED_VALUE"""),1.0) -> 1
A41: =IFERROR(__xludf.DUMMYFUNCTION("""COMPUTED_VALUE"""),"Bajaj (Grey)") -> Bajaj (Grey) | B41: =IFERROR(__xludf.DUMMYFUNCTION("""COMPUTED_VALUE"""),"CRM-WG-NW-Butterfly-Grey") -> CRM-WG-NW-Butterfly-Grey | C41: =IFERROR(__xludf.DUMMYFUNCTION("""COMPUTED_VALUE"""),18.0) -> 18 | E41: =IFERROR(__xludf.DUMMYFUNCTION("""COMPUTED_VALUE"""),"SC-TS (4Q)") -> SC-TS (4Q) | F41: =SUMIF(A:A,E41,C:C) -> 22 | G41: =XLOOKUP(E41,K:K,Q:Q) -> 44 | H41: =G41-F41 -> 22 | K41: =IFERROR(__xludf.DUMMYFUNCTION("""COMPUTED_VALUE"""),"E510-CANON") -> E510-CANON | M41: =IFERROR(__xludf.DUMMYFUNCTION("""COMPUTED_VALUE"""),"Printer") -> Printer | N41: =IFERROR(__xludf.DUMMYFUNCTION("""COMPUTED_VALUE"""),"AG") -> AG | O41: =IFERROR(__xludf.DUMMYFUNCTION("""COMPUTED_VALUE"""),-4.0) -> -4 | P41: =IFERROR(__xludf.DUMMYFUNCTION("""COMPUTED_VALUE"""),0.0) -> 0 | Q41: =IFERROR(__xludf.DUMMYFUNCTION("""COMPUTED_VALUE"""),4.0) -> 4 | R41: =IFERROR(__xludf.DUMMYFUNCTION("""COMPUTED_VALUE"""),5.0) -> 5 | S41: =IFERROR(__xludf.DUMMYFUNCTION("""COMPUTED_VALUE"""),0.0) -> 0 | T41: =IFERROR(__xludf.DUMMYFUNCTION("""COMPUTED_VALUE"""),0.0) -> 0 | U41: =IFERROR(__xludf.DUMMYFUNCTION("""COMPUTED_VALUE"""),0.0) -> 0 | V41: =IFERROR(__xludf.DUMMYFUNCTION("""COMPUTED_VALUE"""),0.0) -> 0 | W41: =IFERROR(__xludf.DUMMYFUNCTION("""COMPUTED_VALUE"""),0.0) -> 0 | X41: =IFERROR(__xludf.DUMMYFUNCTION("""COMPUTED_VALUE"""),0.0) -> 0 | Y41: =IFERROR(__xludf.DUMMYFUNCTION("""COMPUTED_VALUE"""),4.0) -> 4 | Z41: =IFERROR(__xludf.DUMMYFUNCTION("""COMPUTED_VALUE"""),"Discontinued") -> Discontinued | AB41: =IFERROR(__xludf.DUMMYFUNCTION("""COMPUTED_VALUE"""),1.0) -> 1
A42: =IFERROR(__xludf.DUMMYFUNCTION("""COMPUTED_VALUE"""),"Bajaj (Grey)") -> Bajaj (Grey) | B42: =IFERROR(__xludf.DUMMYFUNCTION("""COMPUTED_VALUE"""),"CRM-WG-NW-Butterfly-Grey") -> CRM-WG-NW-Butterfly-Grey | C42: =IFERROR(__xludf.DUMMYFUNCTION("""COMPUTED_VALUE"""),10.0) -> 10 | E42: =IFERROR(__xludf.DUMMYFUNCTION("""COMPUTED_VALUE"""),"Cubes-Grey (3Q)") -> Cubes-Grey (3Q) | F42: =SUMIF(A:A,E42,C:C) -> 208 | G42: =XLOOKUP(E42,K:K,Q:Q) -> 72 | H42: =G42-F42 -> -136 | K42: =IFERROR(__xludf.DUMMYFUNCTION("""COMPUTED_VALUE"""),"L565") -> L565 | M42: =IFERROR(__xludf.DUMMYFUNCTION("""COMPUTED_VALUE"""),"Printer") -> Printer | N42: =IFERROR(__xludf.DUMMYFUNCTION("""COMPUTED_VALUE"""),"AG") -> AG | O42: =IFERROR(__xludf.DUMMYFUNCTION("""COMPUTED_VALUE"""),-4.0) -> -4 | P42: =IFERROR(__xludf.DUMMYFUNCTION("""COMPUTED_VALUE"""),0.0) -> 0 | Q42: =IFERROR(__xludf.DUMMYFUNCTION("""COMPUTED_VALUE"""),4.0) -> 4 | R42: =IFERROR(__xludf.DUMMYFUNCTION("""COMPUTED_VALUE"""),5.0) -> 5 | S42: =IFERROR(__xludf.DUMMYFUNCTION("""COMPUTED_VALUE"""),0.0) -> 0 | T42: =IFERROR(__xludf.DUMMYFUNCTION("""COMPUTED_VALUE"""),0.0) -> 0 | U42: =IFERROR(__xludf.DUMMYFUNCTION("""COMPUTED_VALUE"""),0.0) -> 0 | V42: =IFERROR(__xludf.DUMMYFUNCTION("""COMPUTED_VALUE"""),0.0) -> 0 | W42: =IFERROR(__xludf.DUMMYFUNCTION("""COMPUTED_VALUE"""),0.0) -> 0 | X42: =IFERROR(__xludf.DUMMYFUNCTION("""COMPUTED_VALUE"""),0.0) -> 0 | Y42: =IFERROR(__xludf.DUMMYFUNCTION("""COMPUTED_VALUE"""),4.0) -> 4 | Z42: =IFERROR(__xludf.DUMMYFUNCTION("""COMPUTED_VALUE"""),"Discontinued") -> Discontinued | AB42: =IFERROR(__xludf.DUMMYFUNCTION("""COMPUTED_VALUE"""),1.0) -> 1
A43: =IFERROR(__xludf.DUMMYFUNCTION("""COMPUTED_VALUE"""),"Bajaj (Grey)") -> Bajaj (Grey) | B43: =IFERROR(__xludf.DUMMYFUNCTION("""COMPUTED_VALUE"""),"CRM-WG-NW-Butterfly-Grey") -> CRM-WG-NW-Butterfly-Grey | C43: =IFERROR(__xludf.DUMMYFUNCTION("""COMPUTED_VALUE"""),30.0) -> 30 | F43: =SUMIF(A:A,E43,C:C) -> 0 | G43: =XLOOKUP(E43,K:K,Q:Q) -> #N/A | H43: =G43-F43 -> #N/A | K43: =IFERROR(__xludf.DUMMYFUNCTION("""COMPUTED_VALUE"""),"HP 3545") -> HP 3545 | M43: =IFERROR(__xludf.DUMMYFUNCTION("""COMPUTED_VALUE"""),"Printer") -> Printer | N43: =IFERROR(__xludf.DUMMYFUNCTION("""COMPUTED_VALUE"""),"AG") -> AG | O43: =IFERROR(__xludf.DUMMYFUNCTION("""COMPUTED_VALUE"""),-1.0) -> -1 | P43: =IFERROR(__xludf.DUMMYFUNCTION("""COMPUTED_VALUE"""),0.0) -> 0 | Q43: =IFERROR(__xludf.DUMMYFUNCTION("""COMPUTED_VALUE"""),1.0) -> 1 | R43: =IFERROR(__xludf.DUMMYFUNCTION("""COMPUTED_VALUE"""),5.0) -> 5 | S43: =IFERROR(__xludf.DUMMYFUNCTION("""COMPUTED_VALUE"""),0.0) -> 0 | T43: =IFERROR(__xludf.DUMMYFUNCTION("""COMPUTED_VALUE"""),0.0) -> 0 | U43: =IFERROR(__xludf.DUMMYFUNCTION("""COMPUTED_VALUE"""),0.0) -> 0 | V43: =IFERROR(__xludf.DUMMYFUNCTION("""COMPUTED_VALUE"""),0.0) -> 0 | W43: =IFERROR(__xludf.DUMMYFUNCTION("""COMPUTED_VALUE"""),0.0) -> 0 | X43: =IFERROR(__xludf.DUMMYFUNCTION("""COMPUTED_VALUE"""),0.0) -> 0 | Y43: =IFERROR(__xludf.DUMMYFUNCTION("""COMPUTED_VALUE"""),1.0) -> 1 | Z43: =IFERROR(__xludf.DUMMYFUNCTION("""COMPUTED_VALUE"""),"Discontinued") -> Discontinued | AB43: =IFERROR(__xludf.DUMMYFUNCTION("""COMPUTED_VALUE"""),1.0) -> 1
A44: =IFERROR(__xludf.DUMMYFUNCTION("""COMPUTED_VALUE"""),"Bajaj (Grey)") -> Bajaj (Grey) | B44: =IFERROR(__xludf.DUMMYFUNCTION("""COMPUTED_VALUE"""),"CRM-WG-NW-Butterfly-Grey") -> CRM-WG-NW-Butterfly-Grey | C44: =IFERROR(__xludf.DUMMYFUNCTION("""COMPUTED_VALUE"""),4.0) -> 4 | F44: =SUMIF(A:A,E44,C:C) -> 0 | G44: =XLOOKUP(E44,K:K,Q:Q) -> #N/A | H44: =G44-F44 -> #N/A
A45: =IFERROR(__xludf.DUMMYFUNCTION("""COMPUTED_VALUE"""),"Bajaj (Grey)") -> Bajaj (Grey) | B45: =IFERROR(__xludf.DUMMYFUNCTION("""COMPUTED_VALUE"""),"CRM-WG-NW-Butterfly-Grey") -> CRM-WG-NW-Butterfly-Grey | C45: =IFERROR(__xludf.DUMMYFUNCTION("""COMPUTED_VALUE"""),8.0) -> 8 | F45: =SUMIF(A:A,E45,C:C) -> 0 | G45: =XLOOKUP(E45,K:K,Q:Q) -> #N/A | H45: =G45-F45 -> #N/A
A46: =IFERROR(__xludf.DUMMYFUNCTION("""COMPUTED_VALUE"""),"Bajaj (Black)") -> Bajaj (Black) | B46: =IFERROR(__xludf.DUMMYFUNCTION("""COMPUTED_VALUE"""),"CRM-WG-NW-Butterfly-Black") -> CRM-WG-NW-Butterfly-Black | C46: =IFERROR(__xludf.DUMMYFUNCTION("""COMPUTED_VALUE"""),2.0) -> 2 | F46: =SUMIF(A:A,E46,C:C) -> 0 | G46: =XLOOKUP(E46,K:K,Q:Q) -> #N/A | H46: =G46-F46 -> #N/A | K46: =IFERROR(__xludf.DUMMYFUNCTION("""COMPUTED_VALUE"""),"HP 580 (Black)") -> HP 580 (Black) | M46: =IFERROR(__xludf.DUMMYFUNCTION("""COMPUTED_VALUE"""),"Printer NW") -> Printer NW | N46: =IFERROR(__xludf.DUMMYFUNCTION("""COMPUTED_VALUE"""),"AG") -> AG | O46: =IFERROR(__xludf.DUMMYFUNCTION("""COMPUTED_VALUE"""),-112.0) -> -112 | P46: =IFERROR(__xludf.DUMMYFUNCTION("""COMPUTED_VALUE"""),210.0) -> 210 | Q46: =IFERROR(__xludf.DUMMYFUNCTION("""COMPUTED_VALUE"""),322.0) -> 322 | R46: =IFERROR(__xludf.DUMMYFUNCTION("""COMPUTED_VALUE"""),5.0) -> 5 | S46: =IFERROR(__xludf.DUMMYFUNCTION("""COMPUTED_VALUE"""),65.0) -> 65 | T46: =IFERROR(__xludf.DUMMYFUNCTION("""COMPUTED_VALUE"""),85.0) -> 85 | U46: =IFERROR(__xludf.DUMMYFUNCTION("""COMPUTED_VALUE"""),115.0) -> 115 | V46: =IFERROR(__xludf.DUMMYFUNCTION("""COMPUTED_VALUE"""),126.0) -> 126 | W46: =IFERROR(__xludf.DUMMYFUNCTION("""COMPUTED_VALUE"""),308.0) -> 308 | X46: =IFERROR(__xludf.DUMMYFUNCTION("""COMPUTED_VALUE"""),48.0) -> 48 | Y46: =IFERROR(__xludf.DUMMYFUNCTION("""COMPUTED_VALUE"""),167.0) -> 167 | AB46: =IFERROR(__xludf.DUMMYFUNCTION("""COMPUTED_VALUE"""),1.5) -> 1.5
A47: =IFERROR(__xludf.DUMMYFUNCTION("""COMPUTED_VALUE"""),"Bajaj (Black)") -> Bajaj (Black) | B47: =IFERROR(__xludf.DUMMYFUNCTION("""COMPUTED_VALUE"""),"CRM-WG-NW-Butterfly-Black") -> CRM-WG-NW-Butterfly-Black | C47: =IFERROR(__xludf.DUMMYFUNCTION("""COMPUTED_VALUE"""),4.0) -> 4 | F47: =SUMIF(A:A,E47,C:C) -> 0 | G47: =XLOOKUP(E47,K:K,Q:Q) -> #N/A | H47: =G47-F47 -> #N/A | K47: =IFERROR(__xludf.DUMMYFUNCTION("""COMPUTED_VALUE"""),"HP 136NW (Black)") -> HP 136NW (Black) | M47: =IFERROR(__xludf.DUMMYFUNCTION("""COMPUTED_VALUE"""),"Printer NW") -> Printer NW | N47: =IFERROR(__xludf.DUMMYFUNCTION("""COMPUTED_VALUE"""),"AG") -> AG | O47: =IFERROR(__xludf.DUMMYFUNCTION("""COMPUTED_VALUE"""),-108.0) -> -108 | P47: =IFERROR(__xludf.DUMMYFUNCTION("""COMPUTED_VALUE"""),25.0) -> 25 | Q47: =IFERROR(__xludf.DUMMYFUNCTION("""COMPUTED_VALUE"""),133.0) -> 133 | R47: =IFERROR(__xludf.DUMMYFUNCTION("""COMPUTED_VALUE"""),5.0) -> 5 | S47: =IFERROR(__xludf.DUMMYFUNCTION("""COMPUTED_VALUE"""),6.0) -> 6 | T47: =IFERROR(__xludf.DUMMYFUNCTION("""COMPUTED_VALUE"""),1.0) -> 1 | U47: =IFERROR(__xludf.DUMMYFUNCTION("""COMPUTED_VALUE"""),20.0) -> 20 | V47: =IFERROR(__xludf.DUMMYFUNCTION("""COMPUTED_VALUE"""),18.0) -> 18 | W47: =IFERROR(__xludf.DUMMYFUNCTION("""COMPUTED_VALUE"""),37.0) -> 37 | X47: =IFERROR(__xludf.DUMMYFUNCTION("""COMPUTED_VALUE"""),12.0) -> 12 | Y47: =IFERROR(__xludf.DUMMYFUNCTION("""COMPUTED_VALUE"""),25.0) -> 25 | AB47: =IFERROR(__xludf.DUMMYFUNCTION("""COMPUTED_VALUE"""),1.5) -> 1.5
A48: =IFERROR(__xludf.DUMMYFUNCTION("""COMPUTED_VALUE"""),"Bajaj (Black)") -> Bajaj (Black) | B48: =IFERROR(__xludf.DUMMYFUNCTION("""COMPUTED_VALUE"""),"CRM-WG-NW-Butterfly-Black") -> CRM-WG-NW-Butterfly-Black | C48: =IFERROR(__xludf.DUMMYFUNCTION("""COMPUTED_VALUE"""),8.0) -> 8 | F48: =SUMIF(A:A,E48,C:C) -> 0 | G48: =XLOOKUP(E48,K:K,Q:Q) -> #N/A | H48: =G48-F48 -> #N/A | K48: =IFERROR(__xludf.DUMMYFUNCTION("""COMPUTED_VALUE"""),"HP 750 (Black)") -> HP 750 (Black) | M48: =IFERROR(__xludf.DUMMYFUNCTION("""COMPUTED_VALUE"""),"Printer NW") -> Printer NW | N48: =IFERROR(__xludf.DUMMYFUNCTION("""COMPUTED_VALUE"""),"AG") -> AG | O48: =IFERROR(__xludf.DUMMYFUNCTION("""COMPUTED_VALUE"""),-6.0) -> -6 | P48: =IFERROR(__xludf.DUMMYFUNCTION("""COMPUTED_VALUE"""),10.0) -> 10 | Q48: =IFERROR(__xludf.DUMMYFUNCTION("""COMPUTED_VALUE"""),16.0) -> 16 | R48: =IFERROR(__xludf.DUMMYFUNCTION("""COMPUTED_VALUE"""),5.0) -> 5 | S48: =IFERROR(__xludf.DUMMYFUNCTION("""COMPUTED_VALUE"""),9.0) -> 9 | T48: =IFERROR(__xludf.DUMMYFUNCTION("""COMPUTED_VALUE"""),18.0) -> 18 | U48: =IFERROR(__xludf.DUMMYFUNCTION("""COMPUTED_VALUE"""),0.0) -> 0 | V48: =IFERROR(__xludf.DUMMYFUNCTION("""COMPUTED_VALUE"""),0.0) -> 0 | W48: =IFERROR(__xludf.DUMMYFUNCTION("""COMPUTED_VALUE"""),5.0) -> 5 | X48: =IFERROR(__xludf.DUMMYFUNCTION("""COMPUTED_VALUE"""),5.0) -> 5 | Y48: =IFERROR(__xludf.DUMMYFUNCTION("""COMPUTED_VALUE"""),20.0) -> 20 | AB48: =IFERROR(__xludf.DUMMYFUNCTION("""COMPUTED_VALUE"""),1.5) -> 1.5
A49: =IFERROR(__xludf.DUMMYFUNCTION("""COMPUTED_VALUE"""),"Bajaj (Black)") -> Bajaj (Black) | B49: =IFERROR(__xludf.DUMMYFUNCTION("""COMPUTED_VALUE"""),"CRM-WG-NW-Butterfly-Black") -> CRM-WG-NW-Butterfly-Black | C49: =IFERROR(__xludf.DUMMYFUNCTION("""COMPUTED_VALUE"""),4.0) -> 4 | F49: =SUMIF(A:A,E49,C:C) -> 0 | G49: =XLOOKUP(E49,K:K,Q:Q) -> #N/A | H49: =G49-F49 -> #N/A | K49: =IFERROR(__xludf.DUMMYFUNCTION("""COMPUTED_VALUE"""),"HP 670 (Black)") -> HP 670 (Black) | M49: =IFERROR(__xludf.DUMMYFUNCTION("""COMPUTED_VALUE"""),"Printer NW") -> Printer NW | N49: =IFERROR(__xludf.DUMMYFUNCTION("""COMPUTED_VALUE"""),"AG") -> AG | O49: =IFERROR(__xludf.DUMMYFUNCTION("""COMPUTED_VALUE"""),-20.0) -> -20 | P49: =IFERROR(__xludf.DUMMYFUNCTION("""COMPUTED_VALUE"""),176.0) -> 176 | Q49: =IFERROR(__xludf.DUMMYFUNCTION("""COMPUTED_VALUE"""),196.0) -> 196 | R49: =IFERROR(__xludf.DUMMYFUNCTION("""COMPUTED_VALUE"""),5.0) -> 5 | S49: =IFERROR(__xludf.DUMMYFUNCTION("""COMPUTED_VALUE"""),15.0) -> 15 | T49: =IFERROR(__xludf.DUMMYFUNCTION("""COMPUTED_VALUE"""),53.0) -> 53 | U49: =IFERROR(__xludf.DUMMYFUNCTION("""COMPUTED_VALUE"""),74.0) -> 74 | V49: =IFERROR(__xludf.DUMMYFUNCTION("""COMPUTED_VALUE"""),170.0) -> 170 | W49: =IFERROR(__xludf.DUMMYFUNCTION("""COMPUTED_VALUE"""),273.0) -> 273 | X49: =IFERROR(__xludf.DUMMYFUNCTION("""COMPUTED_VALUE"""),128.0) -> 128 | Y49: =IFERROR(__xludf.DUMMYFUNCTION("""COMPUTED_VALUE"""),323.0) -> 323 | AB49: =IFERROR(__xludf.DUMMYFUNCTION("""COMPUTED_VALUE"""),1.5) -> 1.5
A50: =IFERROR(__xludf.DUMMYFUNCTION("""COMPUTED_VALUE"""),"Bajaj (Black)") -> Bajaj (Black) | B50: =IFERROR(__xludf.DUMMYFUNCTION("""COMPUTED_VALUE"""),"CRM-WG-NW-Butterfly-Black") -> CRM-WG-NW-Butterfly-Black | C50: =IFERROR(__xludf.DUMMYFUNCTION("""COMPUTED_VALUE"""),12.0) -> 12 | F50: =SUMIF(A:A,E50,C:C) -> 0 | G50: =XLOOKUP(E50,K:K,Q:Q) -> #N/A | H50: =G50-F50 -> #N/A | K50: =IFERROR(__xludf.DUMMYFUNCTION("""COMPUTED_VALUE"""),"HP 4826 (Black)") -> HP 4826 (Black) | M50: =IFERROR(__xludf.DUMMYFUNCTION("""COMPUTED_VALUE"""),"Printer NW") -> Printer NW | N50: =IFERROR(__xludf.DUMMYFUNCTION("""COMPUTED_VALUE"""),"AG") -> AG | O50: =IFERROR(__xludf.DUMMYFUNCTION("""COMPUTED_VALUE"""),-87.0) -> -87 | P50: =IFERROR(__xludf.DUMMYFUNCTION("""COMPUTED_VALUE"""),59.0) -> 59 | Q50: =IFERROR(__xludf.DUMMYFUNCTION("""COMPUTED_VALUE"""),146.0) -> 146 | R50: =IFERROR(__xludf.DUMMYFUNCTION("""COMPUTED_VALUE"""),5.0) -> 5 | S50: =IFERROR(__xludf.DUMMYFUNCTION("""COMPUTED_VALUE"""),39.0) -> 39 | T50: =IFERROR(__xludf.DUMMYFUNCTION("""COMPUTED_VALUE"""),34.0) -> 34 | U50: =IFERROR(__xludf.DUMMYFUNCTION("""COMPUTED_VALUE"""),34.0) -> 34 | V50: =IFERROR(__xludf.DUMMYFUNCTION("""COMPUTED_VALUE"""),16.0) -> 16 | W50: =IFERROR(__xludf.DUMMYFUNCTION("""COMPUTED_VALUE"""),73.0) -> 73 | X50: =IFERROR(__xludf.DUMMYFUNCTION("""COMPUTED_VALUE"""),38.0) -> 38 | Y50: =IFERROR(__xludf.DUMMYFUNCTION("""COMPUTED_VALUE"""),17.0) -> 17 | AB50: =IFERROR(__xludf.DUMMYFUNCTION("""COMPUTED_VALUE"""),1.5) -> 1.5
A51: =IFERROR(__xludf.DUMMYFUNCTION("""COMPUTED_VALUE"""),"Bajaj (Black)") -> Bajaj (Black) | B51: =IFERROR(__xludf.DUMMYFUNCTION("""COMPUTED_VALUE"""),"CRM-WG-NW-Butterfly-Black") -> CRM-WG-NW-Butterfly-Black | C51: =IFERROR(__xludf.DUMMYFUNCTION("""COMPUTED_VALUE"""),2.0) -> 2 | F51: =SUMIF(A:A,E51,C:C) -> 0 | G51: =XLOOKUP(E51,K:K,Q:Q) -> #N/A | H51: =G51-F51 -> #N/A | K51: =IFERROR(__xludf.DUMMYFUNCTION("""COMPUTED_VALUE"""),"HP 580 (Grey)") -> HP 580 (Grey) | M51: =IFERROR(__xludf.DUMMYFUNCTION("""COMPUTED_VALUE"""),"Printer NW") -> Printer NW | N51: =IFERROR(__xludf.DUMMYFUNCTION("""COMPUTED_VALUE"""),"AG") -> AG | O51: =IFERROR(__xludf.DUMMYFUNCTION("""COMPUTED_VALUE"""),-294.0) -> -294 | P51: =IFERROR(__xludf.DUMMYFUNCTION("""COMPUTED_VALUE"""),643.0) -> 643 | Q51: =IFERROR(__xludf.DUMMYFUNCTION("""COMPUTED_VALUE"""),937.0) -> 937 | R51: =IFERROR(__xludf.DUMMYFUNCTION("""COMPUTED_VALUE"""),5.0) -> 5 | S51: =IFERROR(__xludf.DUMMYFUNCTION("""COMPUTED_VALUE"""),177.0) -> 177 | T51: =IFERROR(__xludf.DUMMYFUNCTION("""COMPUTED_VALUE"""),182.0) -> 182 | U51: =IFERROR(__xludf.DUMMYFUNCTION("""COMPUTED_VALUE"""),316.0) -> 316 | V51: =IFERROR(__xludf.DUMMYFUNCTION("""COMPUTED_VALUE"""),498.0) -> 498 | W51: =IFERROR(__xludf.DUMMYFUNCTION("""COMPUTED_VALUE"""),968.0) -> 968 | X51: =IFERROR(__xludf.DUMMYFUNCTION("""COMPUTED_VALUE"""),283.0) -> 283 | Y51: =IFERROR(__xludf.DUMMYFUNCTION("""COMPUTED_VALUE"""),460.0) -> 460 | AB51: =IFERROR(__xludf.DUMMYFUNCTION("""COMPUTED_VALUE"""),1.5) -> 1.5
A52: =IFERROR(__xludf.DUMMYFUNCTION("""COMPUTED_VALUE"""),"Bajaj (Black)") -> Bajaj (Black) | B52: =IFERROR(__xludf.DUMMYFUNCTION("""COMPUTED_VALUE"""),"CRM-WG-NW-Butterfly-Black") -> CRM-WG-NW-Butterfly-Black | C52: =IFERROR(__xludf.DUMMYFUNCTION("""COMPUTED_VALUE"""),4.0) -> 4 | F52: =SUMIF(A:A,E52,C:C) -> 0 | G52: =XLOOKUP(E52,K:K,Q:Q) -> #N/A | H52: =G52-F52 -> #N/A | K52: =IFERROR(__xludf.DUMMYFUNCTION("""COMPUTED_VALUE"""),"HP 136NW (Grey)") -> HP 136NW (Grey) | M52: =IFERROR(__xludf.DUMMYFUNCTION("""COMPUTED_VALUE"""),"Printer NW") -> Printer NW | N52: =IFERROR(__xludf.DUMMYFUNCTION("""COMPUTED_VALUE"""),"AG") -> AG | O52: =IFERROR(__xludf.DUMMYFUNCTION("""COMPUTED_VALUE"""),20.0) -> 20 | P52: =IFERROR(__xludf.DUMMYFUNCTION("""COMPUTED_VALUE"""),62.0) -> 62 | Q52: =IFERROR(__xludf.DUMMYFUNCTION("""COMPUTED_VALUE"""),42.0) -> 42 | R52: =IFERROR(__xludf.DUMMYFUNCTION("""COMPUTED_VALUE"""),5.0) -> 5 | S52: =IFERROR(__xludf.DUMMYFUNCTION("""COMPUTED_VALUE"""),87.0) -> 87 | T52: =IFERROR(__xludf.DUMMYFUNCTION("""COMPUTED_VALUE"""),12.0) -> 12 | U52: =IFERROR(__xludf.DUMMYFUNCTION("""COMPUTED_VALUE"""),16.0) -> 16 | V52: =IFERROR(__xludf.DUMMYFUNCTION("""COMPUTED_VALUE"""),19.0) -> 19 | W52: =IFERROR(__xludf.DUMMYFUNCTION("""COMPUTED_VALUE"""),70.0) -> 70 | X52: =IFERROR(__xludf.DUMMYFUNCTION("""COMPUTED_VALUE"""),56.0) -> 56 | Y52: =IFERROR(__xludf.DUMMYFUNCTION("""COMPUTED_VALUE"""),98.0) -> 98 | AB52: =IFERROR(__xludf.DUMMYFUNCTION("""COMPUTED_VALUE"""),1.5) -> 1.5
A53: =IFERROR(__xludf.DUMMYFUNCTION("""COMPUTED_VALUE"""),"Bajaj (Black)") -> Bajaj (Black) | B53: =IFERROR(__xludf.DUMMYFUNCTION("""COMPUTED_VALUE"""),"CRM-WG-NW-Butterfly-Black") -> CRM-WG-NW-Butterfly-Black | C53: =IFERROR(__xludf.DUMMYFUNCTION("""COMPUTED_VALUE"""),4.0) -> 4 | F53: =SUMIF(A:A,E53,C:C) -> 0 | G53: =XLOOKUP(E53,K:K,Q:Q) -> #N/A | H53: =G53-F53 -> #N/A | K53: =IFERROR(__xludf.DUMMYFUNCTION("""COMPUTED_VALUE"""),"HP 750 (Grey)") -> HP 750 (Grey) | M53: =IFERROR(__xludf.DUMMYFUNCTION("""COMPUTED_VALUE"""),"Printer NW") -> Printer NW | N53: =IFERROR(__xludf.DUMMYFUNCTION("""COMPUTED_VALUE"""),"AG") -> AG | O53: =IFERROR(__xludf.DUMMYFUNCTION("""COMPUTED_VALUE"""),-48.0) -> -48 | P53: =IFERROR(__xludf.DUMMYFUNCTION("""COMPUTED_VALUE"""),38.0) -> 38 | Q53: =IFERROR(__xludf.DUMMYFUNCTION("""COMPUTED_VALUE"""),86.0) -> 86 | R53: =IFERROR(__xludf.DUMMYFUNCTION("""COMPUTED_VALUE"""),5.0) -> 5 | S53: =IFERROR(__xludf.DUMMYFUNCTION("""COMPUTED_VALUE"""),44.0) -> 44 | T53: =IFERROR(__xludf.DUMMYFUNCTION("""COMPUTED_VALUE"""),2.0) -> 2 | U53: =IFERROR(__xludf.DUMMYFUNCTION("""COMPUTED_VALUE"""),27.0) -> 27 | V53: =IFERROR(__xludf.DUMMYFUNCTION("""COMPUTED_VALUE"""),18.0) -> 18 | W53: =IFERROR(__xludf.DUMMYFUNCTION("""COMPUTED_VALUE"""),34.0) -> 34 | X53: =IFERROR(__xludf.DUMMYFUNCTION("""COMPUTED_VALUE"""),21.0) -> 21 | Y53: =IFERROR(__xludf.DUMMYFUNCTION("""COMPUTED_VALUE"""),107.0) -> 107 | AB53: =IFERROR(__xludf.DUMMYFUNCTION("""COMPUTED_VALUE"""),1.5) -> 1.5
